Workbook

Sheet Draft HQ
A1: AMERESCO'S BEST — 2026 DRAFT HQ v2
A2: Live value signal • exposure alerts • tier scarcity • rival threat • phase strategy • next-entry guidance
A4: LIVE ROOM CONTROL | D4: CURRENT NOMINATION - SELECT FROM DROPDOWN | H4: POSITION BUDGET | L4: STRONGEST RIVAL
A5: Starting budget | B5: 200 | D5: Player | H5: Position | I5: Plan | J5: Actual | K5: Variance | L5: Team | M5: =INDEX('Team Tracker'!$A$6:$A$18,MATCH(MAX('Team Tracker'!$G$6:$G$18),'Team Tracker'!$G$6:$G$18,0)) -> RD
A6: My spend | B6: =SUMIF('Auction Log'!$D$5:$D$304,"ME",'Auction Log'!$E$5:$E$304) -> 0 | D6: Value vs Market | E6: =IFERROR(INDEX('Player Board'!$B$5:$B$304,MATCH(E5,'Player Board'!$A$5:$A$304,0)),"") | F6: Signal | G6: =IFERROR(INDEX('Player Board'!$C$5:$C$304,MATCH(E5,'Player Board'!$A$5:$A$304,0)),"") | H6: QB | I6: 9 | J6: =SUMIFS('Auction Log'!$E$5:$E$304,'Auction Log'!$D$5:$D$304,"ME",'Auction Log'!$C$5:$C$304,H6) -> 0 | K6: =I6-J6 -> 9 | L6: Max bid | M6: =MAX('Team Tracker'!$G$6:$G$18) -> 186
A7: Budget left | B7: =B5-B6 -> 200 | D7: Market | E7: =IFERROR(INDEX('Player Board'!$N$5:$N$304,MATCH(E5,'Player Board'!$A$5:$A$304,0)),"") | F7: Target | G7: =IFERROR(INDEX('Player Board'!$S$5:$S$304,MATCH(E5,'Player Board'!$A$5:$A$304,0)),"") | H7: RB | I7: 90 | J7: =SUMIFS('Auction Log'!$E$5:$E$304,'Auction Log'!$D$5:$D$304,"ME",'Auction Log'!$C$5:$C$304,H7) -> 0 | K7: =I7-J7 -> 90 | L7: Slots left | M7: =INDEX('Team Tracker'!$F$6:$F$18,MATCH(M5,'Team Tracker'!$A$6:$A$18,0)) -> 15
A8: Players won | B8: =COUNTIF('Auction Log'!$D$5:$D$304,"ME") -> 0 | D8: Stop price | E8: =IFERROR(INDEX('Player Board'!$R$5:$R$304,MATCH(E5,'Player Board'!$A$5:$A$304,0)),"") | F8: SAFE BID | G8: =IF(E5="","",IF(E9<>"Available",0,MIN($B$10,ROUND(E8*$B$13,0)))) | H8: WR | I8: 88 | J8: =SUMIFS('Auction Log'!$E$5:$E$304,'Auction Log'!$D$5:$D$304,"ME",'Auction Log'!$C$5:$C$304,H8) -> 0 | K8: =I8-J8 -> 88 | L8: Need to drain | M8: =INDEX('Team Tracker'!$N$6:$N$18,MATCH(M5,'Team Tracker'!$A$6:$A$18,0)) -> RB
A9: Slots left | B9: =15-B8 -> 15 | D9: Status | E9: =IFERROR(INDEX('Player Board'!$D$5:$D$304,MATCH(E5,'Player Board'!$A$5:$A$304,0)),"") | F9: Nomination | G9: =IFERROR(INDEX('Player Board'!$T$5:$T$304,MATCH(E5,'Player Board'!$A$5:$A$304,0)),"") | H9: TE | I9: 11 | J9: =SUMIFS('Auction Log'!$E$5:$E$304,'Auction Log'!$D$5:$D$304,"ME",'Auction Log'!$C$5:$C$304,H9) -> 0 | K9: =I9-J9 -> 11 | L9: Threat | M9: =IF(M6>50,"HIGH",IF(M6>25,"MODERATE","LOW")) -> HIGH
A10: Legal max bid | B10: =IF(B9=0,0,B7-B9+1) -> 186 | D10: Injury / news | E10: =IFERROR(INDEX('Player Board'!$U$5:$U$304,MATCH(E5,'Player Board'!$A$5:$A$304,0)),"") | H10: D/ST | I10: 1 | J10: =SUMIFS('Auction Log'!$E$5:$E$304,'Auction Log'!$D$5:$D$304,"ME",'Auction Log'!$C$5:$C$304,H10) -> 0 | K10: =I10-J10 -> 1 | L10: Action | M10: ="Nominate "&M8&" to drain cash" -> Nominate RB to drain cash
A11: Room dollars left | B11: =SUM('Team Tracker'!$D$5:$D$18) -> 2800 | H11: K | I11: 1 | J11: =SUMIFS('Auction Log'!$E$5:$E$304,'Auction Log'!$D$5:$D$304,"ME",'Auction Log'!$C$5:$C$304,H11) -> 0 | K11: =I11-J11 -> 1
A12: Pool value left | B12: =SUMIFS('Player Board'!$R$5:$R$304,'Player Board'!$D$5:$D$304,"Available",'Player Board'!$W$5:$W$304,"YES") -> 2800 | D12: =IF(E5="","SELECT CURRENT NOMINATION FROM DROPDOWN",IF(E9<>"Available","SOLD - select next nomination",IF(E6>=5,"SMASH BUY - bid assertively up to SAFE BID",IF(E6>=2,"BUY - Target or below",IF(E6>=-1,"NEUTRAL - only at Target",IF(E6>=-4,"AVOID - demand a discount","DO NOT BID")))))) -> SELECT CURRENT NOMINATION FROM DROPDOWN
A13: Inflation | B13: =IFERROR(B11/B12,1) -> 1
A14: DRAFT PROGRESS | D14: DYNAMIC GAME FLOW | H14: POSITION HEALTH & REMAINING NEEDS
A15: Nominations completed | B15: =COUNTIF('Auction Log'!$B$5:$B$304,"<>") -> 0 | D15: Phase status | E15: =IF(B15=0,"READY",B17&" — "&B15&" nominations logged") -> READY | H15: Position | I15: Owned | J15: Target | K15: Needed | L15: Status
A16: Estimated time left | B16: =MAX(0,(210-B15)*0.83/1440) -> 0.12104167 | D16: Market state | E16: =IF(B13>1.1,"HEATING UP",IF(B13>=1,"NEUTRAL","DEFLATING")) -> NEUTRAL | H16: QB | I16: ='Team Tracker'!H5 -> 0 | J16: 1 | K16: =MAX(0,J16-I16) -> 1 | L16: =IF(I16>=J16,"SET",IF($B$15>=60,"CRITICAL — fill now","NEED "&K16)) -> NEED 1
A17: Current phase | B17: =IF(B15<=20,"OPENING",IF(B15<=90,"MIDDLE",IF(B15<150,"LATE","ENDGAME"))) -> OPENING | D17: Recommended | E17: =IF(B13>1.1,"Room underspent; remaining prices are rising. Buy scarce targets before tiers close.",IF(B13>=1,"Neutral market. Buy at Target or below with confidence.","Room overspent; remaining players are deflating. Stay patient and obey SAFE BID.")) -> Neutral market. Buy at Target or below with confidence. | H17: RB | I17: ='Team Tracker'!I5 -> 0 | J17: 5 | K17: =MAX(0,J17-I17) -> 5 | L17: =IF(I17>=5,"SET",IF(AND($B$15>=60,I17<4),"CRITICAL — need "&K17,IF(AND($B$15>=30,I17<3),"HIGH ALERT — need "&K17,"NEED "&K17))) -> NEED 5
A18: Last sale | B18: =IF(B15=0,"—",INDEX('Auction Log'!$B$5:$B$304,MATCH(B15,'Auction Log'!$A$5:$A$304,0))) -> — | H18: WR | I18: ='Team Tracker'!J5 -> 0 | J18: 5 | K18: =MAX(0,J18-I18) -> 5 | L18: =IF(I18>=5,"SET",IF(AND($B$15>=60,I18<4),"CRITICAL — need "&K18,IF(AND($B$15>=30,I18<3),"HIGH ALERT — need "&K18,"NEED "&K18))) -> NEED 5
H19: TE | I19: ='Team Tracker'!K5 -> 0 | J19: 1 | K19: =MAX(0,J19-I19) -> 1 | L19: =IF(I19>=1,"SET",IF($B$15>=90,"HIGH ALERT","NEED 1")) -> NEED 1
H20: D/ST | I20: ='Team Tracker'!L5 -> 0 | J20: 1 | K20: =MAX(0,J20-I20) -> 1 | L20: =IF(I20>=1,"SET",IF($B$15<150,"WAIT — reserve $1","NEED 1 NOW")) -> WAIT — reserve $1
H21: K | I21: ='Team Tracker'!M5 -> 0 | J21: 1 | K21: =MAX(0,J21-I21) -> 1 | L21: =IF(I21>=1,"SET",IF($B$15<150,"WAIT — reserve $1","NEED 1 NOW")) -> WAIT — reserve $1
H22: =IF(AND($B$15>=60,I17<4),"RB DEPTH CRITICAL — prioritize the next value RB",IF(AND($B$15>=30,I17<3),"RB DEPTH HIGH ALERT — need volume",IF(AND($B$15>=60,I18<4),"WR DEPTH CRITICAL — prioritize the next value WR",IF(AND($B$15>=30,I18<3),"WR DEPTH HIGH ALERT — need targets","POSITION HEALTH ON TRACK")))) -> POSITION HEALTH ON TRACK
A24: STAR TRACKER — TOP AVAILABLE BY VALUE TIER | G24: ENDGAME MUST-HAVES
A25: Tier | B25: Ceiling band | C25: Left | D25: Top three available | G25: Player | H25: Pos | I25: Target | J25: Max | K25: Status | L25: Sold | M25: Action
A26: TIER 1 | B26: $55+ | C26: =COUNTIFS('Player Board'!$R$5:$R$304,">=55",'Player Board'!$D$5:$D$304,"Available") -> 7 | D26: =IF(C26=0,"—",IFERROR(INDEX('Player Board'!$A$5:$A$304,SMALL('Player Board'!$X$5:$X$304,1)-4),"")&IF(C26>1,CHAR(10)&IFERROR(INDEX('Player Board'!$A$5:$A$304,SMALL('Player Board'!$X$5:$X$304,2)-4),""),"")&IF(C26>2,CHAR(10)&IFERROR(INDEX('Player Board'!$A$5:$A$304,SMALL('Player Board'!$X$5:$X$304,3)-4),""),"")) -> Jahmyr Gibbs Ja'Marr Chase Bijan Robinson | G26: Matthew Stafford | H26: =IFERROR(INDEX('Player Board'!$G$5:$G$304,MATCH(G26,'Player Board'!$A$5:$A$304,0)),"") -> QB | I26: =IFERROR(INDEX('Player Board'!$S$5:$S$304,MATCH(G26,'Player Board'!$A$5:$A$304,0)),"") -> 8 | J26: =IFERROR(INDEX('Player Board'!$R$5:$R$304,MATCH(G26,'Player Board'!$A$5:$A$304,0)),"") -> 10 | K26: =IFERROR(INDEX('Player Board'!$D$5:$D$304,MATCH(G26,'Player Board'!$A$5:$A$304,0)),"") -> Available | L26: =IFERROR(INDEX('Player Board'!$E$5:$E$304,MATCH(G26,'Player Board'!$A$5:$A$304,0)),"") | M26: =IF(K26="","NOT ON BOARD",IF(K26="Available","WATCH",IF(L26<>"","SOLD $"&L26,"GONE"))) -> WATCH
A27: TIER 2 | B27: $40–$54 | C27: =COUNTIFS('Player Board'!$R$5:$R$304,">=40",'Player Board'!$R$5:$R$304,"<55",'Player Board'!$D$5:$D$304,"Available") -> 7 | D27: =IF(C27=0,"—",IFERROR(INDEX('Player Board'!$A$5:$A$304,SMALL('Player Board'!$Y$5:$Y$304,1)-4),"")&IF(C27>1,CHAR(10)&IFERROR(INDEX('Player Board'!$A$5:$A$304,SMALL('Player Board'!$Y$5:$Y$304,2)-4),""),"")&IF(C27>2,CHAR(10)&IFERROR(INDEX('Player Board'!$A$5:$A$304,SMALL('Player Board'!$Y$5:$Y$304,3)-4),""),"")) -> Jonathan Taylor CeeDee Lamb Drake London | G27: Wan'Dale Robinson | H27: =IFERROR(INDEX('Player Board'!$G$5:$G$304,MATCH(G27,'Player Board'!$A$5:$A$304,0)),"") -> WR | I27: =IFERROR(INDEX('Player Board'!$S$5:$S$304,MATCH(G27,'Player Board'!$A$5:$A$304,0)),"") -> 8 | J27: =IFERROR(INDEX('Player Board'!$R$5:$R$304,MATCH(G27,'Player Board'!$A$5:$A$304,0)),"") -> 9 | K27: =IFERROR(INDEX('Player Board'!$D$5:$D$304,MATCH(G27,'Player Board'!$A$5:$A$304,0)),"") -> Available | L27: =IFERROR(INDEX('Player Board'!$E$5:$E$304,MATCH(G27,'Player Board'!$A$5:$A$304,0)),"") | M27: =IF(K27="","NOT ON BOARD",IF(K27="Available","WATCH",IF(L27<>"","SOLD $"&L27,"GONE"))) -> WATCH
A28: TIER 3 | B28: $25–$39 | C28: =COUNTIFS('Player Board'!$R$5:$R$304,">=25",'Player Board'!$R$5:$R$304,"<40",'Player Board'!$D$5:$D$304,"Available") -> 27 | D28: =IF(C28=0,"—",IFERROR(INDEX('Player Board'!$A$5:$A$304,SMALL('Player Board'!$Z$5:$Z$304,1)-4),"")&IF(C28>1,CHAR(10)&IFERROR(INDEX('Player Board'!$A$5:$A$304,SMALL('Player Board'!$Z$5:$Z$304,2)-4),""),"")&IF(C28>2,CHAR(10)&IFERROR(INDEX('Player Board'!$A$5:$A$304,SMALL('Player Board'!$Z$5:$Z$304,3)-4),""),"")) -> Chase Brown Chris Olave A.J. Brown | G28: Michael Wilson | H28: =IFERROR(INDEX('Player Board'!$G$5:$G$304,MATCH(G28,'Player Board'!$A$5:$A$304,0)),"") -> WR | I28: =IFERROR(INDEX('Player Board'!$S$5:$S$304,MATCH(G28,'Player Board'!$A$5:$A$304,0)),"") -> 8 | J28: =IFERROR(INDEX('Player Board'!$R$5:$R$304,MATCH(G28,'Player Board'!$A$5:$A$304,0)),"") -> 9 | K28: =IFERROR(INDEX('Player Board'!$D$5:$D$304,MATCH(G28,'Player Board'!$A$5:$A$304,0)),"") -> Available | L28: =IFERROR(INDEX('Player Board'!$E$5:$E$304,MATCH(G28,'Player Board'!$A$5:$A$304,0)),"") | M28: =IF(K28="","NOT ON BOARD",IF(K28="Available","WATCH",IF(L28<>"","SOLD $"&L28,"GONE"))) -> WATCH
G29: Kyle Pitts Sr. | H29: =IFERROR(INDEX('Player Board'!$G$5:$G$304,MATCH(G29,'Player Board'!$A$5:$A$304,0)),"") -> TE | I29: =IFERROR(INDEX('Player Board'!$S$5:$S$304,MATCH(G29,'Player Board'!$A$5:$A$304,0)),"") -> 12 | J29: =IFERROR(INDEX('Player Board'!$R$5:$R$304,MATCH(G29,'Player Board'!$A$5:$A$304,0)),"") -> 14 | K29: =IFERROR(INDEX('Player Board'!$D$5:$D$304,MATCH(G29,'Player Board'!$A$5:$A$304,0)),"") -> Available | L29: =IFERROR(INDEX('Player Board'!$E$5:$E$304,MATCH(G29,'Player Board'!$A$5:$A$304,0)),"") | M29: =IF(K29="","NOT ON BOARD",IF(K29="Available","WATCH",IF(L29<>"","SOLD $"&L29,"GONE"))) -> WATCH
G30: David Montgomery | H30: =IFERROR(INDEX('Player Board'!$G$5:$G$304,MATCH(G30,'Player Board'!$A$5:$A$304,0)),"") -> RB | I30: =IFERROR(INDEX('Player Board'!$S$5:$S$304,MATCH(G30,'Player Board'!$A$5:$A$304,0)),"") -> 13 | J30: =IFERROR(INDEX('Player Board'!$R$5:$R$304,MATCH(G30,'Player Board'!$A$5:$A$304,0)),"") -> 15 | K30: =IFERROR(INDEX('Player Board'!$D$5:$D$304,MATCH(G30,'Player Board'!$A$5:$A$304,0)),"") -> Available | L30: =IFERROR(INDEX('Player Board'!$E$5:$E$304,MATCH(G30,'Player Board'!$A$5:$A$304,0)),"") | M30: =IF(K30="","NOT ON BOARD",IF(K30="Available","WATCH",IF(L30<>"","SOLD $"&L30,"GONE"))) -> WATCH
G31: =IFERROR(INDEX(G26:G30,MATCH("Available",K26:K30,0))&" is still available — current adjusted max $"&MIN($B$10,ROUND(INDEX(J26:J30,MATCH("Available",K26:K30,0))*$B$13,0)),"All listed endgame targets are gone.") -> Matthew Stafford is still available — current adjusted max $10
A33: QUICK ENTRY & RECOVERY — MACRO-FREE
A34: Next entry row | B34: =COUNTIF('Auction Log'!$B$5:$B$304,"<>")+5 -> 5 | D34: ="GO TO AUCTION LOG — enter the next sale in bright-green row "&B34 -> GO TO AUCTION LOG — enter the next sale in bright-green row 5
A35: Undo last sale | B35: =IF(B15=0,"Nothing to undo.","Clear Player, Winner, Price, Roster Slot and Note in Auction Log row "&(B15+4)&".") -> Nothing to undo.
A36: Refresh / reset | B36: Refresh: Ctrl+Alt+F9. Reset: select Auction Log input columns B, D:F and I from row 5 down, then press Delete.

Sheet Player Board
A1: CUSTOM 2026 PLAYER BOARD — VALUE FIRST
A2: LIVE FILTERS: Availability + Position + Signal. Player and Value columns stay frozen while scrolling.
A4: Player | B4: V vs Mkt | C4: Signal | D4: Owner | E4: Sold | F4: Team | G4: Pos | H4: Bye | I4: ECR | J4: Tier | K4: FP Proj | L4: Clay PPR | M4: ESPN 10T $ | N4: 14T Market | O4: Consensus $ | P4: Bonus $ | Q4: Injury $ | R4: Hard Ceiling | S4: Target | T4: Nominate | U4: Injury / News | V4: Sale Value | W4: Pool
A5: Jahmyr Gibbs | B5: =R5-N5 -> 7 | C5: =IF(B5>=5,"SMASH BUY",IF(B5>=2,"BUY",IF(B5>=-1,"NEUTRAL",IF(B5>=-4,"AVOID","DO NOT BID")))) -> SMASH BUY | D5: =IF(COUNTIFS('Auction Log'!$B$5:$B$304,A5,'Auction Log'!$D$5:$D$304,"<>",'Auction Log'!$E$5:$E$304,">0")=0,"Available",IFERROR(INDEX('Auction Log'!$D$5:$D$304,MATCH(1,('Auction Log'!$B$5:$B$304=A5)*('Auction Log'!$D$5:$D$304<>"")*('Auction Log'!$E$5:$E$304>0),0)),"SOLD")) -> Available | E5: =IF(COUNTIFS('Auction Log'!$B$5:$B$304,A5,'Auction Log'!$D$5:$D$304,"<>",'Auction Log'!$E$5:$E$304,">0")=0,"",IFERROR(INDEX('Auction Log'!$E$5:$E$304,MATCH(1,('Auction Log'!$B$5:$B$304=A5)*('Auction Log'!$D$5:$D$304<>"")*('Auction Log'!$E$5:$E$304>0),0)),"")) | F5: DET | G5: RB | H5: 6 | I5: 2 | J5: 1 | K5: 373 | L5: 365 | M5: 57 | N5: 59 | O5: 0 | P5: 3 | Q5: 0 | R5: 66 | S5: 62 | T5: TARGET | V5: =IF(E5="","",R5-E5) | W5: YES | X5: =IF(AND(D5="Available",R5>=55),ROW(),9999) -> 5 | Y5: =IF(AND(D5="Available",R5>=40,R5<55),ROW(),9999) -> 9999 | Z5: =IF(AND(D5="Available",R5>=25,R5<40),ROW(),9999) -> 9999 | AA5: =IF(K5="","",IF(L5="",K5,ROUND(AVERAGE(K5,L5),0))) -> 369
A6: Ja'Marr Chase | B6: =R6-N6 -> 7 | C6: =IF(B6>=5,"SMASH BUY",IF(B6>=2,"BUY",IF(B6>=-1,"NEUTRAL",IF(B6>=-4,"AVOID","DO NOT BID")))) -> SMASH BUY | D6: =IF(COUNTIFS('Auction Log'!$B$5:$B$304,A6,'Auction Log'!$D$5:$D$304,"<>",'Auction Log'!$E$5:$E$304,">0")=0,"Available",IFERROR(INDEX('Auction Log'!$D$5:$D$304,MATCH(1,('Auction Log'!$B$5:$B$304=A6)*('Auction Log'!$D$5:$D$304<>"")*('Auction Log'!$E$5:$E$304>0),0)),"SOLD")) -> Available | E6: =IF(COUNTIFS('Auction Log'!$B$5:$B$304,A6,'Auction Log'!$D$5:$D$304,"<>",'Auction Log'!$E$5:$E$304,">0")=0,"",IFERROR(INDEX('Auction Log'!$E$5:$E$304,MATCH(1,('Auction Log'!$B$5:$B$304=A6)*('Auction Log'!$D$5:$D$304<>"")*('Auction Log'!$E$5:$E$304>0),0)),"")) | F6: CIN | G6: WR | H6: 6 | I6: 1 | J6: 1 | K6: 336 | L6: 337 | M6: 56 | N6: 58 | O6: 0 | P6: 3 | Q6: 0 | R6: 65 | S6: 61 | T6: TARGET | V6: =IF(E6="","",R6-E6) | W6: YES | X6: =IF(AND(D6="Available",R6>=55),ROW(),9999) -> 6 | Y6: =IF(AND(D6="Available",R6>=40,R6<55),ROW(),9999) -> 9999 | Z6: =IF(AND(D6="Available",R6>=25,R6<40),ROW(),9999) -> 9999 | AA6: =IF(K6="","",IF(L6="",K6,ROUND(AVERAGE(K6,L6),0))) -> 337
A7: Bijan Robinson | B7: =R7-N7 -> 7 | C7: =IF(B7>=5,"SMASH BUY",IF(B7>=2,"BUY",IF(B7>=-1,"NEUTRAL",IF(B7>=-4,"AVOID","DO NOT BID")))) -> SMASH BUY | D7: =IF(COUNTIFS('Auction Log'!$B$5:$B$304,A7,'Auction Log'!$D$5:$D$304,"<>",'Auction Log'!$E$5:$E$304,">0")=0,"Available",IFERROR(INDEX('Auction Log'!$D$5:$D$304,MATCH(1,('Auction Log'!$B$5:$B$304=A7)*('Auction Log'!$D$5:$D$304<>"")*('Auction Log'!$E$5:$E$304>0),0)),"SOLD")) -> Available | E7: =IF(COUNTIFS('Auction Log'!$B$5:$B$304,A7,'Auction Log'!$D$5:$D$304,"<>",'Auction Log'!$E$5:$E$304,">0")=0,"",IFERROR(INDEX('Auction Log'!$E$5:$E$304,MATCH(1,('Auction Log'!$B$5:$B$304=A7)*('Auction Log'!$D$5:$D$304<>"")*('Auction Log'!$E$5:$E$304>0),0)),"")) | F7: ATL | G7: RB | H7: 11 | I7: 4 | J7: 1 | K7: 369 | L7: 353 | M7: 56 | N7: 58 | O7: 0 | P7: 3 | Q7: 0 | R7: 65 | S7: 61 | T7: TARGET | V7: =IF(E7="","",R7-E7) | W7: YES | X7: =IF(AND(D7="Available",R7>=55),ROW(),9999) -> 7 | Y7: =IF(AND(D7="Available",R7>=40,R7<55),ROW(),9999) -> 9999 | Z7: =IF(AND(D7="Available",R7>=25,R7<40),ROW(),9999) -> 9999 | AA7: =IF(K7="","",IF(L7="",K7,ROUND(AVERAGE(K7,L7),0))) -> 361
A8: Jaxon Smith-Njigba | B8: =R8-N8 -> 8 | C8: =IF(B8>=5,"SMASH BUY",IF(B8>=2,"BUY",IF(B8>=-1,"NEUTRAL",IF(B8>=-4,"AVOID","DO NOT BID")))) -> SMASH BUY | D8: =IF(COUNTIFS('Auction Log'!$B$5:$B$304,A8,'Auction Log'!$D$5:$D$304,"<>",'Auction Log'!$E$5:$E$304,">0")=0,"Available",IFERROR(INDEX('Auction Log'!$D$5:$D$304,MATCH(1,('Auction Log'!$B$5:$B$304=A8)*('Auction Log'!$D$5:$D$304<>"")*('Auction Log'!$E$5:$E$304>0),0)),"SOLD")) -> Available | E8: =IF(COUNTIFS('Auction Log'!$B$5:$B$304,A8,'Auction Log'!$D$5:$D$304,"<>",'Auction Log'!$E$5:$E$304,">0")=0,"",IFERROR(INDEX('Auction Log'!$E$5:$E$304,MATCH(1,('Auction Log'!$B$5:$B$304=A8)*('Auction Log'!$D$5:$D$304<>"")*('Auction Log'!$E$5:$E$304>0),0)),"")) | F8: SEA | G8: WR | H8: 11 | I8: 5 | J8: 1 | K8: 326 | L8: 327 | M8: 54 | N8: 55 | O8: 0 | P8: 4 | Q8: 0 | R8: 63 | S8: 59 | T8: TARGET | V8: =IF(E8="","",R8-E8) | W8: YES | X8: =IF(AND(D8="Available",R8>=55),ROW(),9999) -> 8 | Y8: =IF(AND(D8="Available",R8>=40,R8<55),ROW(),9999) -> 9999 | Z8: =IF(AND(D8="Available",R8>=25,R8<40),ROW(),9999) -> 9999 | AA8: =IF(K8="","",IF(L8="",K8,ROUND(AVERAGE(K8,L8),0))) -> 327
A9: Puka Nacua | B9: =R9-N9 -> 3 | C9: =IF(B9>=5,"SMASH BUY",IF(B9>=2,"BUY",IF(B9>=-1,"NEUTRAL",IF(B9>=-4,"AVOID","DO NOT BID")))) -> BUY | D9: =IF(COUNTIFS('Auction Log'!$B$5:$B$304,A9,'Auction Log'!$D$5:$D$304,"<>",'Auction Log'!$E$5:$E$304,">0")=0,"Available",IFERROR(INDEX('Auction Log'!$D$5:$D$304,MATCH(1,('Auction Log'!$B$5:$B$304=A9)*('Auction Log'!$D$5:$D$304<>"")*('Auction Log'!$E$5:$E$304>0),0)),"SOLD")) -> Available | E9: =IF(COUNTIFS('Auction Log'!$B$5:$B$304,A9,'Auction Log'!$D$5:$D$304,"<>",'Auction Log'!$E$5:$E$304,">0")=0,"",IFERROR(INDEX('Auction Log'!$E$5:$E$304,MATCH(1,('Auction Log'!$B$5:$B$304=A9)*('Auction Log'!$D$5:$D$304<>"")*('Auction Log'!$E$5:$E$304>0),0)),"")) | F9: LAR | G9: WR | H9: 11 | I9: 3 | J9: 1 | K9: 340 | L9: 356 | M9: 55 | N9: 59 | O9: -1 | P9: 4 | Q9: 4 | R9: 62 | S9: 58 | T9: DRAIN | U9: Groin - still questionable; was not practicing as of 8/24 (ESPN 8/26). Discount only — no smash at full Target. | V9: =IF(E9="","",R9-E9) | W9: YES | X9: =IF(AND(D9="Available",R9>=55),ROW(),9999) -> 9 | Y9: =IF(AND(D9="Available",R9>=40,R9<55),ROW(),9999) -> 9999 | Z9: =IF(AND(D9="Available",R9>=25,R9<40),ROW(),9999) -> 9999 | AA9: =IF(K9="","",IF(L9="",K9,ROUND(AVERAGE(K9,L9),0))) -> 348
A10: Amon-Ra St. Brown | B10: =R10-N10 -> 7 | C10: =IF(B10>=5,"SMASH BUY",IF(B10>=2,"BUY",IF(B10>=-1,"NEUTRAL",IF(B10>=-4,"AVOID","DO NOT BID")))) -> SMASH BUY | D10: =IF(COUNTIFS('Auction Log'!$B$5:$B$304,A10,'Auction Log'!$D$5:$D$304,"<>",'Auction Log'!$E$5:$E$304,">0")=0,"Available",IFERROR(INDEX('Auction Log'!$D$5:$D$304,MATCH(1,('Auction Log'!$B$5:$B$304=A10)*('Auction Log'!$D$5:$D$304<>"")*('Auction Log'!$E$5:$E$304>0),0)),"SOLD")) -> Available | E10: =IF(COUNTIFS('Auction Log'!$B$5:$B$304,A10,'Auction Log'!$D$5:$D$304,"<>",'Auction Log'!$E$5:$E$304,">0")=0,"",IFERROR(INDEX('Auction Log'!$E$5:$E$304,MATCH(1,('Auction Log'!$B$5:$B$304=A10)*('Auction Log'!$D$5:$D$304<>"")*('Auction Log'!$E$5:$E$304>0),0)),"")) | F10: DET | G10: WR | H10: 6 | I10: 6 | J10: 1 | K10: 320 | L10: 324 | M10: 52 | N10: 53 | O10: 0 | P10: 3 | Q10: 0 | R10: 60 | S10: 56 | T10: TARGET | V10: =IF(E10="","",R10-E10) | W10: YES | X10: =IF(AND(D10="Available",R10>=55),ROW(),9999) -> 10 | Y10: =IF(AND(D10="Available",R10>=40,R10<55),ROW(),9999) -> 9999 | Z10: =IF(AND(D10="Available",R10>=25,R10<40),ROW(),9999) -> 9999 | AA10: =IF(K10="","",IF(L10="",K10,ROUND(AVERAGE(K10,L10),0))) -> 322
A11: Christian McCaffrey | B11: =R11-N11 -> 7 | C11: =IF(B11>=5,"SMASH BUY",IF(B11>=2,"BUY",IF(B11>=-1,"NEUTRAL",IF(B11>=-4,"AVOID","DO NOT BID")))) -> SMASH BUY | D11: =IF(COUNTIFS('Auction Log'!$B$5:$B$304,A11,'Auction Log'!$D$5:$D$304,"<>",'Auction Log'!$E$5:$E$304,">0")=0,"Available",IFERROR(INDEX('Auction Log'!$D$5:$D$304,MATCH(1,('Auction Log'!$B$5:$B$304=A11)*('Auction Log'!$D$5:$D$304<>"")*('Auction Log'!$E$5:$E$304>0),0)),"SOLD")) -> Available | E11: =IF(COUNTIFS('Auction Log'!$B$5:$B$304,A11,'Auction Log'!$D$5:$D$304,"<>",'Auction Log'!$E$5:$E$304,">0")=0,"",IFERROR(INDEX('Auction Log'!$E$5:$E$304,MATCH(1,('Auction Log'!$B$5:$B$304=A11)*('Auction Log'!$D$5:$D$304<>"")*('Auction Log'!$E$5:$E$304>0),0)),"")) | F11: SF | G11: RB | H11: 8 | I11: 9 | J11: 2 | K11: 335 | L11: 343 | M11: 53 | N11: 49 | O11: 1 | P11: 2 | Q11: 0 | R11: 56 | S11: 52 | T11: TARGET | V11: =IF(E11="","",R11-E11) | W11: YES | X11: =IF(AND(D11="Available",R11>=55),ROW(),9999) -> 11 | Y11: =IF(AND(D11="Available",R11>=40,R11<55),ROW(),9999) -> 9999 | Z11: =IF(AND(D11="Available",R11>=25,R11<40),ROW(),9999) -> 9999 | AA11: =IF(K11="","",IF(L11="",K11,ROUND(AVERAGE(K11,L11),0))) -> 339
A12: Jonathan Taylor | B12: =R12-N12 -> 8 | C12: =IF(B12>=5,"SMASH BUY",IF(B12>=2,"BUY",IF(B12>=-1,"NEUTRAL",IF(B12>=-4,"AVOID","DO NOT BID")))) -> SMASH BUY | D12: =IF(COUNTIFS('Auction Log'!$B$5:$B$304,A12,'Auction Log'!$D$5:$D$304,"<>",'Auction Log'!$E$5:$E$304,">0")=0,"Available",IFERROR(INDEX('Auction Log'!$D$5:$D$304,MATCH(1,('Auction Log'!$B$5:$B$304=A12)*('Auction Log'!$D$5:$D$304<>"")*('Auction Log'!$E$5:$E$304>0),0)),"SOLD")) -> Available | E12: =IF(COUNTIFS('Auction Log'!$B$5:$B$304,A12,'Auction Log'!$D$5:$D$304,"<>",'Auction Log'!$E$5:$E$304,">0")=0,"",IFERROR(INDEX('Auction Log'!$E$5:$E$304,MATCH(1,('Auction Log'!$B$5:$B$304=A12)*('Auction Log'!$D$5:$D$304<>"")*('Auction Log'!$E$5:$E$304>0),0)),"")) | F12: IND | G12: RB | H12: 13 | I12: 10 | J12: 2 | K12: 310 | L12: 316 | M12: 52 | N12: 43 | O12: 2 | P12: 3 | Q12: 0 | R12: 51 | S12: 47 | T12: TARGET | V12: =IF(E12="","",R12-E12) | W12: YES | X12: =IF(AND(D12="Available",R12>=55),ROW(),9999) -> 9999 | Y12: =IF(AND(D12="Available",R12>=40,R12<55),ROW(),9999) -> 12 | Z12: =IF(AND(D12="Available",R12>=25,R12<40),ROW(),9999) -> 9999 | AA12: =IF(K12="","",IF(L12="",K12,ROUND(AVERAGE(K12,L12),0))) -> 313
A13: CeeDee Lamb | B13: =R13-N13 -> 9 | C13: =IF(B13>=5,"SMASH BUY",IF(B13>=2,"BUY",IF(B13>=-1,"NEUTRAL",IF(B13>=-4,"AVOID","DO NOT BID")))) -> SMASH BUY | D13: =IF(COUNTIFS('Auction Log'!$B$5:$B$304,A13,'Auction Log'!$D$5:$D$304,"<>",'Auction Log'!$E$5:$E$304,">0")=0,"Available",IFERROR(INDEX('Auction Log'!$D$5:$D$304,MATCH(1,('Auction Log'!$B$5:$B$304=A13)*('Auction Log'!$D$5:$D$304<>"")*('Auction Log'!$E$5:$E$304>0),0)),"SOLD")) -> Available | E13: =IF(COUNTIFS('Auction Log'!$B$5:$B$304,A13,'Auction Log'!$D$5:$D$304,"<>",'Auction Log'!$E$5:$E$304,">0")=0,"",IFERROR(INDEX('Auction Log'!$E$5:$E$304,MATCH(1,('Auction Log'!$B$5:$B$304=A13)*('Auction Log'!$D$5:$D$304<>"")*('Auction Log'!$E$5:$E$304>0),0)),"")) | F13: DAL | G13: WR | H13: 14 | I13: 7 | J13: 2 | K13: 273 | L13: 293 | M13: 51 | N13: 39 | O13: 3 | P13: 3 | Q13: 0 | R13: 48 | S13: 44 | T13: TARGET | V13: =IF(E13="","",R13-E13) | W13: YES | X13: =IF(AND(D13="Available",R13>=55),ROW(),9999) -> 9999 | Y13: =IF(AND(D13="Available",R13>=40,R13<55),ROW(),9999) -> 13 | Z13: =IF(AND(D13="Available",R13>=25,R13<40),ROW(),9999) -> 9999 | AA13: =IF(K13="","",IF(L13="",K13,ROUND(AVERAGE(K13,L13),0))) -> 283
A14: Drake London | B14: =R14-N14 -> 5 | C14: =IF(B14>=5,"SMASH BUY",IF(B14>=2,"BUY",IF(B14>=-1,"NEUTRAL",IF(B14>=-4,"AVOID","DO NOT BID")))) -> SMASH BUY | D14: =IF(COUNTIFS('Auction Log'!$B$5:$B$304,A14,'Auction Log'!$D$5:$D$304,"<>",'Auction Log'!$E$5:$E$304,">0")=0,"Available",IFERROR(INDEX('Auction Log'!$D$5:$D$304,MATCH(1,('Auction Log'!$B$5:$B$304=A14)*('Auction Log'!$D$5:$D$304<>"")*('Auction Log'!$E$5:$E$304>0),0)),"SOLD")) -> Available | E14: =IF(COUNTIFS('Auction Log'!$B$5:$B$304,A14,'Auction Log'!$D$5:$D$304,"<>",'Auction Log'!$E$5:$E$304,">0")=0,"",IFERROR(INDEX('Auction Log'!$E$5:$E$304,MATCH(1,('Auction Log'!$B$5:$B$304=A14)*('Auction Log'!$D$5:$D$304<>"")*('Auction Log'!$E$5:$E$304>0),0)),"")) | F14: ATL | G14: WR | H14: 11 | I14: 11 | J14: 2 | K14: 287 | L14: 270 | M14: 43 | N14: 43 | O14: 0 | P14: 2 | Q14: 0 | R14: 48 | S14: 44 | T14: TARGET | V14: =IF(E14="","",R14-E14) | W14: YES | X14: =IF(AND(D14="Available",R14>=55),ROW(),9999) -> 9999 | Y14: =IF(AND(D14="Available",R14>=40,R14<55),ROW(),9999) -> 14 | Z14: =IF(AND(D14="Available",R14>=25,R14<40),ROW(),9999) -> 9999 | AA14: =IF(K14="","",IF(L14="",K14,ROUND(AVERAGE(K14,L14),0))) -> 279
A15: Justin Jefferson | B15: =R15-N15 -> 7 | C15: =IF(B15>=5,"SMASH BUY",IF(B15>=2,"BUY",IF(B15>=-1,"NEUTRAL",IF(B15>=-4,"AVOID","DO NOT BID")))) -> SMASH BUY | D15: =IF(COUNTIFS('Auction Log'!$B$5:$B$304,A15,'Auction Log'!$D$5:$D$304,"<>",'Auction Log'!$E$5:$E$304,">0")=0,"Available",IFERROR(INDEX('Auction Log'!$D$5:$D$304,MATCH(1,('Auction Log'!$B$5:$B$304=A15)*('Auction Log'!$D$5:$D$304<>"")*('Auction Log'!$E$5:$E$304>0),0)),"SOLD")) -> Available | E15: =IF(COUNTIFS('Auction Log'!$B$5:$B$304,A15,'Auction Log'!$D$5:$D$304,"<>",'Auction Log'!$E$5:$E$304,">0")=0,"",IFERROR(INDEX('Auction Log'!$E$5:$E$304,MATCH(1,('Auction Log'!$B$5:$B$304=A15)*('Auction Log'!$D$5:$D$304<>"")*('Auction Log'!$E$5:$E$304>0),0)),"")) | F15: MIN | G15: WR | H15: 6 | I15: 8 | J15: 2 | K15: 272 | L15: 294 | M15: 48 | N15: 39 | O15: 2 | P15: 2 | Q15: 0 | R15: 46 | S15: 42 | T15: TARGET | V15: =IF(E15="","",R15-E15) | W15: YES | X15: =IF(AND(D15="Available",R15>=55),ROW(),9999) -> 9999 | Y15: =IF(AND(D15="Available",R15>=40,R15<55),ROW(),9999) -> 15 | Z15: =IF(AND(D15="Available",R15>=25,R15<40),ROW(),9999) -> 9999 | AA15: =IF(K15="","",IF(L15="",K15,ROUND(AVERAGE(K15,L15),0))) -> 283
A16: De'Von Achane | B16: =R16-N16 -> 6 | C16: =IF(B16>=5,"SMASH BUY",IF(B16>=2,"BUY",IF(B16>=-1,"NEUTRAL",IF(B16>=-4,"AVOID","DO NOT BID")))) -> SMASH BUY | D16: =IF(COUNTIFS('Auction Log'!$B$5:$B$304,A16,'Auction Log'!$D$5:$D$304,"<>",'Auction Log'!$E$5:$E$304,">0")=0,"Available",IFERROR(INDEX('Auction Log'!$D$5:$D$304,MATCH(1,('Auction Log'!$B$5:$B$304=A16)*('Auction Log'!$D$5:$D$304<>"")*('Auction Log'!$E$5:$E$304>0),0)),"SOLD")) -> Available | E16: =IF(COUNTIFS('Auction Log'!$B$5:$B$304,A16,'Auction Log'!$D$5:$D$304,"<>",'Auction Log'!$E$5:$E$304,">0")=0,"",IFERROR(INDEX('Auction Log'!$E$5:$E$304,MATCH(1,('Auction Log'!$B$5:$B$304=A16)*('Auction Log'!$D$5:$D$304<>"")*('Auction Log'!$E$5:$E$304>0),0)),"")) | F16: MIA | G16: RB | H16: 6 | I16: 19 | J16: 3 | K16: 292 | L16: 293 | M16: 50 | N16: 39 | O16: 1 | P16: 2 | Q16: 0 | R16: 45 | S16: 41 | T16: TARGET | V16: =IF(E16="","",R16-E16) | W16: YES | X16: =IF(AND(D16="Available",R16>=55),ROW(),9999) -> 9999 | Y16: =IF(AND(D16="Available",R16>=40,R16<55),ROW(),9999) -> 16 | Z16: =IF(AND(D16="Available",R16>=25,R16<40),ROW(),9999) -> 9999 | AA16: =IF(K16="","",IF(L16="",K16,ROUND(AVERAGE(K16,L16),0))) -> 293
A17: James Cook III | B17: =R17-N17 -> 8 | C17: =IF(B17>=5,"SMASH BUY",IF(B17>=2,"BUY",IF(B17>=-1,"NEUTRAL",IF(B17>=-4,"AVOID","DO NOT BID")))) -> SMASH BUY | D17: =IF(COUNTIFS('Auction Log'!$B$5:$B$304,A17,'Auction Log'!$D$5:$D$304,"<>",'Auction Log'!$E$5:$E$304,">0")=0,"Available",IFERROR(INDEX('Auction Log'!$D$5:$D$304,MATCH(1,('Auction Log'!$B$5:$B$304=A17)*('Auction Log'!$D$5:$D$304<>"")*('Auction Log'!$E$5:$E$304>0),0)),"SOLD")) -> Available | E17: =IF(COUNTIFS('Auction Log'!$B$5:$B$304,A17,'Auction Log'!$D$5:$D$304,"<>",'Auction Log'!$E$5:$E$304,">0")=0,"",IFERROR(INDEX('Auction Log'!$E$5:$E$304,MATCH(1,('Auction Log'!$B$5:$B$304=A17)*('Auction Log'!$D$5:$D$304<>"")*('Auction Log'!$E$5:$E$304>0),0)),"")) | F17: BUF | G17: RB | H17: 7 | I17: 14 | J17: 3 | K17: 271 | L17: 280 | M17: 46 | N17: 34 | O17: 3 | P17: 3 | Q17: 0 | R17: 42 | S17: 39 | T17: TARGET | V17: =IF(E17="","",R17-E17) | W17: YES | X17: =IF(AND(D17="Available",R17>=55),ROW(),9999) -> 9999 | Y17: =IF(AND(D17="Available",R17>=40,R17<55),ROW(),9999) -> 17 | Z17: =IF(AND(D17="Available",R17>=25,R17<40),ROW(),9999) -> 9999 | AA17: =IF(K17="","",IF(L17="",K17,ROUND(AVERAGE(K17,L17),0))) -> 276
A18: Rashee Rice | B18: =R18-N18 -> 2 | C18: =IF(B18>=5,"SMASH BUY",IF(B18>=2,"BUY",IF(B18>=-1,"NEUTRAL",IF(B18>=-4,"AVOID","DO NOT BID")))) -> BUY | D18: =IF(COUNTIFS('Auction Log'!$B$5:$B$304,A18,'Auction Log'!$D$5:$D$304,"<>",'Auction Log'!$E$5:$E$304,">0")=0,"Available",IFERROR(INDEX('Auction Log'!$D$5:$D$304,MATCH(1,('Auction Log'!$B$5:$B$304=A18)*('Auction Log'!$D$5:$D$304<>"")*('Auction Log'!$E$5:$E$304>0),0)),"SOLD")) -> Available | E18: =IF(COUNTIFS('Auction Log'!$B$5:$B$304,A18,'Auction Log'!$D$5:$D$304,"<>",'Auction Log'!$E$5:$E$304,">0")=0,"",IFERROR(INDEX('Auction Log'!$E$5:$E$304,MATCH(1,('Auction Log'!$B$5:$B$304=A18)*('Auction Log'!$D$5:$D$304<>"")*('Auction Log'!$E$5:$E$304>0),0)),"")) | F18: KC | G18: WR | H18: 5 | I18: 21 | J18: 3 | K18: 274 | L18: 271 | M18: 40 | N18: 40 | O18: -1 | P18: 1 | Q18: 0 | R18: 42 | S18: 39 | T18: HOLD | V18: =IF(E18="","",R18-E18) | W18: YES | X18: =IF(AND(D18="Available",R18>=55),ROW(),9999) -> 9999 | Y18: =IF(AND(D18="Available",R18>=40,R18<55),ROW(),9999) -> 18 | Z18: =IF(AND(D18="Available",R18>=25,R18<40),ROW(),9999) -> 9999 | AA18: =IF(K18="","",IF(L18="",K18,ROUND(AVERAGE(K18,L18),0))) -> 273
A19: Chase Brown | B19: =R19-N19 -> 3 | C19: =IF(B19>=5,"SMASH BUY",IF(B19>=2,"BUY",IF(B19>=-1,"NEUTRAL",IF(B19>=-4,"AVOID","DO NOT BID")))) -> BUY | D19: =IF(COUNTIFS('Auction Log'!$B$5:$B$304,A19,'Auction Log'!$D$5:$D$304,"<>",'Auction Log'!$E$5:$E$304,">0")=0,"Available",IFERROR(INDEX('Auction Log'!$D$5:$D$304,MATCH(1,('Auction Log'!$B$5:$B$304=A19)*('Auction Log'!$D$5:$D$304<>"")*('Auction Log'!$E$5:$E$304>0),0)),"SOLD")) -> Available | E19: =IF(COUNTIFS('Auction Log'!$B$5:$B$304,A19,'Auction Log'!$D$5:$D$304,"<>",'Auction Log'!$E$5:$E$304,">0")=0,"",IFERROR(INDEX('Auction Log'!$E$5:$E$304,MATCH(1,('Auction Log'!$B$5:$B$304=A19)*('Auction Log'!$D$5:$D$304<>"")*('Auction Log'!$E$5:$E$304>0),0)),"")) | F19: CIN | G19: RB | H19: 6 | I19: 15 | J19: 3 | K19: 279 | L19: 272 | M19: 35 | N19: 36 | O19: 0 | P19: 1 | Q19: 0 | R19: 39 | S19: 36 | T19: HOLD | V19: =IF(E19="","",R19-E19) | W19: YES | X19: =IF(AND(D19="Available",R19>=55),ROW(),9999) -> 9999 | Y19: =IF(AND(D19="Available",R19>=40,R19<55),ROW(),9999) -> 9999 | Z19: =IF(AND(D19="Available",R19>=25,R19<40),ROW(),9999) -> 19 | AA19: =IF(K19="","",IF(L19="",K19,ROUND(AVERAGE(K19,L19),0))) -> 276
A20: Chris Olave | B20: =R20-N20 -> 3 | C20: =IF(B20>=5,"SMASH BUY",IF(B20>=2,"BUY",IF(B20>=-1,"NEUTRAL",IF(B20>=-4,"AVOID","DO NOT BID")))) -> BUY | D20: =IF(COUNTIFS('Auction Log'!$B$5:$B$304,A20,'Auction Log'!$D$5:$D$304,"<>",'Auction Log'!$E$5:$E$304,">0")=0,"Available",IFERROR(INDEX('Auction Log'!$D$5:$D$304,MATCH(1,('Auction Log'!$B$5:$B$304=A20)*('Auction Log'!$D$5:$D$304<>"")*('Auction Log'!$E$5:$E$304>0),0)),"SOLD")) -> Available | E20: =IF(COUNTIFS('Auction Log'!$B$5:$B$304,A20,'Auction Log'!$D$5:$D$304,"<>",'Auction Log'!$E$5:$E$304,">0")=0,"",IFERROR(INDEX('Auction Log'!$E$5:$E$304,MATCH(1,('Auction Log'!$B$5:$B$304=A20)*('Auction Log'!$D$5:$D$304<>"")*('Auction Log'!$E$5:$E$304>0),0)),"")) | F20: NO | G20: WR | H20: 8 | I20: 17 | J20: 3 | K20: 262 | L20: 250 | M20: 30 | N20: 36 | O20: -1 | P20: 2 | Q20: 0 | R20: 39 | S20: 36 | T20: HOLD | V20: =IF(E20="","",R20-E20) | W20: YES | X20: =IF(AND(D20="Available",R20>=55),ROW(),9999) -> 9999 | Y20: =IF(AND(D20="Available",R20>=40,R20<55),ROW(),9999) -> 9999 | Z20: =IF(AND(D20="Available",R20>=25,R20<40),ROW(),9999) -> 20 | AA20: =IF(K20="","",IF(L20="",K20,ROUND(AVERAGE(K20,L20),0))) -> 256
A21: A.J. Brown | B21: =R21-N21 -> 3 | C21: =IF(B21>=5,"SMASH BUY",IF(B21>=2,"BUY",IF(B21>=-1,"NEUTRAL",IF(B21>=-4,"AVOID","DO NOT BID")))) -> BUY | D21: =IF(COUNTIFS('Auction Log'!$B$5:$B$304,A21,'Auction Log'!$D$5:$D$304,"<>",'Auction Log'!$E$5:$E$304,">0")=0,"Available",IFERROR(INDEX('Auction Log'!$D$5:$D$304,MATCH(1,('Auction Log'!$B$5:$B$304=A21)*('Auction Log'!$D$5:$D$304<>"")*('Auction Log'!$E$5:$E$304>0),0)),"SOLD")) -> Available | E21: =IF(COUNTIFS('Auction Log'!$B$5:$B$304,A21,'Auction Log'!$D$5:$D$304,"<>",'Auction Log'!$E$5:$E$304,">0")=0,"",IFERROR(INDEX('Auction Log'!$E$5:$E$304,MATCH(1,('Auction Log'!$B$5:$B$304=A21)*('Auction Log'!$D$5:$D$304<>"")*('Auction Log'!$E$5:$E$304>0),0)),"")) | F21: NE | G21: WR | H21: 11 | I21: 12 | J21: 3 | K21: 256 | L21: 249 | M21: 29 | N21: 35 | O21: -1 | P21: 2 | Q21: 0 | R21: 38 | S21: 35 | T21: HOLD | V21: =IF(E21="","",R21-E21) | W21: YES | X21: =IF(AND(D21="Available",R21>=55),ROW(),9999) -> 9999 | Y21: =IF(AND(D21="Available",R21>=40,R21<55),ROW(),9999) -> 9999 | Z21: =IF(AND(D21="Available",R21>=25,R21<40),ROW(),9999) -> 21 | AA21: =IF(K21="","",IF(L21="",K21,ROUND(AVERAGE(K21,L21),0))) -> 253
... A29: Omarion Hampton | B29: =R29-N29 -> 4 | C29: =IF(B29>=5,"SMASH BUY",IF(B29>=2,"BUY",IF(B29>=-1,"NEUTRAL",IF(B29>=-4,"AVOID","DO NOT BID")))) -> BUY | D29: =IF(COUNTIFS('Auction Log'!$B$5:$B$304,A29,'Auction Log'!$D$5:$D$304,"<>",'Auction Log'!$E$5:$E$304,">0")=0,"Available",IFERROR(INDEX('Auction Log'!$D$5:$D$304,MATCH(1,('Auction Log'!$B$5:$B$304=A29)*('Auction Log'!$D$5:$D$304<>"")*('Auction Log'!$E$5:$E$304>0),0)),"SOLD")) -> Available | E29: =IF(COUNTIFS('Auction Log'!$B$5:$B$304,A29,'Auction Log'!$D$5:$D$304,"<>",'Auction Log'!$E$5:$E$304,">0")=0,"",IFERROR(INDEX('Auction Log'!$E$5:$E$304,MATCH(1,('Auction Log'!$B$5:$B$304=A29)*('Auction Log'!$D$5:$D$304<>"")*('Auction Log'!$E$5:$E$304>0),0)),"")) | F29: LAC | G29: RB | H29: 7 | I29: 25 | J29: 4 | K29: 254 | L29: 262 | M29: 33 | N29: 30 | O29: 1 | P29: 1 | Q29: 0 | R29: 34 | S29: 31 | T29: TARGET | V29: =IF(E29="","",R29-E29) | W29: YES | X29: =IF(AND(D29="Available",R29>=55),ROW(),9999) -> 9999 | Y29: =IF(AND(D29="Available",R29>=40,R29<55),ROW(),9999) -> 9999 | Z29: =IF(AND(D29="Available",R29>=25,R29<40),ROW(),9999) -> 29 | AA29: =IF(K29="","",IF(L29="",K29,ROUND(AVERAGE(K29,L29),0))) -> 258
A30: Ashton Jeanty | B30: =R30-N30 -> 2 | C30: =IF(B30>=5,"SMASH BUY",IF(B30>=2,"BUY",IF(B30>=-1,"NEUTRAL",IF(B30>=-4,"AVOID","DO NOT BID")))) -> BUY | D30: =IF(COUNTIFS('Auction Log'!$B$5:$B$304,A30,'Auction Log'!$D$5:$D$304,"<>",'Auction Log'!$E$5:$E$304,">0")=0,"Available",IFERROR(INDEX('Auction Log'!$D$5:$D$304,MATCH(1,('Auction Log'!$B$5:$B$304=A30)*('Auction Log'!$D$5:$D$304<>"")*('Auction Log'!$E$5:$E$304>0),0)),"SOLD")) -> Available | E30: =IF(COUNTIFS('Auction Log'!$B$5:$B$304,A30,'Auction Log'!$D$5:$D$304,"<>",'Auction Log'!$E$5:$E$304,">0")=0,"",IFERROR(INDEX('Auction Log'!$E$5:$E$304,MATCH(1,('Auction Log'!$B$5:$B$304=A30)*('Auction Log'!$D$5:$D$304<>"")*('Auction Log'!$E$5:$E$304>0),0)),"")) | F30: LV | G30: RB | H30: 13 | I30: 28 | J30: 4 | K30: 261 | L30: 281 | M30: 45 | N30: 32 | O30: 3 | P30: 1 | Q30: 4 | R30: 34 | S30: 31 | T30: DRAIN | U30: Ankle - Raiders optimistic 'more low than high' sprain, not long-term (Rapoport 8/25 via ESPN). Buyable near Target; not a healthy stud. | V30: =IF(E30="","",R30-E30) | W30: YES | X30: =IF(AND(D30="Available",R30>=55),ROW(),9999) -> 9999 | Y30: =IF(AND(D30="Available",R30>=40,R30<55),ROW(),9999) -> 9999 | Z30: =IF(AND(D30="Available",R30>=25,R30<40),ROW(),9999) -> 30 | AA30: =IF(K30="","",IF(L30="",K30,ROUND(AVERAGE(K30,L30),0))) -> 271
A31: Garrett Wilson | B31: =R31-N31 -> 3 | C31: =IF(B31>=5,"SMASH BUY",IF(B31>=2,"BUY",IF(B31>=-1,"NEUTRAL",IF(B31>=-4,"AVOID","DO NOT BID")))) -> BUY | D31: =IF(COUNTIFS('Auction Log'!$B$5:$B$304,A31,'Auction Log'!$D$5:$D$304,"<>",'Auction Log'!$E$5:$E$304,">0")=0,"Available",IFERROR(INDEX('Auction Log'!$D$5:$D$304,MATCH(1,('Auction Log'!$B$5:$B$304=A31)*('Auction Log'!$D$5:$D$304<>"")*('Auction Log'!$E$5:$E$304>0),0)),"SOLD")) -> Available | E31: =IF(COUNTIFS('Auction Log'!$B$5:$B$304,A31,'Auction Log'!$D$5:$D$304,"<>",'Auction Log'!$E$5:$E$304,">0")=0,"",IFERROR(INDEX('Auction Log'!$E$5:$E$304,MATCH(1,('Auction Log'!$B$5:$B$304=A31)*('Auction Log'!$D$5:$D$304<>"")*('Auction Log'!$E$5:$E$304>0),0)),"")) | F31: NYJ | G31: WR | H31: 13 | I31: 29 | J31: 4 | K31: 243 | L31: 250 | M31: 30 | N31: 31 | O31: 0 | P31: 1 | Q31: 0 | R31: 34 | S31: 31 | T31: HOLD | V31: =IF(E31="","",R31-E31) | W31: YES | X31: =IF(AND(D31="Available",R31>=55),ROW(),9999) -> 9999 | Y31: =IF(AND(D31="Available",R31>=40,R31<55),ROW(),9999) -> 9999 | Z31: =IF(AND(D31="Available",R31>=25,R31<40),ROW(),9999) -> 31 | AA31: =IF(K31="","",IF(L31="",K31,ROUND(AVERAGE(K31,L31),0))) -> 247
A32: Malik Nabers | B32: =R32-N32 -> 2 | C32: =IF(B32>=5,"SMASH BUY",IF(B32>=2,"BUY",IF(B32>=-1,"NEUTRAL",IF(B32>=-4,"AVOID","DO NOT BID")))) -> BUY | D32: =IF(COUNTIFS('Auction Log'!$B$5:$B$304,A32,'Auction Log'!$D$5:$D$304,"<>",'Auction Log'!$E$5:$E$304,">0")=0,"Available",IFERROR(INDEX('Auction Log'!$D$5:$D$304,MATCH(1,('Auction Log'!$B$5:$B$304=A32)*('Auction Log'!$D$5:$D$304<>"")*('Auction Log'!$E$5:$E$304>0),0)),"SOLD")) -> Available | E32: =IF(COUNTIFS('Auction Log'!$B$5:$B$304,A32,'Auction Log'!$D$5:$D$304,"<>",'Auction Log'!$E$5:$E$304,">0")=0,"",IFERROR(INDEX('Auction Log'!$E$5:$E$304,MATCH(1,('Auction Log'!$B$5:$B$304=A32)*('Auction Log'!$D$5:$D$304<>"")*('Auction Log'!$E$5:$E$304>0),0)),"")) | F32: NYG | G32: WR | H32: 8 | I32: 24 | J32: 4 | K32: 240 | L32: 246 | M32: 28 | N32: 30 | O32: 0 | P32: 1 | Q32: 1 | R32: 32 | S32: 29 | T32: HOLD | U32: Knee - still on limited/red-jersey path as of 8/23 (ESPN). Cap at Target; do not chase. | V32: =IF(E32="","",R32-E32) | W32: YES | X32: =IF(AND(D32="Available",R32>=55),ROW(),9999) -> 9999 | Y32: =IF(AND(D32="Available",R32>=40,R32<55),ROW(),9999) -> 9999 | Z32: =IF(AND(D32="Available",R32>=25,R32<40),ROW(),9999) -> 32 | AA32: =IF(K32="","",IF(L32="",K32,ROUND(AVERAGE(K32,L32),0))) -> 243
A33: Zay Flowers | B33: =R33-N33 -> 2 | C33: =IF(B33>=5,"SMASH BUY",IF(B33>=2,"BUY",IF(B33>=-1,"NEUTRAL",IF(B33>=-4,"AVOID","DO NOT BID")))) -> BUY | D33: =IF(COUNTIFS('Auction Log'!$B$5:$B$304,A33,'Auction Log'!$D$5:$D$304,"<>",'Auction Log'!$E$5:$E$304,">0")=0,"Available",IFERROR(INDEX('Auction Log'!$D$5:$D$304,MATCH(1,('Auction Log'!$B$5:$B$304=A33)*('Auction Log'!$D$5:$D$304<>"")*('Auction Log'!$E$5:$E$304>0),0)),"SOLD")) -> Available | E33: =IF(COUNTIFS('Auction Log'!$B$5:$B$304,A33,'Auction Log'!$D$5:$D$304,"<>",'Auction Log'!$E$5:$E$304,">0")=0,"",IFERROR(INDEX('Auction Log'!$E$5:$E$304,MATCH(1,('Auction Log'!$B$5:$B$304=A33)*('Auction Log'!$D$5:$D$304<>"")*('Auction Log'!$E$5:$E$304>0),0)),"")) | F33: BAL | G33: WR | H33: 13 | I33: 30 | J33: 4 | K33: 242 | L33: 239 | M33: 23 | N33: 30 | O33: -2 | P33: 2 | Q33: 0 | R33: 32 | S33: 29 | T33: HOLD | V33: =IF(E33="","",R33-E33) | W33: YES | X33: =IF(AND(D33="Available",R33>=55),ROW(),9999) -> 9999 | Y33: =IF(AND(D33="Available",R33>=40,R33<55),ROW(),9999) -> 9999 | Z33: =IF(AND(D33="Available",R33>=25,R33<40),ROW(),9999) -> 33 | AA33: =IF(K33="","",IF(L33="",K33,ROUND(AVERAGE(K33,L33),0))) -> 241
A34: DeVonta Smith | B34: =R34-N34 -> 1 | C34: =IF(B34>=5,"SMASH BUY",IF(B34>=2,"BUY",IF(B34>=-1,"NEUTRAL",IF(B34>=-4,"AVOID","DO NOT BID")))) -> NEUTRAL | D34: =IF(COUNTIFS('Auction Log'!$B$5:$B$304,A34,'Auction Log'!$D$5:$D$304,"<>",'Auction Log'!$E$5:$E$304,">0")=0,"Available",IFERROR(INDEX('Auction Log'!$D$5:$D$304,MATCH(1,('Auction Log'!$B$5:$B$304=A34)*('Auction Log'!$D$5:$D$304<>"")*('Auction Log'!$E$5:$E$304>0),0)),"SOLD")) -> Available | E34: =IF(COUNTIFS('Auction Log'!$B$5:$B$304,A34,'Auction Log'!$D$5:$D$304,"<>",'Auction Log'!$E$5:$E$304,">0")=0,"",IFERROR(INDEX('Auction Log'!$E$5:$E$304,MATCH(1,('Auction Log'!$B$5:$B$304=A34)*('Auction Log'!$D$5:$D$304<>"")*('Auction Log'!$E$5:$E$304>0),0)),"")) | F34: PHI | G34: WR | H34: 10 | I34: 22 | J34: 4 | K34: 237 | L34: 239 | M34: 22 | N34: 29 | O34: -1 | P34: 1 | Q34: 0 | R34: 30 | S34: 27 | T34: TARGET | V34: =IF(E34="","",R34-E34) | W34: YES | X34: =IF(AND(D34="Available",R34>=55),ROW(),9999) -> 9999 | Y34: =IF(AND(D34="Available",R34>=40,R34<55),ROW(),9999) -> 9999 | Z34: =IF(AND(D34="Available",R34>=25,R34<40),ROW(),9999) -> 34 | AA34: =IF(K34="","",IF(L34="",K34,ROUND(AVERAGE(K34,L34),0))) -> 238
A35: Josh Allen | B35: =R35-N35 -> 0 | C35: =IF(B35>=5,"SMASH BUY",IF(B35>=2,"BUY",IF(B35>=-1,"NEUTRAL",IF(B35>=-4,"AVOID","DO NOT BID")))) -> NEUTRAL | D35: =IF(COUNTIFS('Auction Log'!$B$5:$B$304,A35,'Auction Log'!$D$5:$D$304,"<>",'Auction Log'!$E$5:$E$304,">0")=0,"Available",IFERROR(INDEX('Auction Log'!$D$5:$D$304,MATCH(1,('Auction Log'!$B$5:$B$304=A35)*('Auction Log'!$D$5:$D$304<>"")*('Auction Log'!$E$5:$E$304>0),0)),"SOLD")) -> Available | E35: =IF(COUNTIFS('Auction Log'!$B$5:$B$304,A35,'Auction Log'!$D$5:$D$304,"<>",'Auction Log'!$E$5:$E$304,">0")=0,"",IFERROR(INDEX('Auction Log'!$E$5:$E$304,MATCH(1,('Auction Log'!$B$5:$B$304=A35)*('Auction Log'!$D$5:$D$304<>"")*('Auction Log'!$E$5:$E$304>0),0)),"")) | F35: BUF | G35: QB | H35: 7 | I35: 26 | J35: 4 | K35: 372 | L35: 369 | M35: 22 | N35: 30 | O35: -2 | P35: 1 | Q35: 0 | R35: 30 | S35: 27 | T35: HOLD | V35: =IF(E35="","",R35-E35) | W35: YES | X35: =IF(AND(D35="Available",R35>=55),ROW(),9999) -> 9999 | Y35: =IF(AND(D35="Available",R35>=40,R35<55),ROW(),9999) -> 9999 | Z35: =IF(AND(D35="Available",R35>=25,R35<40),ROW(),9999) -> 35 | AA35: =IF(K35="","",IF(L35="",K35,ROUND(AVERAGE(K35,L35),0))) -> 371
A36: Tetairoa McMillan | B36: =R36-N36 -> 2 | C36: =IF(B36>=5,"SMASH BUY",IF(B36>=2,"BUY",IF(B36>=-1,"NEUTRAL",IF(B36>=-4,"AVOID","DO NOT BID")))) -> BUY | D36: =IF(COUNTIFS('Auction Log'!$B$5:$B$304,A36,'Auction Log'!$D$5:$D$304,"<>",'Auction Log'!$E$5:$E$304,">0")=0,"Available",IFERROR(INDEX('Auction Log'!$D$5:$D$304,MATCH(1,('Auction Log'!$B$5:$B$304=A36)*('Auction Log'!$D$5:$D$304<>"")*('Auction Log'!$E$5:$E$304>0),0)),"SOLD")) -> Available | E36: =IF(COUNTIFS('Auction Log'!$B$5:$B$304,A36,'Auction Log'!$D$5:$D$304,"<>",'Auction Log'!$E$5:$E$304,">0")=0,"",IFERROR(INDEX('Auction Log'!$E$5:$E$304,MATCH(1,('Auction Log'!$B$5:$B$304=A36)*('Auction Log'!$D$5:$D$304<>"")*('Auction Log'!$E$5:$E$304>0),0)),"")) | F36: CAR | G36: WR | H36: 5 | I36: 32 | J36: 4 | K36: 234 | L36: 236 | M36: 24 | N36: 28 | O36: -1 | P36: 2 | Q36: 0 | R36: 30 | S36: 27 | T36: HOLD | V36: =IF(E36="","",R36-E36) | W36: YES | X36: =IF(AND(D36="Available",R36>=55),ROW(),9999) -> 9999 | Y36: =IF(AND(D36="Available",R36>=40,R36<55),ROW(),9999) -> 9999 | Z36: =IF(AND(D36="Available",R36>=25,R36<40),ROW(),9999) -> 36 | AA36: =IF(K36="","",IF(L36="",K36,ROUND(AVERAGE(K36,L36),0))) -> 235
A37: Josh Jacobs | B37: =R37-N37 -> 1 | C37: =IF(B37>=5,"SMASH BUY",IF(B37>=2,"BUY",IF(B37>=-1,"NEUTRAL",IF(B37>=-4,"AVOID","DO NOT BID")))) -> NEUTRAL | D37: =IF(COUNTIFS('Auction Log'!$B$5:$B$304,A37,'Auction Log'!$D$5:$D$304,"<>",'Auction Log'!$E$5:$E$304,">0")=0,"Available",IFERROR(INDEX('Auction Log'!$D$5:$D$304,MATCH(1,('Auction Log'!$B$5:$B$304=A37)*('Auction Log'!$D$5:$D$304<>"")*('Auction Log'!$E$5:$E$304>0),0)),"SOLD")) -> Available | E37: =IF(COUNTIFS('Auction Log'!$B$5:$B$304,A37,'Auction Log'!$D$5:$D$304,"<>",'Auction Log'!$E$5:$E$304,">0")=0,"",IFERROR(INDEX('Auction Log'!$E$5:$E$304,MATCH(1,('Auction Log'!$B$5:$B$304=A37)*('Auction Log'!$D$5:$D$304<>"")*('Auction Log'!$E$5:$E$304>0),0)),"")) | F37: GB | G37: RB | H37: 11 | I37: 43 | J37: 5 | K37: 249 | L37: 259 | M37: 27 | N37: 29 | O37: -1 | P37: 1 | Q37: 0 | R37: 30 | S37: 27 | T37: HOLD | V37: =IF(E37="","",R37-E37) | W37: YES | X37: =IF(AND(D37="Available",R37>=55),ROW(),9999) -> 9999 | Y37: =IF(AND(D37="Available",R37>=40,R37<55),ROW(),9999) -> 9999 | Z37: =IF(AND(D37="Available",R37>=25,R37<40),ROW(),9999) -> 37 | AA37: =IF(K37="","",IF(L37="",K37,ROUND(AVERAGE(K37,L37),0))) -> 254
A38: Jeremiyah Love | B38: =R38-N38 -> -1 | C38: =IF(B38>=5,"SMASH BUY",IF(B38>=2,"BUY",IF(B38>=-1,"NEUTRAL",IF(B38>=-4,"AVOID","DO NOT BID")))) -> NEUTRAL | D38: =IF(COUNTIFS('Auction Log'!$B$5:$B$304,A38,'Auction Log'!$D$5:$D$304,"<>",'Auction Log'!$E$5:$E$304,">0")=0,"Available",IFERROR(INDEX('Auction Log'!$D$5:$D$304,MATCH(1,('Auction Log'!$B$5:$B$304=A38)*('Auction Log'!$D$5:$D$304<>"")*('Auction Log'!$E$5:$E$304>0),0)),"SOLD")) -> Available | E38: =IF(COUNTIFS('Auction Log'!$B$5:$B$304,A38,'Auction Log'!$D$5:$D$304,"<>",'Auction Log'!$E$5:$E$304,">0")=0,"",IFERROR(INDEX('Auction Log'!$E$5:$E$304,MATCH(1,('Auction Log'!$B$5:$B$304=A38)*('Auction Log'!$D$5:$D$304<>"")*('Auction Log'!$E$5:$E$304>0),0)),"")) | F38: ARI | G38: RB | H38: 14 | I38: 41 | J38: 5 | K38: 255 | L38: 278 | M38: 42 | N38: 30 | O38: 2 | P38: 1 | Q38: 5 | R38: 29 | S38: 26 | T38: DRAIN | U38: High ankle - light agility only 8/26; est. return Sep 13 (ESPN). Week 1 risk real — fade unless steal. | V38: =IF(E38="","",R38-E38) | W38: YES | X38: =IF(AND(D38="Available",R38>=55),ROW(),9999) -> 9999 | Y38: =IF(AND(D38="Available",R38>=40,R38<55),ROW(),9999) -> 9999 | Z38: =IF(AND(D38="Available",R38>=25,R38<40),ROW(),9999) -> 38 | AA38: =IF(K38="","",IF(L38="",K38,ROUND(AVERAGE(K38,L38),0))) -> 267
A39: Breece Hall | B39: =R39-N39 -> 0 | C39: =IF(B39>=5,"SMASH BUY",IF(B39>=2,"BUY",IF(B39>=-1,"NEUTRAL",IF(B39>=-4,"AVOID","DO NOT BID")))) -> NEUTRAL | D39: =IF(COUNTIFS('Auction Log'!$B$5:$B$304,A39,'Auction Log'!$D$5:$D$304,"<>",'Auction Log'!$E$5:$E$304,">0")=0,"Available",IFERROR(INDEX('Auction Log'!$D$5:$D$304,MATCH(1,('Auction Log'!$B$5:$B$304=A39)*('Auction Log'!$D$5:$D$304<>"")*('Auction Log'!$E$5:$E$304>0),0)),"SOLD")) -> Available | E39: =IF(COUNTIFS('Auction Log'!$B$5:$B$304,A39,'Auction Log'!$D$5:$D$304,"<>",'Auction Log'!$E$5:$E$304,">0")=0,"",IFERROR(INDEX('Auction Log'!$E$5:$E$304,MATCH(1,('Auction Log'!$B$5:$B$304=A39)*('Auction Log'!$D$5:$D$304<>"")*('Auction Log'!$E$5:$E$304>0),0)),"")) | F39: NYJ | G39: RB | H39: 13 | I39: 39 | J39: 5 | K39: 245 | L39: 274 | M39: 32 | N39: 28 | O39: 1 | P39: 2 | Q39: 4 | R39: 28 | S39: 25 | T39: DRAIN | U39: Groin - side agility only 8/24; earlier 2–3 week miss outlook (ESPN). Discount only — early-season hole. | V39: =IF(E39="","",R39-E39) | W39: YES | X39: =IF(AND(D39="Available",R39>=55),ROW(),9999) -> 9999 | Y39: =IF(AND(D39="Available",R39>=40,R39<55),ROW(),9999) -> 9999 | Z39: =IF(AND(D39="Available",R39>=25,R39<40),ROW(),9999) -> 39 | AA39: =IF(K39="","",IF(L39="",K39,ROUND(AVERAGE(K39,L39),0))) -> 260
A40: Javonte Williams | B40: =R40-N40 -> 3 | C40: =IF(B40>=5,"SMASH BUY",IF(B40>=2,"BUY",IF(B40>=-1,"NEUTRAL",IF(B40>=-4,"AVOID","DO NOT BID")))) -> BUY | D40: =IF(COUNTIFS('Auction Log'!$B$5:$B$304,A40,'Auction Log'!$D$5:$D$304,"<>",'Auction Log'!$E$5:$E$304,">0")=0,"Available",IFERROR(INDEX('Auction Log'!$D$5:$D$304,MATCH(1,('Auction Log'!$B$5:$B$304=A40)*('Auction Log'!$D$5:$D$304<>"")*('Auction Log'!$E$5:$E$304>0),0)),"SOLD")) -> Available | E40: =IF(COUNTIFS('Auction Log'!$B$5:$B$304,A40,'Auction Log'!$D$5:$D$304,"<>",'Auction Log'!$E$5:$E$304,">0")=0,"",IFERROR(INDEX('Auction Log'!$E$5:$E$304,MATCH(1,('Auction Log'!$B$5:$B$304=A40)*('Auction Log'!$D$5:$D$304<>"")*('Auction Log'!$E$5:$E$304>0),0)),"")) | F40: DAL | G40: RB | H40: 14 | I40: 44 | J40: 5 | K40: 234 | L40: 259 | M40: 26 | N40: 25 | O40: 0 | P40: 2 | Q40: 0 | R40: 28 | S40: 25 | T40: TARGET | V40: =IF(E40="","",R40-E40) | W40: YES | X40: =IF(AND(D40="Available",R40>=55),ROW(),9999) -> 9999 | Y40: =IF(AND(D40="Available",R40>=40,R40<55),ROW(),9999) -> 9999 | Z40: =IF(AND(D40="Available",R40>=25,R40<40),ROW(),9999) -> 40 | AA40: =IF(K40="","",IF(L40="",K40,ROUND(AVERAGE(K40,L40),0))) -> 247
A41: Kyren Williams | B41: =R41-N41 -> 0 | C41: =IF(B41>=5,"SMASH BUY",IF(B41>=2,"BUY",IF(B41>=-1,"NEUTRAL",IF(B41>=-4,"AVOID","DO NOT BID")))) -> NEUTRAL | D41: =IF(COUNTIFS('Auction Log'!$B$5:$B$304,A41,'Auction Log'!$D$5:$D$304,"<>",'Auction Log'!$E$5:$E$304,">0")=0,"Available",IFERROR(INDEX('Auction Log'!$D$5:$D$304,MATCH(1,('Auction Log'!$B$5:$B$304=A41)*('Auction Log'!$D$5:$D$304<>"")*('Auction Log'!$E$5:$E$304>0),0)),"SOLD")) -> Available | E41: =IF(COUNTIFS('Auction Log'!$B$5:$B$304,A41,'Auction Log'!$D$5:$D$304,"<>",'Auction Log'!$E$5:$E$304,">0")=0,"",IFERROR(INDEX('Auction Log'!$E$5:$E$304,MATCH(1,('Auction Log'!$B$5:$B$304=A41)*('Auction Log'!$D$5:$D$304<>"")*('Auction Log'!$E$5:$E$304>0),0)),"")) | F41: LAR | G41: RB | H41: 11 | I41: 42 | J41: 5 | K41: 240 | L41: 232 | M41: 21 | N41: 27 | O41: -2 | P41: 1 | Q41: 0 | R41: 27 | S41: 24 | T41: HOLD | V41: =IF(E41="","",R41-E41) | W41: YES | X41: =IF(AND(D41="Available",R41>=55),ROW(),9999) -> 9999 | Y41: =IF(AND(D41="Available",R41>=40,R41<55),ROW(),9999) -> 9999 | Z41: =IF(AND(D41="Available",R41>=25,R41<40),ROW(),9999) -> 41 | AA41: =IF(K41="","",IF(L41="",K41,ROUND(AVERAGE(K41,L41),0))) -> 236
A42: Ladd McConkey | B42: =R42-N42 -> 1 | C42: =IF(B42>=5,"SMASH BUY",IF(B42>=2,"BUY",IF(B42>=-1,"NEUTRAL",IF(B42>=-4,"AVOID","DO NOT BID")))) -> NEUTRAL | D42: =IF(COUNTIFS('Auction Log'!$B$5:$B$304,A42,'Auction Log'!$D$5:$D$304,"<>",'Auction Log'!$E$5:$E$304,">0")=0,"Available",IFERROR(INDEX('Auction Log'!$D$5:$D$304,MATCH(1,('Auction Log'!$B$5:$B$304=A42)*('Auction Log'!$D$5:$D$304<>"")*('Auction Log'!$E$5:$E$304>0),0)),"SOLD")) -> Available | E42: =IF(COUNTIFS('Auction Log'!$B$5:$B$304,A42,'Auction Log'!$D$5:$D$304,"<>",'Auction Log'!$E$5:$E$304,">0")=0,"",IFERROR(INDEX('Auction Log'!$E$5:$E$304,MATCH(1,('Auction Log'!$B$5:$B$304=A42)*('Auction Log'!$D$5:$D$304<>"")*('Auction Log'!$E$5:$E$304>0),0)),"")) | F42: LAC | G42: WR | H42: 7 | I42: 34 | J42: 4 | K42: 220 | L42: 221 | M42: 17 | N42: 24 | O42: -1 | P42: 1 | Q42: 0 | R42: 25 | S42: 22 | T42: HOLD | V42: =IF(E42="","",R42-E42) | W42: YES | X42: =IF(AND(D42="Available",R42>=55),ROW(),9999) -> 9999 | Y42: =IF(AND(D42="Available",R42>=40,R42<55),ROW(),9999) -> 9999 | Z42: =IF(AND(D42="Available",R42>=25,R42<40),ROW(),9999) -> 42 | AA42: =IF(K42="","",IF(L42="",K42,ROUND(AVERAGE(K42,L42),0))) -> 221
A43: Tee Higgins | B43: =R43-N43 -> 0 | C43: =IF(B43>=5,"SMASH BUY",IF(B43>=2,"BUY",IF(B43>=-1,"NEUTRAL",IF(B43>=-4,"AVOID","DO NOT BID")))) -> NEUTRAL | D43: =IF(COUNTIFS('Auction Log'!$B$5:$B$304,A43,'Auction Log'!$D$5:$D$304,"<>",'Auction Log'!$E$5:$E$304,">0")=0,"Available",IFERROR(INDEX('Auction Log'!$D$5:$D$304,MATCH(1,('Auction Log'!$B$5:$B$304=A43)*('Auction Log'!$D$5:$D$304<>"")*('Auction Log'!$E$5:$E$304>0),0)),"SOLD")) -> Available | E43: =IF(COUNTIFS('Auction Log'!$B$5:$B$304,A43,'Auction Log'!$D$5:$D$304,"<>",'Auction Log'!$E$5:$E$304,">0")=0,"",IFERROR(INDEX('Auction Log'!$E$5:$E$304,MATCH(1,('Auction Log'!$B$5:$B$304=A43)*('Auction Log'!$D$5:$D$304<>"")*('Auction Log'!$E$5:$E$304>0),0)),"")) | F43: CIN | G43: WR | H43: 6 | I43: 35 | J43: 4 | K43: 222 | L43: 219 | M43: 15 | N43: 25 | O43: -2 | P43: 1 | Q43: 0 | R43: 25 | S43: 22 | T43: HOLD | V43: =IF(E43="","",R43-E43) | W43: YES | X43: =IF(AND(D43="Available",R43>=55),ROW(),9999) -> 9999 | Y43: =IF(AND(D43="Available",R43>=40,R43<55),ROW(),9999) -> 9999 | Z43: =IF(AND(D43="Available",R43>=25,R43<40),ROW(),9999) -> 43 | AA43: =IF(K43="","",IF(L43="",K43,ROUND(AVERAGE(K43,L43),0))) -> 221
A44: Travis Etienne Jr. | B44: =R44-N44 -> 0 | C44: =IF(B44>=5,"SMASH BUY",IF(B44>=2,"BUY",IF(B44>=-1,"NEUTRAL",IF(B44>=-4,"AVOID","DO NOT BID")))) -> NEUTRAL | D44: =IF(COUNTIFS('Auction Log'!$B$5:$B$304,A44,'Auction Log'!$D$5:$D$304,"<>",'Auction Log'!$E$5:$E$304,">0")=0,"Available",IFERROR(INDEX('Auction Log'!$D$5:$D$304,MATCH(1,('Auction Log'!$B$5:$B$304=A44)*('Auction Log'!$D$5:$D$304<>"")*('Auction Log'!$E$5:$E$304>0),0)),"SOLD")) -> Available | E44: =IF(COUNTIFS('Auction Log'!$B$5:$B$304,A44,'Auction Log'!$D$5:$D$304,"<>",'Auction Log'!$E$5:$E$304,">0")=0,"",IFERROR(INDEX('Auction Log'!$E$5:$E$304,MATCH(1,('Auction Log'!$B$5:$B$304=A44)*('Auction Log'!$D$5:$D$304<>"")*('Auction Log'!$E$5:$E$304>0),0)),"")) | F44: NO | G44: RB | H44: 8 | I44: 48 | J44: 5 | K44: 235 | L44: 246 | M44: 22 | N44: 25 | O44: -2 | P44: 1 | Q44: 0 | R44: 25 | S44: 22 | T44: HOLD | V44: =IF(E44="","",R44-E44) | W44: YES | X44: =IF(AND(D44="Available",R44>=55),ROW(),9999) -> 9999 | Y44: =IF(AND(D44="Available",R44>=40,R44<55),ROW(),9999) -> 9999 | Z44: =IF(AND(D44="Available",R44>=25,R44<40),ROW(),9999) -> 44 | AA44: =IF(K44="","",IF(L44="",K44,ROUND(AVERAGE(K44,L44),0))) -> 241
A45: Cam Skattebo | B45: =R45-N45 -> 0 | C45: =IF(B45>=5,"SMASH BUY",IF(B45>=2,"BUY",IF(B45>=-1,"NEUTRAL",IF(B45>=-4,"AVOID","DO NOT BID")))) -> NEUTRAL | D45: =IF(COUNTIFS('Auction Log'!$B$5:$B$304,A45,'Auction Log'!$D$5:$D$304,"<>",'Auction Log'!$E$5:$E$304,">0")=0,"Available",IFERROR(INDEX('Auction Log'!$D$5:$D$304,MATCH(1,('Auction Log'!$B$5:$B$304=A45)*('Auction Log'!$D$5:$D$304<>"")*('Auction Log'!$E$5:$E$304>0),0)),"SOLD")) -> Available | E45: =IF(COUNTIFS('Auction Log'!$B$5:$B$304,A45,'Auction Log'!$D$5:$D$304,"<>",'Auction Log'!$E$5:$E$304,">0")=0,"",IFERROR(INDEX('Auction Log'!$E$5:$E$304,MATCH(1,('Auction Log'!$B$5:$B$304=A45)*('Auction Log'!$D$5:$D$304<>"")*('Auction Log'!$E$5:$E$304>0),0)),"")) | F45: NYG | G45: RB | H45: 8 | I45: 56 | J45: 6 | K45: 235 | L45: 230 | M45: 20 | N45: 25 | O45: -2 | P45: 1 | Q45: 0 | R45: 25 | S45: 22 | T45: HOLD | V45: =IF(E45="","",R45-E45) | W45: YES | X45: =IF(AND(D45="Available",R45>=55),ROW(),9999) -> 9999 | Y45: =IF(AND(D45="Available",R45>=40,R45<55),ROW(),9999) -> 9999 | Z45: =IF(AND(D45="Available",R45>=25,R45<40),ROW(),9999) -> 45 | AA45: =IF(K45="","",IF(L45="",K45,ROUND(AVERAGE(K45,L45),0))) -> 233
A46: Davante Adams | B46: =R46-N46 -> -1 | C46: =IF(B46>=5,"SMASH BUY",IF(B46>=2,"BUY",IF(B46>=-1,"NEUTRAL",IF(B46>=-4,"AVOID","DO NOT BID")))) -> NEUTRAL | D46: =IF(COUNTIFS('Auction Log'!$B$5:$B$304,A46,'Auction Log'!$D$5:$D$304,"<>",'Auction Log'!$E$5:$E$304,">0")=0,"Available",IFERROR(INDEX('Auction Log'!$D$5:$D$304,MATCH(1,('Auction Log'!$B$5:$B$304=A46)*('Auction Log'!$D$5:$D$304<>"")*('Auction Log'!$E$5:$E$304>0),0)),"SOLD")) -> Available | E46: =IF(COUNTIFS('Auction Log'!$B$5:$B$304,A46,'Auction Log'!$D$5:$D$304,"<>",'Auction Log'!$E$5:$E$304,">0")=0,"",IFERROR(INDEX('Auction Log'!$E$5:$E$304,MATCH(1,('Auction Log'!$B$5:$B$304=A46)*('Auction Log'!$D$5:$D$304<>"")*('Auction Log'!$E$5:$E$304>0),0)),"")) | F46: LAR | G46: WR | H46: 11 | I46: 49 | J46: 5 | K46: 222 | L46: 232 | M46: 18 | N46: 25 | O46: -3 | P46: 1 | Q46: 0 | R46: 24 | S46: 22 | T46: DRAIN | V46: =IF(E46="","",R46-E46) | W46: YES | X46: =IF(AND(D46="Available",R46>=55),ROW(),9999) -> 9999 | Y46: =IF(AND(D46="Available",R46>=40,R46<55),ROW(),9999) -> 9999 | Z46: =IF(AND(D46="Available",R46>=25,R46<40),ROW(),9999) -> 9999 | AA46: =IF(K46="","",IF(L46="",K46,ROUND(AVERAGE(K46,L46),0))) -> 227
A47: Jaylen Waddle | B47: =R47-N47 -> 2 | C47: =IF(B47>=5,"SMASH BUY",IF(B47>=2,"BUY",IF(B47>=-1,"NEUTRAL",IF(B47>=-4,"AVOID","DO NOT BID")))) -> BUY | D47: =IF(COUNTIFS('Auction Log'!$B$5:$B$304,A47,'Auction Log'!$D$5:$D$304,"<>",'Auction Log'!$E$5:$E$304,">0")=0,"Available",IFERROR(INDEX('Auction Log'!$D$5:$D$304,MATCH(1,('Auction Log'!$B$5:$B$304=A47)*('Auction Log'!$D$5:$D$304<>"")*('Auction Log'!$E$5:$E$304>0),0)),"SOLD")) -> Available | E47: =IF(COUNTIFS('Auction Log'!$B$5:$B$304,A47,'Auction Log'!$D$5:$D$304,"<>",'Auction Log'!$E$5:$E$304,">0")=0,"",IFERROR(INDEX('Auction Log'!$E$5:$E$304,MATCH(1,('Auction Log'!$B$5:$B$304=A47)*('Auction Log'!$D$5:$D$304<>"")*('Auction Log'!$E$5:$E$304>0),0)),"")) | F47: DEN | G47: WR | H47: 10 | I47: 33 | J47: 4 | K47: 210 | L47: 213 | M47: 15 | N47: 21 | O47: 0 | P47: 1 | Q47: 0 | R47: 23 | S47: 21 | T47: TARGET | V47: =IF(E47="","",R47-E47) | W47: YES | X47: =IF(AND(D47="Available",R47>=55),ROW(),9999) -> 9999 | Y47: =IF(AND(D47="Available",R47>=40,R47<55),ROW(),9999) -> 9999 | Z47: =IF(AND(D47="Available",R47>=25,R47<40),ROW(),9999) -> 9999 | AA47: =IF(K47="","",IF(L47="",K47,ROUND(AVERAGE(K47,L47),0))) -> 212
A48: Emeka Egbuka | B48: =R48-N48 -> -3 | C48: =IF(B48>=5,"SMASH BUY",IF(B48>=2,"BUY",IF(B48>=-1,"NEUTRAL",IF(B48>=-4,"AVOID","DO NOT BID")))) -> AVOID | D48: =IF(COUNTIFS('Auction Log'!$B$5:$B$304,A48,'Auction Log'!$D$5:$D$304,"<>",'Auction Log'!$E$5:$E$304,">0")=0,"Available",IFERROR(INDEX('Auction Log'!$D$5:$D$304,MATCH(1,('Auction Log'!$B$5:$B$304=A48)*('Auction Log'!$D$5:$D$304<>"")*('Auction Log'!$E$5:$E$304>0),0)),"SOLD")) -> Available | E48: =IF(COUNTIFS('Auction Log'!$B$5:$B$304,A48,'Auction Log'!$D$5:$D$304,"<>",'Auction Log'!$E$5:$E$304,">0")=0,"",IFERROR(INDEX('Auction Log'!$E$5:$E$304,MATCH(1,('Auction Log'!$B$5:$B$304=A48)*('Auction Log'!$D$5:$D$304<>"")*('Auction Log'!$E$5:$E$304>0),0)),"")) | F48: TB | G48: WR | H48: 10 | I48: 40 | J48: 5 | K48: 228 | L48: 229 | M48: 19 | N48: 26 | O48: -2 | P48: 2 | Q48: 4 | R48: 23 | S48: 21 | T48: DRAIN | U48: Toe - not participating in practice as of 8/25 (ESPN). Soft pass / require big discount. | V48: =IF(E48="","",R48-E48) | W48: YES | X48: =IF(AND(D48="Available",R48>=55),ROW(),9999) -> 9999 | Y48: =IF(AND(D48="Available",R48>=40,R48<55),ROW(),9999) -> 9999 | Z48: =IF(AND(D48="Available",R48>=25,R48<40),ROW(),9999) -> 9999 | AA48: =IF(K48="","",IF(L48="",K48,ROUND(AVERAGE(K48,L48),0))) -> 229
A49: Bucky Irving | B49: =R49-N49 -> 0 | C49: =IF(B49>=5,"SMASH BUY",IF(B49>=2,"BUY",IF(B49>=-1,"NEUTRAL",IF(B49>=-4,"AVOID","DO NOT BID")))) -> NEUTRAL | D49: =IF(COUNTIFS('Auction Log'!$B$5:$B$304,A49,'Auction Log'!$D$5:$D$304,"<>",'Auction Log'!$E$5:$E$304,">0")=0,"Available",IFERROR(INDEX('Auction Log'!$D$5:$D$304,MATCH(1,('Auction Log'!$B$5:$B$304=A49)*('Auction Log'!$D$5:$D$304<>"")*('Auction Log'!$E$5:$E$304>0),0)),"SOLD")) -> Available | E49: =IF(COUNTIFS('Auction Log'!$B$5:$B$304,A49,'Auction Log'!$D$5:$D$304,"<>",'Auction Log'!$E$5:$E$304,">0")=0,"",IFERROR(INDEX('Auction Log'!$E$5:$E$304,MATCH(1,('Auction Log'!$B$5:$B$304=A49)*('Auction Log'!$D$5:$D$304<>"")*('Auction Log'!$E$5:$E$304>0),0)),"")) | F49: TB | G49: RB | H49: 10 | I49: 60 | J49: 6 | K49: 224 | L49: 207 | M49: 19 | N49: 23 | O49: -2 | P49: 1 | Q49: 0 | R49: 23 | S49: 21 | T49: HOLD | V49: =IF(E49="","",R49-E49) | W49: YES | X49: =IF(AND(D49="Available",R49>=55),ROW(),9999) -> 9999 | Y49: =IF(AND(D49="Available",R49>=40,R49<55),ROW(),9999) -> 9999 | Z49: =IF(AND(D49="Available",R49>=25,R49<40),ROW(),9999) -> 9999 | AA49: =IF(K49="","",IF(L49="",K49,ROUND(AVERAGE(K49,L49),0))) -> 216
A50: Terry McLaurin | B50: =R50-N50 -> 1 | C50: =IF(B50>=5,"SMASH BUY",IF(B50>=2,"BUY",IF(B50>=-1,"NEUTRAL",IF(B50>=-4,"AVOID","DO NOT BID")))) -> NEUTRAL | D50: =IF(COUNTIFS('Auction Log'!$B$5:$B$304,A50,'Auction Log'!$D$5:$D$304,"<>",'Auction Log'!$E$5:$E$304,">0")=0,"Available",IFERROR(INDEX('Auction Log'!$D$5:$D$304,MATCH(1,('Auction Log'!$B$5:$B$304=A50)*('Auction Log'!$D$5:$D$304<>"")*('Auction Log'!$E$5:$E$304>0),0)),"SOLD")) -> Available | E50: =IF(COUNTIFS('Auction Log'!$B$5:$B$304,A50,'Auction Log'!$D$5:$D$304,"<>",'Auction Log'!$E$5:$E$304,">0")=0,"",IFERROR(INDEX('Auction Log'!$E$5:$E$304,MATCH(1,('Auction Log'!$B$5:$B$304=A50)*('Auction Log'!$D$5:$D$304<>"")*('Auction Log'!$E$5:$E$304>0),0)),"")) | F50: WAS | G50: WR | H50: 7 | I50: 45 | J50: 5 | K50: 210 | L50: 219 | M50: 17 | N50: 21 | O50: -1 | P50: 1 | Q50: 0 | R50: 22 | S50: 20 | T50: HOLD | V50: =IF(E50="","",R50-E50) | W50: YES | X50: =IF(AND(D50="Available",R50>=55),ROW(),9999) -> 9999 | Y50: =IF(AND(D50="Available",R50>=40,R50<55),ROW(),9999) -> 9999 | Z50: =IF(AND(D50="Available",R50>=25,R50<40),ROW(),9999) -> 9999 | AA50: =IF(K50="","",IF(L50="",K50,ROUND(AVERAGE(K50,L50),0))) -> 215
A51: Jameson Williams | B51: =R51-N51 -> -1 | C51: =IF(B51>=5,"SMASH BUY",IF(B51>=2,"BUY",IF(B51>=-1,"NEUTRAL",IF(B51>=-4,"AVOID","DO NOT BID")))) -> NEUTRAL | D51: =IF(COUNTIFS('Auction Log'!$B$5:$B$304,A51,'Auction Log'!$D$5:$D$304,"<>",'Auction Log'!$E$5:$E$304,">0")=0,"Available",IFERROR(INDEX('Auction Log'!$D$5:$D$304,MATCH(1,('Auction Log'!$B$5:$B$304=A51)*('Auction Log'!$D$5:$D$304<>"")*('Auction Log'!$E$5:$E$304>0),0)),"SOLD")) -> Available | E51: =IF(COUNTIFS('Auction Log'!$B$5:$B$304,A51,'Auction Log'!$D$5:$D$304,"<>",'Auction Log'!$E$5:$E$304,">0")=0,"",IFERROR(INDEX('Auction Log'!$E$5:$E$304,MATCH(1,('Auction Log'!$B$5:$B$304=A51)*('Auction Log'!$D$5:$D$304<>"")*('Auction Log'!$E$5:$E$304>0),0)),"")) | F51: DET | G51: WR | H51: 6 | I51: 54 | J51: 6 | K51: 217 | L51: 208 | M51: 12 | N51: 23 | O51: -3 | P51: 1 | Q51: 0 | R51: 22 | S51: 20 | T51: HOLD | V51: =IF(E51="","",R51-E51) | W51: YES | X51: =IF(AND(D51="Available",R51>=55),ROW(),9999) -> 9999 | Y51: =IF(AND(D51="Available",R51>=40,R51<55),ROW(),9999) -> 9999 | Z51: =IF(AND(D51="Available",R51>=25,R51<40),ROW(),9999) -> 9999 | AA51: =IF(K51="","",IF(L51="",K51,ROUND(AVERAGE(K51,L51),0))) -> 213
A52: D'Andre Swift | B52: =R52-N52 -> -1 | C52: =IF(B52>=5,"SMASH BUY",IF(B52>=2,"BUY",IF(B52>=-1,"NEUTRAL",IF(B52>=-4,"AVOID","DO NOT BID")))) -> NEUTRAL | D52: =IF(COUNTIFS('Auction Log'!$B$5:$B$304,A52,'Auction Log'!$D$5:$D$304,"<>",'Auction Log'!$E$5:$E$304,">0")=0,"Available",IFERROR(INDEX('Auction Log'!$D$5:$D$304,MATCH(1,('Auction Log'!$B$5:$B$304=A52)*('Auction Log'!$D$5:$D$304<>"")*('Auction Log'!$E$5:$E$304>0),0)),"SOLD")) -> Available | E52: =IF(COUNTIFS('Auction Log'!$B$5:$B$304,A52,'Auction Log'!$D$5:$D$304,"<>",'Auction Log'!$E$5:$E$304,">0")=0,"",IFERROR(INDEX('Auction Log'!$E$5:$E$304,MATCH(1,('Auction Log'!$B$5:$B$304=A52)*('Auction Log'!$D$5:$D$304<>"")*('Auction Log'!$E$5:$E$304>0),0)),"")) | F52: CHI | G52: RB | H52: 10 | I52: 55 | J52: 6 | K52: 223 | L52: 212 | M52: 9 | N52: 23 | O52: -3 | P52: 1 | Q52: 0 | R52: 22 | S52: 20 | T52: HOLD | V52: =IF(E52="","",R52-E52) | W52: YES | X52: =IF(AND(D52="Available",R52>=55),ROW(),9999) -> 9999 | Y52: =IF(AND(D52="Available",R52>=40,R52<55),ROW(),9999) -> 9999 | Z52: =IF(AND(D52="Available",R52>=25,R52<40),ROW(),9999) -> 9999 | AA52: =IF(K52="","",IF(L52="",K52,ROUND(AVERAGE(K52,L52),0))) -> 218
A53: Colston Loveland | B53: =R53-N53 -> 1 | C53: =IF(B53>=5,"SMASH BUY",IF(B53>=2,"BUY",IF(B53>=-1,"NEUTRAL",IF(B53>=-4,"AVOID","DO NOT BID")))) -> NEUTRAL | D53: =IF(COUNTIFS('Auction Log'!$B$5:$B$304,A53,'Auction Log'!$D$5:$D$304,"<>",'Auction Log'!$E$5:$E$304,">0")=0,"Available",IFERROR(INDEX('Auction Log'!$D$5:$D$304,MATCH(1,('Auction Log'!$B$5:$B$304=A53)*('Auction Log'!$D$5:$D$304<>"")*('Auction Log'!$E$5:$E$304>0),0)),"SOLD")) -> Available | E53: =IF(COUNTIFS('Auction Log'!$B$5:$B$304,A53,'Auction Log'!$D$5:$D$304,"<>",'Auction Log'!$E$5:$E$304,">0")=0,"",IFERROR(INDEX('Auction Log'!$E$5:$E$304,MATCH(1,('Auction Log'!$B$5:$B$304=A53)*('Auction Log'!$D$5:$D$304<>"")*('Auction Log'!$E$5:$E$304>0),0)),"")) | F53: CHI | G53: TE | H53: 10 | I53: 37 | J53: 5 | K53: 211 | L53: 206 | M53: 13 | N53: 20 | O53: -1 | P53: 1 | Q53: 0 | R53: 21 | S53: 19 | T53: HOLD | V53: =IF(E53="","",R53-E53) | W53: YES | X53: =IF(AND(D53="Available",R53>=55),ROW(),9999) -> 9999 | Y53: =IF(AND(D53="Available",R53>=40,R53<55),ROW(),9999) -> 9999 | Z53: =IF(AND(D53="Available",R53>=25,R53<40),ROW(),9999) -> 9999 | AA53: =IF(K53="","",IF(L53="",K53,ROUND(AVERAGE(K53,L53),0))) -> 209
A54: DJ Moore | B54: =R54-N54 -> 0 | C54: =IF(B54>=5,"SMASH BUY",IF(B54>=2,"BUY",IF(B54>=-1,"NEUTRAL",IF(B54>=-4,"AVOID","DO NOT BID")))) -> NEUTRAL | D54: =IF(COUNTIFS('Auction Log'!$B$5:$B$304,A54,'Auction Log'!$D$5:$D$304,"<>",'Auction Log'!$E$5:$E$304,">0")=0,"Available",IFERROR(INDEX('Auction Log'!$D$5:$D$304,MATCH(1,('Auction Log'!$B$5:$B$304=A54)*('Auction Log'!$D$5:$D$304<>"")*('Auction Log'!$E$5:$E$304>0),0)),"SOLD")) -> Available | E54: =IF(COUNTIFS('Auction Log'!$B$5:$B$304,A54,'Auction Log'!$D$5:$D$304,"<>",'Auction Log'!$E$5:$E$304,">0")=0,"",IFERROR(INDEX('Auction Log'!$E$5:$E$304,MATCH(1,('Auction Log'!$B$5:$B$304=A54)*('Auction Log'!$D$5:$D$304<>"")*('Auction Log'!$E$5:$E$304>0),0)),"")) | F54: BUF | G54: WR | H54: 7 | I54: 51 | J54: 5 | K54: 208 | L54: 209 | M54: 11 | N54: 21 | O54: -2 | P54: 1 | Q54: 0 | R54: 21 | S54: 19 | T54: HOLD | V54: =IF(E54="","",R54-E54) | W54: YES | X54: =IF(AND(D54="Available",R54>=55),ROW(),9999) -> 9999 | Y54: =IF(AND(D54="Available",R54>=40,R54<55),ROW(),9999) -> 9999 | Z54: =IF(AND(D54="Available",R54>=25,R54<40),ROW(),9999) -> 9999 | AA54: =IF(K54="","",IF(L54="",K54,ROUND(AVERAGE(K54,L54),0))) -> 209
A55: Rome Odunze | B55: =R55-N55 -> 1 | C55: =IF(B55>=5,"SMASH BUY",IF(B55>=2,"BUY",IF(B55>=-1,"NEUTRAL",IF(B55>=-4,"AVOID","DO NOT BID")))) -> NEUTRAL | D55: =IF(COUNTIFS('Auction Log'!$B$5:$B$304,A55,'Auction Log'!$D$5:$D$304,"<>",'Auction Log'!$E$5:$E$304,">0")=0,"Available",IFERROR(INDEX('Auction Log'!$D$5:$D$304,MATCH(1,('Auction Log'!$B$5:$B$304=A55)*('Auction Log'!$D$5:$D$304<>"")*('Auction Log'!$E$5:$E$304>0),0)),"SOLD")) -> Available | E55: =IF(COUNTIFS('Auction Log'!$B$5:$B$304,A55,'Auction Log'!$D$5:$D$304,"<>",'Auction Log'!$E$5:$E$304,">0")=0,"",IFERROR(INDEX('Auction Log'!$E$5:$E$304,MATCH(1,('Auction Log'!$B$5:$B$304=A55)*('Auction Log'!$D$5:$D$304<>"")*('Auction Log'!$E$5:$E$304>0),0)),"")) | F55: CHI | G55: WR | H55: 10 | I55: 57 | J55: 6 | K55: 205 | L55: 213 | M55: 14 | N55: 20 | O55: -1 | P55: 1 | Q55: 0 | R55: 21 | S55: 19 | T55: HOLD | V55: =IF(E55="","",R55-E55) | W55: YES | X55: =IF(AND(D55="Available",R55>=55),ROW(),9999) -> 9999 | Y55: =IF(AND(D55="Available",R55>=40,R55<55),ROW(),9999) -> 9999 | Z55: =IF(AND(D55="Available",R55>=25,R55<40),ROW(),9999) -> 9999 | AA55: =IF(K55="","",IF(L55="",K55,ROUND(AVERAGE(K55,L55),0))) -> 209
A56: Quinshon Judkins | B56: =R56-N56 -> 1 | C56: =IF(B56>=5,"SMASH BUY",IF(B56>=2,"BUY",IF(B56>=-1,"NEUTRAL",IF(B56>=-4,"AVOID","DO NOT BID")))) -> NEUTRAL | D56: =IF(COUNTIFS('Auction Log'!$B$5:$B$304,A56,'Auction Log'!$D$5:$D$304,"<>",'Auction Log'!$E$5:$E$304,">0")=0,"Available",IFERROR(INDEX('Auction Log'!$D$5:$D$304,MATCH(1,('Auction Log'!$B$5:$B$304=A56)*('Auction Log'!$D$5:$D$304<>"")*('Auction Log'!$E$5:$E$304>0),0)),"SOLD")) -> Available | E56: =IF(COUNTIFS('Auction Log'!$B$5:$B$304,A56,'Auction Log'!$D$5:$D$304,"<>",'Auction Log'!$E$5:$E$304,">0")=0,"",IFERROR(INDEX('Auction Log'!$E$5:$E$304,MATCH(1,('Auction Log'!$B$5:$B$304=A56)*('Auction Log'!$D$5:$D$304<>"")*('Auction Log'!$E$5:$E$304>0),0)),"")) | F56: CLE | G56: RB | H56: 11 | I56: 62 | J56: 6 | K56: 215 | L56: 226 | M56: 21 | N56: 20 | O56: -1 | P56: 2 | Q56: 1 | R56: 21 | S56: 19 | T56: HOLD | U56: Undisclosed - reportedly 'a little something nagging, nothing big'; did not play in second preseason game (8/24) | V56: =IF(E56="","",R56-E56) | W56: YES | X56: =IF(AND(D56="Available",R56>=55),ROW(),9999) -> 9999 | Y56: =IF(AND(D56="Available",R56>=40,R56<55),ROW(),9999) -> 9999 | Z56: =IF(AND(D56="Available",R56>=25,R56<40),ROW(),9999) -> 9999 | AA56: =IF(K56="","",IF(L56="",K56,ROUND(AVERAGE(K56,L56),0))) -> 221
A57: Lamar Jackson | B57: =R57-N57 -> 5 | C57: =IF(B57>=5,"SMASH BUY",IF(B57>=2,"BUY",IF(B57>=-1,"NEUTRAL",IF(B57>=-4,"AVOID","DO NOT BID")))) -> SMASH BUY | D57: =IF(COUNTIFS('Auction Log'!$B$5:$B$304,A57,'Auction Log'!$D$5:$D$304,"<>",'Auction Log'!$E$5:$E$304,">0")=0,"Available",IFERROR(INDEX('Auction Log'!$D$5:$D$304,MATCH(1,('Auction Log'!$B$5:$B$304=A57)*('Auction Log'!$D$5:$D$304<>"")*('Auction Log'!$E$5:$E$304>0),0)),"SOLD")) -> Available | E57: =IF(COUNTIFS('Auction Log'!$B$5:$B$304,A57,'Auction Log'!$D$5:$D$304,"<>",'Auction Log'!$E$5:$E$304,">0")=0,"",IFERROR(INDEX('Auction Log'!$E$5:$E$304,MATCH(1,('Auction Log'!$B$5:$B$304=A57)*('Auction Log'!$D$5:$D$304<>"")*('Auction Log'!$E$5:$E$304>0),0)),"")) | F57: BAL | G57: QB | H57: 13 | I57: 31 | J57: 4 | K57: 325 | L57: 323 | M57: 10 | N57: 15 | O57: 3 | P57: 1 | Q57: 0 | R57: 20 | S57: 18 | T57: TARGET | V57: =IF(E57="","",R57-E57) | W57: YES | X57: =IF(AND(D57="Available",R57>=55),ROW(),9999) -> 9999 | Y57: =IF(AND(D57="Available",R57>=40,R57<55),ROW(),9999) -> 9999 | Z57: =IF(AND(D57="Available",R57>=25,R57<40),ROW(),9999) -> 9999 | AA57: =IF(K57="","",IF(L57="",K57,ROUND(AVERAGE(K57,L57),0))) -> 324
A58: Drake Maye | B58: =R58-N58 -> 4 | C58: =IF(B58>=5,"SMASH BUY",IF(B58>=2,"BUY",IF(B58>=-1,"NEUTRAL",IF(B58>=-4,"AVOID","DO NOT BID")))) -> BUY | D58: =IF(COUNTIFS('Auction Log'!$B$5:$B$304,A58,'Auction Log'!$D$5:$D$304,"<>",'Auction Log'!$E$5:$E$304,">0")=0,"Available",IFERROR(INDEX('Auction Log'!$D$5:$D$304,MATCH(1,('Auction Log'!$B$5:$B$304=A58)*('Auction Log'!$D$5:$D$304<>"")*('Auction Log'!$E$5:$E$304>0),0)),"SOLD")) -> Available | E58: =IF(COUNTIFS('Auction Log'!$B$5:$B$304,A58,'Auction Log'!$D$5:$D$304,"<>",'Auction Log'!$E$5:$E$304,">0")=0,"",IFERROR(INDEX('Auction Log'!$E$5:$E$304,MATCH(1,('Auction Log'!$B$5:$B$304=A58)*('Auction Log'!$D$5:$D$304<>"")*('Auction Log'!$E$5:$E$304>0),0)),"")) | F58: NE | G58: QB | H58: 11 | I58: 38 | J58: 5 | K58: 323 | L58: 319 | M58: 10 | N58: 15 | O58: 2 | P58: 1 | Q58: 0 | R58: 19 | S58: 17 | T58: TARGET | V58: =IF(E58="","",R58-E58) | W58: YES | X58: =IF(AND(D58="Available",R58>=55),ROW(),9999) -> 9999 | Y58: =IF(AND(D58="Available",R58>=40,R58<55),ROW(),9999) -> 9999 | Z58: =IF(AND(D58="Available",R58>=25,R58<40),ROW(),9999) -> 9999 | AA58: =IF(K58="","",IF(L58="",K58,ROUND(AVERAGE(K58,L58),0))) -> 321
A59: Luther Burden III | B59: =R59-N59 -> -2 | C59: =IF(B59>=5,"SMASH BUY",IF(B59>=2,"BUY",IF(B59>=-1,"NEUTRAL",IF(B59>=-4,"AVOID","DO NOT BID")))) -> AVOID | D59: =IF(COUNTIFS('Auction Log'!$B$5:$B$304,A59,'Auction Log'!$D$5:$D$304,"<>",'Auction Log'!$E$5:$E$304,">0")=0,"Available",IFERROR(INDEX('Auction Log'!$D$5:$D$304,MATCH(1,('Auction Log'!$B$5:$B$304=A59)*('Auction Log'!$D$5:$D$304<>"")*('Auction Log'!$E$5:$E$304>0),0)),"SOLD")) -> Available | E59: =IF(COUNTIFS('Auction Log'!$B$5:$B$304,A59,'Auction Log'!$D$5:$D$304,"<>",'Auction Log'!$E$5:$E$304,">0")=0,"",IFERROR(INDEX('Auction Log'!$E$5:$E$304,MATCH(1,('Auction Log'!$B$5:$B$304=A59)*('Auction Log'!$D$5:$D$304<>"")*('Auction Log'!$E$5:$E$304>0),0)),"")) | F59: CHI | G59: WR | H59: 10 | I59: 47 | J59: 5 | K59: 208 | L59: 206 | M59: 11 | N59: 21 | O59: -2 | P59: 0 | Q59: 1 | R59: 19 | S59: 17 | T59: HOLD | U59: Groin - returned to practice 8/26 but individuals only (ESPN). | V59: =IF(E59="","",R59-E59) | W59: YES | X59: =IF(AND(D59="Available",R59>=55),ROW(),9999) -> 9999 | Y59: =IF(AND(D59="Available",R59>=40,R59<55),ROW(),9999) -> 9999 | Z59: =IF(AND(D59="Available",R59>=25,R59<40),ROW(),9999) -> 9999 | AA59: =IF(K59="","",IF(L59="",K59,ROUND(AVERAGE(K59,L59),0))) -> 207
A60: Tyler Warren | B60: =R60-N60 -> 2 | C60: =IF(B60>=5,"SMASH BUY",IF(B60>=2,"BUY",IF(B60>=-1,"NEUTRAL",IF(B60>=-4,"AVOID","DO NOT BID")))) -> BUY | D60: =IF(COUNTIFS('Auction Log'!$B$5:$B$304,A60,'Auction Log'!$D$5:$D$304,"<>",'Auction Log'!$E$5:$E$304,">0")=0,"Available",IFERROR(INDEX('Auction Log'!$D$5:$D$304,MATCH(1,('Auction Log'!$B$5:$B$304=A60)*('Auction Log'!$D$5:$D$304<>"")*('Auction Log'!$E$5:$E$304>0),0)),"SOLD")) -> Available | E60: =IF(COUNTIFS('Auction Log'!$B$5:$B$304,A60,'Auction Log'!$D$5:$D$304,"<>",'Auction Log'!$E$5:$E$304,">0")=0,"",IFERROR(INDEX('Auction Log'!$E$5:$E$304,MATCH(1,('Auction Log'!$B$5:$B$304=A60)*('Auction Log'!$D$5:$D$304<>"")*('Auction Log'!$E$5:$E$304>0),0)),"")) | F60: IND | G60: TE | H60: 13 | I60: 52 | J60: 6 | K60: 199 | L60: 211 | M60: 13 | N60: 17 | O60: 0 | P60: 1 | Q60: 0 | R60: 19 | S60: 17 | T60: HOLD | U60: Groin - may sit practice this week but staff preparing him for opener (8/25 via ESPN). Week 1 intent intact. | V60: =IF(E60="","",R60-E60) | W60: YES | X60: =IF(AND(D60="Available",R60>=55),ROW(),9999) -> 9999 | Y60: =IF(AND(D60="Available",R60>=40,R60<55),ROW(),9999) -> 9999 | Z60: =IF(AND(D60="Available",R60>=25,R60<40),ROW(),9999) -> 9999 | AA60: =IF(K60="","",IF(L60="",K60,ROUND(AVERAGE(K60,L60),0))) -> 205
A61: Mike Evans | B61: =R61-N61 -> -1 | C61: =IF(B61>=5,"SMASH BUY",IF(B61>=2,"BUY",IF(B61>=-1,"NEUTRAL",IF(B61>=-4,"AVOID","DO NOT BID")))) -> NEUTRAL | D61: =IF(COUNTIFS('Auction Log'!$B$5:$B$304,A61,'Auction Log'!$D$5:$D$304,"<>",'Auction Log'!$E$5:$E$304,">0")=0,"Available",IFERROR(INDEX('Auction Log'!$D$5:$D$304,MATCH(1,('Auction Log'!$B$5:$B$304=A61)*('Auction Log'!$D$5:$D$304<>"")*('Auction Log'!$E$5:$E$304>0),0)),"SOLD")) -> Available | E61: =IF(COUNTIFS('Auction Log'!$B$5:$B$304,A61,'Auction Log'!$D$5:$D$304,"<>",'Auction Log'!$E$5:$E$304,">0")=0,"",IFERROR(INDEX('Auction Log'!$E$5:$E$304,MATCH(1,('Auction Log'!$B$5:$B$304=A61)*('Auction Log'!$D$5:$D$304<>"")*('Auction Log'!$E$5:$E$304>0),0)),"")) | F61: SF | G61: WR | H61: 8 | I61: 53 | J61: 6 | K61: 204 | L61: 183 | M61: 5 | N61: 19 | O61: -2 | P61: 1 | Q61: 1 | R61: 18 | S61: 16 | T61: HOLD | U61: Groin - not practicing 8/25 (ESPN). NEW caution vs older quad note — do not pay healthy price. | V61: =IF(E61="","",R61-E61) | W61: YES | X61: =IF(AND(D61="Available",R61>=55),ROW(),9999) -> 9999 | Y61: =IF(AND(D61="Available",R61>=40,R61<55),ROW(),9999) -> 9999 | Z61: =IF(AND(D61="Available",R61>=25,R61<40),ROW(),9999) -> 9999 | AA61: =IF(K61="","",IF(L61="",K61,ROUND(AVERAGE(K61,L61),0))) -> 194
A62: Bhayshul Tuten | B62: =R62-N62 -> -1 | C62: =IF(B62>=5,"SMASH BUY",IF(B62>=2,"BUY",IF(B62>=-1,"NEUTRAL",IF(B62>=-4,"AVOID","DO NOT BID")))) -> NEUTRAL | D62: =IF(COUNTIFS('Auction Log'!$B$5:$B$304,A62,'Auction Log'!$D$5:$D$304,"<>",'Auction Log'!$E$5:$E$304,">0")=0,"Available",IFERROR(INDEX('Auction Log'!$D$5:$D$304,MATCH(1,('Auction Log'!$B$5:$B$304=A62)*('Auction Log'!$D$5:$D$304<>"")*('Auction Log'!$E$5:$E$304>0),0)),"SOLD")) -> Available | E62: =IF(COUNTIFS('Auction Log'!$B$5:$B$304,A62,'Auction Log'!$D$5:$D$304,"<>",'Auction Log'!$E$5:$E$304,">0")=0,"",IFERROR(INDEX('Auction Log'!$E$5:$E$304,MATCH(1,('Auction Log'!$B$5:$B$304=A62)*('Auction Log'!$D$5:$D$304<>"")*('Auction Log'!$E$5:$E$304>0),0)),"")) | F62: JAC | G62: RB | H62: 7 | I62: 66 | J62: 6 | K62: 207 | L62: 205 | M62: 9 | N62: 19 | O62: -3 | P62: 1 | Q62: 0 | R62: 18 | S62: 16 | T62: TARGET | V62: =IF(E62="","",R62-E62) | W62: YES | X62: =IF(AND(D62="Available",R62>=55),ROW(),9999) -> 9999 | Y62: =IF(AND(D62="Available",R62>=40,R62<55),ROW(),9999) -> 9999 | Z62: =IF(AND(D62="Available",R62>=25,R62<40),ROW(),9999) -> 9999 | AA62: =IF(K62="","",IF(L62="",K62,ROUND(AVERAGE(K62,L62),0))) -> 206
A63: Jayden Daniels | B63: =R63-N63 -> 2 | C63: =IF(B63>=5,"SMASH BUY",IF(B63>=2,"BUY",IF(B63>=-1,"NEUTRAL",IF(B63>=-4,"AVOID","DO NOT BID")))) -> BUY | D63: =IF(COUNTIFS('Auction Log'!$B$5:$B$304,A63,'Auction Log'!$D$5:$D$304,"<>",'Auction Log'!$E$5:$E$304,">0")=0,"Available",IFERROR(INDEX('Auction Log'!$D$5:$D$304,MATCH(1,('Auction Log'!$B$5:$B$304=A63)*('Auction Log'!$D$5:$D$304<>"")*('Auction Log'!$E$5:$E$304>0),0)),"SOLD")) -> Available | E63: =IF(COUNTIFS('Auction Log'!$B$5:$B$304,A63,'Auction Log'!$D$5:$D$304,"<>",'Auction Log'!$E$5:$E$304,">0")=0,"",IFERROR(INDEX('Auction Log'!$E$5:$E$304,MATCH(1,('Auction Log'!$B$5:$B$304=A63)*('Auction Log'!$D$5:$D$304<>"")*('Auction Log'!$E$5:$E$304>0),0)),"")) | F63: WAS | G63: QB | H63: 7 | I63: 50 | J63: 5 | K63: 323 | L63: 318 | M63: 10 | N63: 15 | O63: 1 | P63: 0 | Q63: 0 | R63: 17 | S63: 15 | T63: HOLD | V63: =IF(E63="","",R63-E63) | W63: YES | X63: =IF(AND(D63="Available",R63>=55),ROW(),9999) -> 9999 | Y63: =IF(AND(D63="Available",R63>=40,R63<55),ROW(),9999) -> 9999 | Z63: =IF(AND(D63="Available",R63>=25,R63<40),ROW(),9999) -> 9999 | AA63: =IF(K63="","",IF(L63="",K63,ROUND(AVERAGE(K63,L63),0))) -> 321
A64: Marvin Harrison Jr. | B64: =R64-N64 -> -1 | C64: =IF(B64>=5,"SMASH BUY",IF(B64>=2,"BUY",IF(B64>=-1,"NEUTRAL",IF(B64>=-4,"AVOID","DO NOT BID")))) -> NEUTRAL | D64: =IF(COUNTIFS('Auction Log'!$B$5:$B$304,A64,'Auction Log'!$D$5:$D$304,"<>",'Auction Log'!$E$5:$E$304,">0")=0,"Available",IFERROR(INDEX('Auction Log'!$D$5:$D$304,MATCH(1,('Auction Log'!$B$5:$B$304=A64)*('Auction Log'!$D$5:$D$304<>"")*('Auction Log'!$E$5:$E$304>0),0)),"SOLD")) -> Available | E64: =IF(COUNTIFS('Auction Log'!$B$5:$B$304,A64,'Auction Log'!$D$5:$D$304,"<>",'Auction Log'!$E$5:$E$304,">0")=0,"",IFERROR(INDEX('Auction Log'!$E$5:$E$304,MATCH(1,('Auction Log'!$B$5:$B$304=A64)*('Auction Log'!$D$5:$D$304<>"")*('Auction Log'!$E$5:$E$304>0),0)),"")) | F64: ARI | G64: WR | H64: 14 | I64: 67 | J64: 6 | K64: 197 | L64: 194 | M64: 7 | N64: 18 | O64: -3 | P64: 1 | Q64: 0 | R64: 17 | S64: 15 | T64: HOLD | V64: =IF(E64="","",R64-E64) | W64: YES | X64: =IF(AND(D64="Available",R64>=55),ROW(),9999) -> 9999 | Y64: =IF(AND(D64="Available",R64>=40,R64<55),ROW(),9999) -> 9999 | Z64: =IF(AND(D64="Available",R64>=25,R64<40),ROW(),9999) -> 9999 | AA64: =IF(K64="","",IF(L64="",K64,ROUND(AVERAGE(K64,L64),0))) -> 196
A65: Joe Burrow | B65: =R65-N65 -> 5 | C65: =IF(B65>=5,"SMASH BUY",IF(B65>=2,"BUY",IF(B65>=-1,"NEUTRAL",IF(B65>=-4,"AVOID","DO NOT BID")))) -> SMASH BUY | D65: =IF(COUNTIFS('Auction Log'!$B$5:$B$304,A65,'Auction Log'!$D$5:$D$304,"<>",'Auction Log'!$E$5:$E$304,">0")=0,"Available",IFERROR(INDEX('Auction Log'!$D$5:$D$304,MATCH(1,('Auction Log'!$B$5:$B$304=A65)*('Auction Log'!$D$5:$D$304<>"")*('Auction Log'!$E$5:$E$304>0),0)),"SOLD")) -> Available | E65: =IF(COUNTIFS('Auction Log'!$B$5:$B$304,A65,'Auction Log'!$D$5:$D$304,"<>",'Auction Log'!$E$5:$E$304,">0")=0,"",IFERROR(INDEX('Auction Log'!$E$5:$E$304,MATCH(1,('Auction Log'!$B$5:$B$304=A65)*('Auction Log'!$D$5:$D$304<>"")*('Auction Log'!$E$5:$E$304>0),0)),"")) | F65: CIN | G65: QB | H65: 6 | I65: 46 | J65: 5 | K65: 311 | L65: 305 | M65: 5 | N65: 11 | O65: 3 | P65: 1 | Q65: 0 | R65: 16 | S65: 14 | T65: TARGET | V65: =IF(E65="","",R65-E65) | W65: YES | X65: =IF(AND(D65="Available",R65>=55),ROW(),9999) -> 9999 | Y65: =IF(AND(D65="Available",R65>=40,R65<55),ROW(),9999) -> 9999 | Z65: =IF(AND(D65="Available",R65>=25,R65<40),ROW(),9999) -> 9999 | AA65: =IF(K65="","",IF(L65="",K65,ROUND(AVERAGE(K65,L65),0))) -> 308
A66: Christian Watson | B66: =R66-N66 -> -1 | C66: =IF(B66>=5,"SMASH BUY",IF(B66>=2,"BUY",IF(B66>=-1,"NEUTRAL",IF(B66>=-4,"AVOID","DO NOT BID")))) -> NEUTRAL | D66: =IF(COUNTIFS('Auction Log'!$B$5:$B$304,A66,'Auction Log'!$D$5:$D$304,"<>",'Auction Log'!$E$5:$E$304,">0")=0,"Available",IFERROR(INDEX('Auction Log'!$D$5:$D$304,MATCH(1,('Auction Log'!$B$5:$B$304=A66)*('Auction Log'!$D$5:$D$304<>"")*('Auction Log'!$E$5:$E$304>0),0)),"SOLD")) -> Available | E66: =IF(COUNTIFS('Auction Log'!$B$5:$B$304,A66,'Auction Log'!$D$5:$D$304,"<>",'Auction Log'!$E$5:$E$304,">0")=0,"",IFERROR(INDEX('Auction Log'!$E$5:$E$304,MATCH(1,('Auction Log'!$B$5:$B$304=A66)*('Auction Log'!$D$5:$D$304<>"")*('Auction Log'!$E$5:$E$304>0),0)),"")) | F66: GB | G66: WR | H66: 11 | I66: 59 | J66: 6 | K66: 195 | L66: 185 | M66: 5 | N66: 17 | O66: -2 | P66: 0 | Q66: 0 | R66: 16 | S66: 14 | T66: TARGET | V66: =IF(E66="","",R66-E66) | W66: YES | X66: =IF(AND(D66="Available",R66>=55),ROW(),9999) -> 9999 | Y66: =IF(AND(D66="Available",R66>=40,R66<55),ROW(),9999) -> 9999 | Z66: =IF(AND(D66="Available",R66>=25,R66<40),ROW(),9999) -> 9999 | AA66: =IF(K66="","",IF(L66="",K66,ROUND(AVERAGE(K66,L66),0))) -> 190
A67: David Montgomery | B67: =R67-N67 -> -1 | C67: =IF(B67>=5,"SMASH BUY",IF(B67>=2,"BUY",IF(B67>=-1,"NEUTRAL",IF(B67>=-4,"AVOID","DO NOT BID")))) -> NEUTRAL | D67: =IF(COUNTIFS('Auction Log'!$B$5:$B$304,A67,'Auction Log'!$D$5:$D$304,"<>",'Auction Log'!$E$5:$E$304,">0")=0,"Available",IFERROR(INDEX('Auction Log'!$D$5:$D$304,MATCH(1,('Auction Log'!$B$5:$B$304=A67)*('Auction Log'!$D$5:$D$304<>"")*('Auction Log'!$E$5:$E$304>0),0)),"SOLD")) -> Available | E67: =IF(COUNTIFS('Auction Log'!$B$5:$B$304,A67,'Auction Log'!$D$5:$D$304,"<>",'Auction Log'!$E$5:$E$304,">0")=0,"",IFERROR(INDEX('Auction Log'!$E$5:$E$304,MATCH(1,('Auction Log'!$B$5:$B$304=A67)*('Auction Log'!$D$5:$D$304<>"")*('Auction Log'!$E$5:$E$304>0),0)),"")) | F67: HOU | G67: RB | H67: 8 | I67: 61 | J67: 6 | K67: 196 | L67: 193 | M67: 8 | N67: 16 | O67: -2 | P67: 0 | Q67: 0 | R67: 15 | S67: 13 | T67: TARGET | V67: =IF(E67="","",R67-E67) | W67: YES | X67: =IF(AND(D67="Available",R67>=55),ROW(),9999) -> 9999 | Y67: =IF(AND(D67="Available",R67>=40,R67<55),ROW(),9999) -> 9999 | Z67: =IF(AND(D67="Available",R67>=25,R67<40),ROW(),9999) -> 9999 | AA67: =IF(K67="","",IF(L67="",K67,ROUND(AVERAGE(K67,L67),0))) -> 195
A68: Carnell Tate | B68: =R68-N68 -> 3 | C68: =IF(B68>=5,"SMASH BUY",IF(B68>=2,"BUY",IF(B68>=-1,"NEUTRAL",IF(B68>=-4,"AVOID","DO NOT BID")))) -> BUY | D68: =IF(COUNTIFS('Auction Log'!$B$5:$B$304,A68,'Auction Log'!$D$5:$D$304,"<>",'Auction Log'!$E$5:$E$304,">0")=0,"Available",IFERROR(INDEX('Auction Log'!$D$5:$D$304,MATCH(1,('Auction Log'!$B$5:$B$304=A68)*('Auction Log'!$D$5:$D$304<>"")*('Auction Log'!$E$5:$E$304>0),0)),"SOLD")) -> Available | E68: =IF(COUNTIFS('Auction Log'!$B$5:$B$304,A68,'Auction Log'!$D$5:$D$304,"<>",'Auction Log'!$E$5:$E$304,">0")=0,"",IFERROR(INDEX('Auction Log'!$E$5:$E$304,MATCH(1,('Auction Log'!$B$5:$B$304=A68)*('Auction Log'!$D$5:$D$304<>"")*('Auction Log'!$E$5:$E$304>0),0)),"")) | F68: TEN | G68: WR | H68: 9 | I68: 64 | J68: 6 | K68: 178 | L68: 202 | M68: 10 | N68: 12 | O68: 1 | P68: 1 | Q68: 0 | R68: 15 | S68: 13 | T68: TARGET | V68: =IF(E68="","",R68-E68) | W68: YES | X68: =IF(AND(D68="Available",R68>=55),ROW(),9999) -> 9999 | Y68: =IF(AND(D68="Available",R68>=40,R68<55),ROW(),9999) -> 9999 | Z68: =IF(AND(D68="Available",R68>=25,R68<40),ROW(),9999) -> 9999 | AA68: =IF(K68="","",IF(L68="",K68,ROUND(AVERAGE(K68,L68),0))) -> 190
A69: DK Metcalf | B69: =R69-N69 -> -2 | C69: =IF(B69>=5,"SMASH BUY",IF(B69>=2,"BUY",IF(B69>=-1,"NEUTRAL",IF(B69>=-4,"AVOID","DO NOT BID")))) -> AVOID | D69: =IF(COUNTIFS('Auction Log'!$B$5:$B$304,A69,'Auction Log'!$D$5:$D$304,"<>",'Auction Log'!$E$5:$E$304,">0")=0,"Available",IFERROR(INDEX('Auction Log'!$D$5:$D$304,MATCH(1,('Auction Log'!$B$5:$B$304=A69)*('Auction Log'!$D$5:$D$304<>"")*('Auction Log'!$E$5:$E$304>0),0)),"SOLD")) -> Available | E69: =IF(COUNTIFS('Auction Log'!$B$5:$B$304,A69,'Auction Log'!$D$5:$D$304,"<>",'Auction Log'!$E$5:$E$304,">0")=0,"",IFERROR(INDEX('Auction Log'!$E$5:$E$304,MATCH(1,('Auction Log'!$B$5:$B$304=A69)*('Auction Log'!$D$5:$D$304<>"")*('Auction Log'!$E$5:$E$304>0),0)),"")) | F69: PIT | G69: WR | H69: 9 | I69: 78 | J69: 7 | K69: 195 | L69: 196 | M69: 6 | N69: 17 | O69: -4 | P69: 1 | Q69: 0 | R69: 15 | S69: 13 | T69: HOLD | U69: Undisclosed - returned to practice 8/24 after sidelined since 8/8 (ESPN). | V69: =IF(E69="","",R69-E69) | W69: YES | X69: =IF(AND(D69="Available",R69>=55),ROW(),9999) -> 9999 | Y69: =IF(AND(D69="Available",R69>=40,R69<55),ROW(),9999) -> 9999 | Z69: =IF(AND(D69="Available",R69>=25,R69<40),ROW(),9999) -> 9999 | AA69: =IF(K69="","",IF(L69="",K69,ROUND(AVERAGE(K69,L69),0))) -> 196
A70: Courtland Sutton | B70: =R70-N70 -> -3 | C70: =IF(B70>=5,"SMASH BUY",IF(B70>=2,"BUY",IF(B70>=-1,"NEUTRAL",IF(B70>=-4,"AVOID","DO NOT BID")))) -> AVOID | D70: =IF(COUNTIFS('Auction Log'!$B$5:$B$304,A70,'Auction Log'!$D$5:$D$304,"<>",'Auction Log'!$E$5:$E$304,">0")=0,"Available",IFERROR(INDEX('Auction Log'!$D$5:$D$304,MATCH(1,('Auction Log'!$B$5:$B$304=A70)*('Auction Log'!$D$5:$D$304<>"")*('Auction Log'!$E$5:$E$304>0),0)),"SOLD")) -> Available | E70: =IF(COUNTIFS('Auction Log'!$B$5:$B$304,A70,'Auction Log'!$D$5:$D$304,"<>",'Auction Log'!$E$5:$E$304,">0")=0,"",IFERROR(INDEX('Auction Log'!$E$5:$E$304,MATCH(1,('Auction Log'!$B$5:$B$304=A70)*('Auction Log'!$D$5:$D$304<>"")*('Auction Log'!$E$5:$E$304>0),0)),"")) | F70: DEN | G70: WR | H70: 10 | I70: 82 | J70: 7 | K70: 199 | L70: 204 | M70: 7 | N70: 18 | O70: -4 | P70: 0 | Q70: 0 | R70: 15 | S70: 13 | T70: HOLD | V70: =IF(E70="","",R70-E70) | W70: YES | X70: =IF(AND(D70="Available",R70>=55),ROW(),9999) -> 9999 | Y70: =IF(AND(D70="Available",R70>=40,R70<55),ROW(),9999) -> 9999 | Z70: =IF(AND(D70="Available",R70>=25,R70<40),ROW(),9999) -> 9999 | AA70: =IF(K70="","",IF(L70="",K70,ROUND(AVERAGE(K70,L70),0))) -> 202
A71: Jalen Hurts | B71: =R71-N71 -> 0 | C71: =IF(B71>=5,"SMASH BUY",IF(B71>=2,"BUY",IF(B71>=-1,"NEUTRAL",IF(B71>=-4,"AVOID","DO NOT BID")))) -> NEUTRAL | D71: =IF(COUNTIFS('Auction Log'!$B$5:$B$304,A71,'Auction Log'!$D$5:$D$304,"<>",'Auction Log'!$E$5:$E$304,">0")=0,"Available",IFERROR(INDEX('Auction Log'!$D$5:$D$304,MATCH(1,('Auction Log'!$B$5:$B$304=A71)*('Auction Log'!$D$5:$D$304<>"")*('Auction Log'!$E$5:$E$304>0),0)),"SOLD")) -> Available | E71: =IF(COUNTIFS('Auction Log'!$B$5:$B$304,A71,'Auction Log'!$D$5:$D$304,"<>",'Auction Log'!$E$5:$E$304,">0")=0,"",IFERROR(INDEX('Auction Log'!$E$5:$E$304,MATCH(1,('Auction Log'!$B$5:$B$304=A71)*('Auction Log'!$D$5:$D$304<>"")*('Auction Log'!$E$5:$E$304>0),0)),"")) | F71: PHI | G71: QB | H71: 10 | I71: 58 | J71: 6 | K71: 320 | L71: 320 | M71: 9 | N71: 14 | O71: 0 | P71: -1 | Q71: 0 | R71: 14 | S71: 12 | T71: HOLD | V71: =IF(E71="","",R71-E71) | W71: YES | X71: =IF(AND(D71="Available",R71>=55),ROW(),9999) -> 9999 | Y71: =IF(AND(D71="Available",R71>=40,R71<55),ROW(),9999) -> 9999 | Z71: =IF(AND(D71="Available",R71>=25,R71<40),ROW(),9999) -> 9999 | AA71: =IF(K71="","",IF(L71="",K71,ROUND(AVERAGE(K71,L71),0))) -> 320
A72: Parker Washington | B72: =R72-N72 -> 0 | C72: =IF(B72>=5,"SMASH BUY",IF(B72>=2,"BUY",IF(B72>=-1,"NEUTRAL",IF(B72>=-4,"AVOID","DO NOT BID")))) -> NEUTRAL | D72: =IF(COUNTIFS('Auction Log'!$B$5:$B$304,A72,'Auction Log'!$D$5:$D$304,"<>",'Auction Log'!$E$5:$E$304,">0")=0,"Available",IFERROR(INDEX('Auction Log'!$D$5:$D$304,MATCH(1,('Auction Log'!$B$5:$B$304=A72)*('Auction Log'!$D$5:$D$304<>"")*('Auction Log'!$E$5:$E$304>0),0)),"SOLD")) -> Available | E72: =IF(COUNTIFS('Auction Log'!$B$5:$B$304,A72,'Auction Log'!$D$5:$D$304,"<>",'Auction Log'!$E$5:$E$304,">0")=0,"",IFERROR(INDEX('Auction Log'!$E$5:$E$304,MATCH(1,('Auction Log'!$B$5:$B$304=A72)*('Auction Log'!$D$5:$D$304<>"")*('Auction Log'!$E$5:$E$304>0),0)),"")) | F72: JAC | G72: WR | H72: 7 | I72: 63 | J72: 6 | K72: 184 | L72: 187 | M72: 6 | N72: 14 | O72: -1 | P72: 0 | Q72: 0 | R72: 14 | S72: 12 | T72: TARGET | U72: Undisclosed - participated in walkthrough on 8/23; should return to practice week of 8/24 | V72: =IF(E72="","",R72-E72) | W72: YES | X72: =IF(AND(D72="Available",R72>=55),ROW(),9999) -> 9999 | Y72: =IF(AND(D72="Available",R72>=40,R72<55),ROW(),9999) -> 9999 | Z72: =IF(AND(D72="Available",R72>=25,R72<40),ROW(),9999) -> 9999 | AA72: =IF(K72="","",IF(L72="",K72,ROUND(AVERAGE(K72,L72),0))) -> 186
A73: TreVeyon Henderson | B73: =R73-N73 -> -1 | C73: =IF(B73>=5,"SMASH BUY",IF(B73>=2,"BUY",IF(B73>=-1,"NEUTRAL",IF(B73>=-4,"AVOID","DO NOT BID")))) -> NEUTRAL | D73: =IF(COUNTIFS('Auction Log'!$B$5:$B$304,A73,'Auction Log'!$D$5:$D$304,"<>",'Auction Log'!$E$5:$E$304,">0")=0,"Available",IFERROR(INDEX('Auction Log'!$D$5:$D$304,MATCH(1,('Auction Log'!$B$5:$B$304=A73)*('Auction Log'!$D$5:$D$304<>"")*('Auction Log'!$E$5:$E$304>0),0)),"SOLD")) -> Available | E73: =IF(COUNTIFS('Auction Log'!$B$5:$B$304,A73,'Auction Log'!$D$5:$D$304,"<>",'Auction Log'!$E$5:$E$304,">0")=0,"",IFERROR(INDEX('Auction Log'!$E$5:$E$304,MATCH(1,('Auction Log'!$B$5:$B$304=A73)*('Auction Log'!$D$5:$D$304<>"")*('Auction Log'!$E$5:$E$304>0),0)),"")) | F73: NE | G73: RB | H73: 11 | I73: 68 | J73: 6 | K73: 192 | L73: 197 | M73: 8 | N73: 15 | O73: -2 | P73: 0 | Q73: 0 | R73: 14 | S73: 12 | T73: HOLD | V73: =IF(E73="","",R73-E73) | W73: YES | X73: =IF(AND(D73="Available",R73>=55),ROW(),9999) -> 9999 | Y73: =IF(AND(D73="Available",R73>=40,R73<55),ROW(),9999) -> 9999 | Z73: =IF(AND(D73="Available",R73>=25,R73<40),ROW(),9999) -> 9999 | AA73: =IF(K73="","",IF(L73="",K73,ROUND(AVERAGE(K73,L73),0))) -> 195
A74: Jadarian Price | B74: =R74-N74 -> 0 | C74: =IF(B74>=5,"SMASH BUY",IF(B74>=2,"BUY",IF(B74>=-1,"NEUTRAL",IF(B74>=-4,"AVOID","DO NOT BID")))) -> NEUTRAL | D74: =IF(COUNTIFS('Auction Log'!$B$5:$B$304,A74,'Auction Log'!$D$5:$D$304,"<>",'Auction Log'!$E$5:$E$304,">0")=0,"Available",IFERROR(INDEX('Auction Log'!$D$5:$D$304,MATCH(1,('Auction Log'!$B$5:$B$304=A74)*('Auction Log'!$D$5:$D$304<>"")*('Auction Log'!$E$5:$E$304>0),0)),"SOLD")) -> Available | E74: =IF(COUNTIFS('Auction Log'!$B$5:$B$304,A74,'Auction Log'!$D$5:$D$304,"<>",'Auction Log'!$E$5:$E$304,">0")=0,"",IFERROR(INDEX('Auction Log'!$E$5:$E$304,MATCH(1,('Auction Log'!$B$5:$B$304=A74)*('Auction Log'!$D$5:$D$304<>"")*('Auction Log'!$E$5:$E$304>0),0)),"")) | F74: SEA | G74: RB | H74: 11 | I74: 70 | J74: 6 | K74: 190 | L74: 194 | M74: 8 | N74: 14 | O74: -1 | P74: 0 | Q74: 0 | R74: 14 | S74: 12 | T74: TARGET | V74: =IF(E74="","",R74-E74) | W74: YES | X74: =IF(AND(D74="Available",R74>=55),ROW(),9999) -> 9999 | Y74: =IF(AND(D74="Available",R74>=40,R74<55),ROW(),9999) -> 9999 | Z74: =IF(AND(D74="Available",R74>=25,R74<40),ROW(),9999) -> 9999 | AA74: =IF(K74="","",IF(L74="",K74,ROUND(AVERAGE(K74,L74),0))) -> 192
A75: Harold Fannin Jr. | B75: =R75-N75 -> -1 | C75: =IF(B75>=5,"SMASH BUY",IF(B75>=2,"BUY",IF(B75>=-1,"NEUTRAL",IF(B75>=-4,"AVOID","DO NOT BID")))) -> NEUTRAL | D75: =IF(COUNTIFS('Auction Log'!$B$5:$B$304,A75,'Auction Log'!$D$5:$D$304,"<>",'Auction Log'!$E$5:$E$304,">0")=0,"Available",IFERROR(INDEX('Auction Log'!$D$5:$D$304,MATCH(1,('Auction Log'!$B$5:$B$304=A75)*('Auction Log'!$D$5:$D$304<>"")*('Auction Log'!$E$5:$E$304>0),0)),"SOLD")) -> Available | E75: =IF(COUNTIFS('Auction Log'!$B$5:$B$304,A75,'Auction Log'!$D$5:$D$304,"<>",'Auction Log'!$E$5:$E$304,">0")=0,"",IFERROR(INDEX('Auction Log'!$E$5:$E$304,MATCH(1,('Auction Log'!$B$5:$B$304=A75)*('Auction Log'!$D$5:$D$304<>"")*('Auction Log'!$E$5:$E$304>0),0)),"")) | F75: CLE | G75: TE | H75: 11 | I75: 71 | J75: 7 | K75: 192 | L75: 188 | M75: 6 | N75: 15 | O75: -2 | P75: 0 | Q75: 0 | R75: 14 | S75: 12 | T75: TARGET | V75: =IF(E75="","",R75-E75) | W75: YES | X75: =IF(AND(D75="Available",R75>=55),ROW(),9999) -> 9999 | Y75: =IF(AND(D75="Available",R75>=40,R75<55),ROW(),9999) -> 9999 | Z75: =IF(AND(D75="Available",R75>=25,R75<40),ROW(),9999) -> 9999 | AA75: =IF(K75="","",IF(L75="",K75,ROUND(AVERAGE(K75,L75),0))) -> 190
A76: Jaylen Warren | B76: =R76-N76 -> -2 | C76: =IF(B76>=5,"SMASH BUY",IF(B76>=2,"BUY",IF(B76>=-1,"NEUTRAL",IF(B76>=-4,"AVOID","DO NOT BID")))) -> AVOID | D76: =IF(COUNTIFS('Auction Log'!$B$5:$B$304,A76,'Auction Log'!$D$5:$D$304,"<>",'Auction Log'!$E$5:$E$304,">0")=0,"Available",IFERROR(INDEX('Auction Log'!$D$5:$D$304,MATCH(1,('Auction Log'!$B$5:$B$304=A76)*('Auction Log'!$D$5:$D$304<>"")*('Auction Log'!$E$5:$E$304>0),0)),"SOLD")) -> Available | E76: =IF(COUNTIFS('Auction Log'!$B$5:$B$304,A76,'Auction Log'!$D$5:$D$304,"<>",'Auction Log'!$E$5:$E$304,">0")=0,"",IFERROR(INDEX('Auction Log'!$E$5:$E$304,MATCH(1,('Auction Log'!$B$5:$B$304=A76)*('Auction Log'!$D$5:$D$304<>"")*('Auction Log'!$E$5:$E$304>0),0)),"")) | F76: PIT | G76: RB | H76: 9 | I76: 72 | J76: 7 | K76: 197 | L76: 192 | M76: 3 | N76: 16 | O76: -3 | P76: 0 | Q76: 0 | R76: 14 | S76: 12 | T76: HOLD | V76: =IF(E76="","",R76-E76) | W76: YES | X76: =IF(AND(D76="Available",R76>=55),ROW(),9999) -> 9999 | Y76: =IF(AND(D76="Available",R76>=40,R76<55),ROW(),9999) -> 9999 | Z76: =IF(AND(D76="Available",R76>=25,R76<40),ROW(),9999) -> 9999 | AA76: =IF(K76="","",IF(L76="",K76,ROUND(AVERAGE(K76,L76),0))) -> 195
A77: Kyle Pitts Sr. | B77: =R77-N77 -> -2 | C77: =IF(B77>=5,"SMASH BUY",IF(B77>=2,"BUY",IF(B77>=-1,"NEUTRAL",IF(B77>=-4,"AVOID","DO NOT BID")))) -> AVOID | D77: =IF(COUNTIFS('Auction Log'!$B$5:$B$304,A77,'Auction Log'!$D$5:$D$304,"<>",'Auction Log'!$E$5:$E$304,">0")=0,"Available",IFERROR(INDEX('Auction Log'!$D$5:$D$304,MATCH(1,('Auction Log'!$B$5:$B$304=A77)*('Auction Log'!$D$5:$D$304<>"")*('Auction Log'!$E$5:$E$304>0),0)),"SOLD")) -> Available | E77: =IF(COUNTIFS('Auction Log'!$B$5:$B$304,A77,'Auction Log'!$D$5:$D$304,"<>",'Auction Log'!$E$5:$E$304,">0")=0,"",IFERROR(INDEX('Auction Log'!$E$5:$E$304,MATCH(1,('Auction Log'!$B$5:$B$304=A77)*('Auction Log'!$D$5:$D$304<>"")*('Auction Log'!$E$5:$E$304>0),0)),"")) | F77: ATL | G77: TE | H77: 11 | I77: 81 | J77: 7 | K77: 196 | L77: 185 | M77: 6 | N77: 16 | O77: -4 | P77: 1 | Q77: 0 | R77: 14 | S77: 12 | T77: TARGET | V77: =IF(E77="","",R77-E77) | W77: YES | X77: =IF(AND(D77="Available",R77>=55),ROW(),9999) -> 9999 | Y77: =IF(AND(D77="Available",R77>=40,R77<55),ROW(),9999) -> 9999 | Z77: =IF(AND(D77="Available",R77>=25,R77<40),ROW(),9999) -> 9999 | AA77: =IF(K77="","",IF(L77="",K77,ROUND(AVERAGE(K77,L77),0))) -> 191
A78: Alec Pierce | B78: =R78-N78 -> -2 | C78: =IF(B78>=5,"SMASH BUY",IF(B78>=2,"BUY",IF(B78>=-1,"NEUTRAL",IF(B78>=-4,"AVOID","DO NOT BID")))) -> AVOID | D78: =IF(COUNTIFS('Auction Log'!$B$5:$B$304,A78,'Auction Log'!$D$5:$D$304,"<>",'Auction Log'!$E$5:$E$304,">0")=0,"Available",IFERROR(INDEX('Auction Log'!$D$5:$D$304,MATCH(1,('Auction Log'!$B$5:$B$304=A78)*('Auction Log'!$D$5:$D$304<>"")*('Auction Log'!$E$5:$E$304>0),0)),"SOLD")) -> Available | E78: =IF(COUNTIFS('Auction Log'!$B$5:$B$304,A78,'Auction Log'!$D$5:$D$304,"<>",'Auction Log'!$E$5:$E$304,">0")=0,"",IFERROR(INDEX('Auction Log'!$E$5:$E$304,MATCH(1,('Auction Log'!$B$5:$B$304=A78)*('Auction Log'!$D$5:$D$304<>"")*('Auction Log'!$E$5:$E$304>0),0)),"")) | F78: IND | G78: WR | H78: 13 | I78: 100 | J78: 8 | K78: 192 | L78: 187 | M78: 6 | N78: 16 | O78: -4 | P78: 1 | Q78: 0 | R78: 14 | S78: 12 | T78: HOLD | U78: Ankle - will not return during training camp but is "moving around well" (8/19) | V78: =IF(E78="","",R78-E78) | W78: YES | X78: =IF(AND(D78="Available",R78>=55),ROW(),9999) -> 9999 | Y78: =IF(AND(D78="Available",R78>=40,R78<55),ROW(),9999) -> 9999 | Z78: =IF(AND(D78="Available",R78>=25,R78<40),ROW(),9999) -> 9999 | AA78: =IF(K78="","",IF(L78="",K78,ROUND(AVERAGE(K78,L78),0))) -> 190
A79: Dak Prescott | B79: =R79-N79 -> 4 | C79: =IF(B79>=5,"SMASH BUY",IF(B79>=2,"BUY",IF(B79>=-1,"NEUTRAL",IF(B79>=-4,"AVOID","DO NOT BID")))) -> BUY | D79: =IF(COUNTIFS('Auction Log'!$B$5:$B$304,A79,'Auction Log'!$D$5:$D$304,"<>",'Auction Log'!$E$5:$E$304,">0")=0,"Available",IFERROR(INDEX('Auction Log'!$D$5:$D$304,MATCH(1,('Auction Log'!$B$5:$B$304=A79)*('Auction Log'!$D$5:$D$304<>"")*('Auction Log'!$E$5:$E$304>0),0)),"SOLD")) -> Available | E79: =IF(COUNTIFS('Auction Log'!$B$5:$B$304,A79,'Auction Log'!$D$5:$D$304,"<>",'Auction Log'!$E$5:$E$304,">0")=0,"",IFERROR(INDEX('Auction Log'!$E$5:$E$304,MATCH(1,('Auction Log'!$B$5:$B$304=A79)*('Auction Log'!$D$5:$D$304<>"")*('Auction Log'!$E$5:$E$304>0),0)),"")) | F79: DAL | G79: QB | H79: 14 | I79: 76 | J79: 7 | K79: 306 | L79: 287 | M79: 4 | N79: 9 | O79: 2 | P79: 1 | Q79: 0 | R79: 13 | S79: 11 | T79: TARGET | V79: =IF(E79="","",R79-E79) | W79: YES | X79: =IF(AND(D79="Available",R79>=55),ROW(),9999) -> 9999 | Y79: =IF(AND(D79="Available",R79>=40,R79<55),ROW(),9999) -> 9999 | Z79: =IF(AND(D79="Available",R79>=25,R79<40),ROW(),9999) -> 9999 | AA79: =IF(K79="","",IF(L79="",K79,ROUND(AVERAGE(K79,L79),0))) -> 297
A80: Rhamondre Stevenson | B80: =R80-N80 -> -2 | C80: =IF(B80>=5,"SMASH BUY",IF(B80>=2,"BUY",IF(B80>=-1,"NEUTRAL",IF(B80>=-4,"AVOID","DO NOT BID")))) -> AVOID | D80: =IF(COUNTIFS('Auction Log'!$B$5:$B$304,A80,'Auction Log'!$D$5:$D$304,"<>",'Auction Log'!$E$5:$E$304,">0")=0,"Available",IFERROR(INDEX('Auction Log'!$D$5:$D$304,MATCH(1,('Auction Log'!$B$5:$B$304=A80)*('Auction Log'!$D$5:$D$304<>"")*('Auction Log'!$E$5:$E$304>0),0)),"SOLD")) -> Available | E80: =IF(COUNTIFS('Auction Log'!$B$5:$B$304,A80,'Auction Log'!$D$5:$D$304,"<>",'Auction Log'!$E$5:$E$304,">0")=0,"",IFERROR(INDEX('Auction Log'!$E$5:$E$304,MATCH(1,('Auction Log'!$B$5:$B$304=A80)*('Auction Log'!$D$5:$D$304<>"")*('Auction Log'!$E$5:$E$304>0),0)),"")) | F80: NE | G80: RB | H80: 11 | I80: 79 | J80: 7 | K80: 191 | L80: 203 | M80: 7 | N80: 15 | O80: -3 | P80: 0 | Q80: 0 | R80: 13 | S80: 11 | T80: TARGET | V80: =IF(E80="","",R80-E80) | W80: YES | X80: =IF(AND(D80="Available",R80>=55),ROW(),9999) -> 9999 | Y80: =IF(AND(D80="Available",R80>=40,R80<55),ROW(),9999) -> 9999 | Z80: =IF(AND(D80="Available",R80>=25,R80<40),ROW(),9999) -> 9999 | AA80: =IF(K80="","",IF(L80="",K80,ROUND(AVERAGE(K80,L80),0))) -> 197
A81: Michael Pittman Jr. | B81: =R81-N81 -> -3 | C81: =IF(B81>=5,"SMASH BUY",IF(B81>=2,"BUY",IF(B81>=-1,"NEUTRAL",IF(B81>=-4,"AVOID","DO NOT BID")))) -> AVOID | D81: =IF(COUNTIFS('Auction Log'!$B$5:$B$304,A81,'Auction Log'!$D$5:$D$304,"<>",'Auction Log'!$E$5:$E$304,">0")=0,"Available",IFERROR(INDEX('Auction Log'!$D$5:$D$304,MATCH(1,('Auction Log'!$B$5:$B$304=A81)*('Auction Log'!$D$5:$D$304<>"")*('Auction Log'!$E$5:$E$304>0),0)),"SOLD")) -> Available | E81: =IF(COUNTIFS('Auction Log'!$B$5:$B$304,A81,'Auction Log'!$D$5:$D$304,"<>",'Auction Log'!$E$5:$E$304,">0")=0,"",IFERROR(INDEX('Auction Log'!$E$5:$E$304,MATCH(1,('Auction Log'!$B$5:$B$304=A81)*('Auction Log'!$D$5:$D$304<>"")*('Auction Log'!$E$5:$E$304>0),0)),"")) | F81: PIT | G81: WR | H81: 9 | I81: 80 | J81: 7 | K81: 190 | L81: 197 | M81: 7 | N81: 16 | O81: -4 | P81: 0 | Q81: 0 | R81: 13 | S81: 11 | T81: HOLD | U81: Hamstring - no concern that he will miss Week 1 (8/24) | V81: =IF(E81="","",R81-E81) | W81: YES | X81: =IF(AND(D81="Available",R81>=55),ROW(),9999) -> 9999 | Y81: =IF(AND(D81="Available",R81>=40,R81<55),ROW(),9999) -> 9999 | Z81: =IF(AND(D81="Available",R81>=25,R81<40),ROW(),9999) -> 9999 | AA81: =IF(K81="","",IF(L81="",K81,ROUND(AVERAGE(K81,L81),0))) -> 194
A82: Tony Pollard | B82: =R82-N82 -> -1 | C82: =IF(B82>=5,"SMASH BUY",IF(B82>=2,"BUY",IF(B82>=-1,"NEUTRAL",IF(B82>=-4,"AVOID","DO NOT BID")))) -> NEUTRAL | D82: =IF(COUNTIFS('Auction Log'!$B$5:$B$304,A82,'Auction Log'!$D$5:$D$304,"<>",'Auction Log'!$E$5:$E$304,">0")=0,"Available",IFERROR(INDEX('Auction Log'!$D$5:$D$304,MATCH(1,('Auction Log'!$B$5:$B$304=A82)*('Auction Log'!$D$5:$D$304<>"")*('Auction Log'!$E$5:$E$304>0),0)),"SOLD")) -> Available | E82: =IF(COUNTIFS('Auction Log'!$B$5:$B$304,A82,'Auction Log'!$D$5:$D$304,"<>",'Auction Log'!$E$5:$E$304,">0")=0,"",IFERROR(INDEX('Auction Log'!$E$5:$E$304,MATCH(1,('Auction Log'!$B$5:$B$304=A82)*('Auction Log'!$D$5:$D$304<>"")*('Auction Log'!$E$5:$E$304>0),0)),"")) | F82: TEN | G82: RB | H82: 9 | I82: 83 | J82: 7 | K82: 188 | L82: 186 | M82: 2 | N82: 14 | O82: -3 | P82: 1 | Q82: 0 | R82: 13 | S82: 11 | T82: HOLD | V82: =IF(E82="","",R82-E82) | W82: YES | X82: =IF(AND(D82="Available",R82>=55),ROW(),9999) -> 9999 | Y82: =IF(AND(D82="Available",R82>=40,R82<55),ROW(),9999) -> 9999 | Z82: =IF(AND(D82="Available",R82>=25,R82<40),ROW(),9999) -> 9999 | AA82: =IF(K82="","",IF(L82="",K82,ROUND(AVERAGE(K82,L82),0))) -> 187
A83: Trevor Lawrence | B83: =R83-N83 -> 3 | C83: =IF(B83>=5,"SMASH BUY",IF(B83>=2,"BUY",IF(B83>=-1,"NEUTRAL",IF(B83>=-4,"AVOID","DO NOT BID")))) -> BUY | D83: =IF(COUNTIFS('Auction Log'!$B$5:$B$304,A83,'Auction Log'!$D$5:$D$304,"<>",'Auction Log'!$E$5:$E$304,">0")=0,"Available",IFERROR(INDEX('Auction Log'!$D$5:$D$304,MATCH(1,('Auction Log'!$B$5:$B$304=A83)*('Auction Log'!$D$5:$D$304<>"")*('Auction Log'!$E$5:$E$304>0),0)),"SOLD")) -> Available | E83: =IF(COUNTIFS('Auction Log'!$B$5:$B$304,A83,'Auction Log'!$D$5:$D$304,"<>",'Auction Log'!$E$5:$E$304,">0")=0,"",IFERROR(INDEX('Auction Log'!$E$5:$E$304,MATCH(1,('Auction Log'!$B$5:$B$304=A83)*('Auction Log'!$D$5:$D$304<>"")*('Auction Log'!$E$5:$E$304>0),0)),"")) | F83: JAC | G83: QB | H83: 7 | I83: 75 | J83: 7 | K83: 306 | L83: 288 | M83: 4 | N83: 9 | O83: 2 | P83: 0 | Q83: 0 | R83: 12 | S83: 10 | T83: TARGET | V83: =IF(E83="","",R83-E83) | W83: YES | X83: =IF(AND(D83="Available",R83>=55),ROW(),9999) -> 9999 | Y83: =IF(AND(D83="Available",R83>=40,R83<55),ROW(),9999) -> 9999 | Z83: =IF(AND(D83="Available",R83>=25,R83<40),ROW(),9999) -> 9999 | AA83: =IF(K83="","",IF(L83="",K83,ROUND(AVERAGE(K83,L83),0))) -> 297
A84: Brian Thomas Jr. | B84: =R84-N84 -> -1 | C84: =IF(B84>=5,"SMASH BUY",IF(B84>=2,"BUY",IF(B84>=-1,"NEUTRAL",IF(B84>=-4,"AVOID","DO NOT BID")))) -> NEUTRAL | D84: =IF(COUNTIFS('Auction Log'!$B$5:$B$304,A84,'Auction Log'!$D$5:$D$304,"<>",'Auction Log'!$E$5:$E$304,">0")=0,"Available",IFERROR(INDEX('Auction Log'!$D$5:$D$304,MATCH(1,('Auction Log'!$B$5:$B$304=A84)*('Auction Log'!$D$5:$D$304<>"")*('Auction Log'!$E$5:$E$304>0),0)),"SOLD")) -> Available | E84: =IF(COUNTIFS('Auction Log'!$B$5:$B$304,A84,'Auction Log'!$D$5:$D$304,"<>",'Auction Log'!$E$5:$E$304,">0")=0,"",IFERROR(INDEX('Auction Log'!$E$5:$E$304,MATCH(1,('Auction Log'!$B$5:$B$304=A84)*('Auction Log'!$D$5:$D$304<>"")*('Auction Log'!$E$5:$E$304>0),0)),"")) | F84: JAC | G84: WR | H84: 7 | I84: 77 | J84: 7 | K84: 181 | L84: 177 | M84: 4 | N84: 13 | O84: -2 | P84: 0 | Q84: 0 | R84: 12 | S84: 10 | T84: HOLD | V84: =IF(E84="","",R84-E84) | W84: YES | X84: =IF(AND(D84="Available",R84>=55),ROW(),9999) -> 9999 | Y84: =IF(AND(D84="Available",R84>=40,R84<55),ROW(),9999) -> 9999 | Z84: =IF(AND(D84="Available",R84>=25,R84<40),ROW(),9999) -> 9999 | AA84: =IF(K84="","",IF(L84="",K84,ROUND(AVERAGE(K84,L84),0))) -> 179
A85: Rico Dowdle | B85: =R85-N85 -> -1 | C85: =IF(B85>=5,"SMASH BUY",IF(B85>=2,"BUY",IF(B85>=-1,"NEUTRAL",IF(B85>=-4,"AVOID","DO NOT BID")))) -> NEUTRAL | D85: =IF(COUNTIFS('Auction Log'!$B$5:$B$304,A85,'Auction Log'!$D$5:$D$304,"<>",'Auction Log'!$E$5:$E$304,">0")=0,"Available",IFERROR(INDEX('Auction Log'!$D$5:$D$304,MATCH(1,('Auction Log'!$B$5:$B$304=A85)*('Auction Log'!$D$5:$D$304<>"")*('Auction Log'!$E$5:$E$304>0),0)),"SOLD")) -> Available | E85: =IF(COUNTIFS('Auction Log'!$B$5:$B$304,A85,'Auction Log'!$D$5:$D$304,"<>",'Auction Log'!$E$5:$E$304,">0")=0,"",IFERROR(INDEX('Auction Log'!$E$5:$E$304,MATCH(1,('Auction Log'!$B$5:$B$304=A85)*('Auction Log'!$D$5:$D$304<>"")*('Auction Log'!$E$5:$E$304>0),0)),"")) | F85: PIT | G85: RB | H85: 9 | I85: 88 | J85: 7 | K85: 180 | L85: 186 | M85: 2 | N85: 13 | O85: -3 | P85: 1 | Q85: 0 | R85: 12 | S85: 10 | T85: HOLD | V85: =IF(E85="","",R85-E85) | W85: YES | X85: =IF(AND(D85="Available",R85>=55),ROW(),9999) -> 9999 | Y85: =IF(AND(D85="Available",R85>=40,R85<55),ROW(),9999) -> 9999 | Z85: =IF(AND(D85="Available",R85>=25,R85<40),ROW(),9999) -> 9999 | AA85: =IF(K85="","",IF(L85="",K85,ROUND(AVERAGE(K85,L85),0))) -> 183
A86: Brock Purdy | B86: =R86-N86 -> 2 | C86: =IF(B86>=5,"SMASH BUY",IF(B86>=2,"BUY",IF(B86>=-1,"NEUTRAL",IF(B86>=-4,"AVOID","DO NOT BID")))) -> BUY | D86: =IF(COUNTIFS('Auction Log'!$B$5:$B$304,A86,'Auction Log'!$D$5:$D$304,"<>",'Auction Log'!$E$5:$E$304,">0")=0,"Available",IFERROR(INDEX('Auction Log'!$D$5:$D$304,MATCH(1,('Auction Log'!$B$5:$B$304=A86)*('Auction Log'!$D$5:$D$304<>"")*('Auction Log'!$E$5:$E$304>0),0)),"SOLD")) -> Available | E86: =IF(COUNTIFS('Auction Log'!$B$5:$B$304,A86,'Auction Log'!$D$5:$D$304,"<>",'Auction Log'!$E$5:$E$304,">0")=0,"",IFERROR(INDEX('Auction Log'!$E$5:$E$304,MATCH(1,('Auction Log'!$B$5:$B$304=A86)*('Auction Log'!$D$5:$D$304<>"")*('Auction Log'!$E$5:$E$304>0),0)),"")) | F86: SF | G86: QB | H86: 8 | I86: 91 | J86: 7 | K86: 308 | L86: 292 | M86: 4 | N86: 10 | O86: 0 | P86: 1 | Q86: 0 | R86: 12 | S86: 10 | T86: HOLD | V86: =IF(E86="","",R86-E86) | W86: YES | X86: =IF(AND(D86="Available",R86>=55),ROW(),9999) -> 9999 | Y86: =IF(AND(D86="Available",R86>=40,R86<55),ROW(),9999) -> 9999 | Z86: =IF(AND(D86="Available",R86>=25,R86<40),ROW(),9999) -> 9999 | AA86: =IF(K86="","",IF(L86="",K86,ROUND(AVERAGE(K86,L86),0))) -> 300
A87: Caleb Williams | B87: =R87-N87 -> 2 | C87: =IF(B87>=5,"SMASH BUY",IF(B87>=2,"BUY",IF(B87>=-1,"NEUTRAL",IF(B87>=-4,"AVOID","DO NOT BID")))) -> BUY | D87: =IF(COUNTIFS('Auction Log'!$B$5:$B$304,A87,'Auction Log'!$D$5:$D$304,"<>",'Auction Log'!$E$5:$E$304,">0")=0,"Available",IFERROR(INDEX('Auction Log'!$D$5:$D$304,MATCH(1,('Auction Log'!$B$5:$B$304=A87)*('Auction Log'!$D$5:$D$304<>"")*('Auction Log'!$E$5:$E$304>0),0)),"SOLD")) -> Available | E87: =IF(COUNTIFS('Auction Log'!$B$5:$B$304,A87,'Auction Log'!$D$5:$D$304,"<>",'Auction Log'!$E$5:$E$304,">0")=0,"",IFERROR(INDEX('Auction Log'!$E$5:$E$304,MATCH(1,('Auction Log'!$B$5:$B$304=A87)*('Auction Log'!$D$5:$D$304<>"")*('Auction Log'!$E$5:$E$304>0),0)),"")) | F87: CHI | G87: QB | H87: 10 | I87: 65 | J87: 6 | K87: 301 | L87: 281 | M87: 3 | N87: 8 | O87: 3 | P87: -1 | Q87: 0 | R87: 10 | S87: 8 | T87: TARGET | V87: =IF(E87="","",R87-E87) | W87: YES | X87: =IF(AND(D87="Available",R87>=55),ROW(),9999) -> 9999 | Y87: =IF(AND(D87="Available",R87>=40,R87<55),ROW(),9999) -> 9999 | Z87: =IF(AND(D87="Available",R87>=25,R87<40),ROW(),9999) -> 9999 | AA87: =IF(K87="","",IF(L87="",K87,ROUND(AVERAGE(K87,L87),0))) -> 291
A88: Justin Herbert | B88: =R88-N88 -> 3 | C88: =IF(B88>=5,"SMASH BUY",IF(B88>=2,"BUY",IF(B88>=-1,"NEUTRAL",IF(B88>=-4,"AVOID","DO NOT BID")))) -> BUY | D88: =IF(COUNTIFS('Auction Log'!$B$5:$B$304,A88,'Auction Log'!$D$5:$D$304,"<>",'Auction Log'!$E$5:$E$304,">0")=0,"Available",IFERROR(INDEX('Auction Log'!$D$5:$D$304,MATCH(1,('Auction Log'!$B$5:$B$304=A88)*('Auction Log'!$D$5:$D$304<>"")*('Auction Log'!$E$5:$E$304>0),0)),"SOLD")) -> Available | E88: =IF(COUNTIFS('Auction Log'!$B$5:$B$304,A88,'Auction Log'!$D$5:$D$304,"<>",'Auction Log'!$E$5:$E$304,">0")=0,"",IFERROR(INDEX('Auction Log'!$E$5:$E$304,MATCH(1,('Auction Log'!$B$5:$B$304=A88)*('Auction Log'!$D$5:$D$304<>"")*('Auction Log'!$E$5:$E$304>0),0)),"")) | F88: LAC | G88: QB | H88: 7 | I88: 69 | J88: 6 | K88: 300 | L88: 283 | M88: 3 | N88: 7 | O88: 3 | P88: 0 | Q88: 0 | R88: 10 | S88: 8 | T88: TARGET | V88: =IF(E88="","",R88-E88) | W88: YES | X88: =IF(AND(D88="Available",R88>=55),ROW(),9999) -> 9999 | Y88: =IF(AND(D88="Available",R88>=40,R88<55),ROW(),9999) -> 9999 | Z88: =IF(AND(D88="Available",R88>=25,R88<40),ROW(),9999) -> 9999 | AA88: =IF(K88="","",IF(L88="",K88,ROUND(AVERAGE(K88,L88),0))) -> 292
A89: J.K. Dobbins | B89: =R89-N89 -> -2 | C89: =IF(B89>=5,"SMASH BUY",IF(B89>=2,"BUY",IF(B89>=-1,"NEUTRAL",IF(B89>=-4,"AVOID","DO NOT BID")))) -> AVOID | D89: =IF(COUNTIFS('Auction Log'!$B$5:$B$304,A89,'Auction Log'!$D$5:$D$304,"<>",'Auction Log'!$E$5:$E$304,">0")=0,"Available",IFERROR(INDEX('Auction Log'!$D$5:$D$304,MATCH(1,('Auction Log'!$B$5:$B$304=A89)*('Auction Log'!$D$5:$D$304<>"")*('Auction Log'!$E$5:$E$304>0),0)),"SOLD")) -> Available | E89: =IF(COUNTIFS('Auction Log'!$B$5:$B$304,A89,'Auction Log'!$D$5:$D$304,"<>",'Auction Log'!$E$5:$E$304,">0")=0,"",IFERROR(INDEX('Auction Log'!$E$5:$E$304,MATCH(1,('Auction Log'!$B$5:$B$304=A89)*('Auction Log'!$D$5:$D$304<>"")*('Auction Log'!$E$5:$E$304>0),0)),"")) | F89: DEN | G89: RB | H89: 10 | I89: 98 | J89: 8 | K89: 176 | L89: 175 | M89: 2 | N89: 12 | O89: -3 | P89: 1 | Q89: 0 | R89: 10 | S89: 8 | T89: HOLD | V89: =IF(E89="","",R89-E89) | W89: YES | X89: =IF(AND(D89="Available",R89>=55),ROW(),9999) -> 9999 | Y89: =IF(AND(D89="Available",R89>=40,R89<55),ROW(),9999) -> 9999 | Z89: =IF(AND(D89="Available",R89>=25,R89<40),ROW(),9999) -> 9999 | AA89: =IF(K89="","",IF(L89="",K89,ROUND(AVERAGE(K89,L89),0))) -> 176
A90: Matthew Stafford | B90: =R90-N90 -> 4 | C90: =IF(B90>=5,"SMASH BUY",IF(B90>=2,"BUY",IF(B90>=-1,"NEUTRAL",IF(B90>=-4,"AVOID","DO NOT BID")))) -> BUY | D90: =IF(COUNTIFS('Auction Log'!$B$5:$B$304,A90,'Auction Log'!$D$5:$D$304,"<>",'Auction Log'!$E$5:$E$304,">0")=0,"Available",IFERROR(INDEX('Auction Log'!$D$5:$D$304,MATCH(1,('Auction Log'!$B$5:$B$304=A90)*('Auction Log'!$D$5:$D$304<>"")*('Auction Log'!$E$5:$E$304>0),0)),"SOLD")) -> Available | E90: =IF(COUNTIFS('Auction Log'!$B$5:$B$304,A90,'Auction Log'!$D$5:$D$304,"<>",'Auction Log'!$E$5:$E$304,">0")=0,"",IFERROR(INDEX('Auction Log'!$E$5:$E$304,MATCH(1,('Auction Log'!$B$5:$B$304=A90)*('Auction Log'!$D$5:$D$304<>"")*('Auction Log'!$E$5:$E$304>0),0)),"")) | F90: LAR | G90: QB | H90: 11 | I90: 104 | J90: 8 | K90: 294 | L90: 293 | M90: 4 | N90: 6 | O90: 2 | P90: 2 | Q90: 0 | R90: 10 | S90: 8 | T90: TARGET | V90: =IF(E90="","",R90-E90) | W90: YES | X90: =IF(AND(D90="Available",R90>=55),ROW(),9999) -> 9999 | Y90: =IF(AND(D90="Available",R90>=40,R90<55),ROW(),9999) -> 9999 | Z90: =IF(AND(D90="Available",R90>=25,R90<40),ROW(),9999) -> 9999 | AA90: =IF(K90="","",IF(L90="",K90,ROUND(AVERAGE(K90,L90),0))) -> 294
A91: Chris Godwin Jr. | B91: =R91-N91 -> -2 | C91: =IF(B91>=5,"SMASH BUY",IF(B91>=2,"BUY",IF(B91>=-1,"NEUTRAL",IF(B91>=-4,"AVOID","DO NOT BID")))) -> AVOID | D91: =IF(COUNTIFS('Auction Log'!$B$5:$B$304,A91,'Auction Log'!$D$5:$D$304,"<>",'Auction Log'!$E$5:$E$304,">0")=0,"Available",IFERROR(INDEX('Auction Log'!$D$5:$D$304,MATCH(1,('Auction Log'!$B$5:$B$304=A91)*('Auction Log'!$D$5:$D$304<>"")*('Auction Log'!$E$5:$E$304>0),0)),"SOLD")) -> Available | E91: =IF(COUNTIFS('Auction Log'!$B$5:$B$304,A91,'Auction Log'!$D$5:$D$304,"<>",'Auction Log'!$E$5:$E$304,">0")=0,"",IFERROR(INDEX('Auction Log'!$E$5:$E$304,MATCH(1,('Auction Log'!$B$5:$B$304=A91)*('Auction Log'!$D$5:$D$304<>"")*('Auction Log'!$E$5:$E$304>0),0)),"")) | F91: TB | G91: WR | H91: 10 | I91: 73 | J91: 7 | K91: 176 | L91: 157 | M91: 1 | N91: 11 | O91: -1 | P91: -1 | Q91: 0 | R91: 9 | S91: 8 | T91: HOLD | V91: =IF(E91="","",R91-E91) | W91: YES | X91: =IF(AND(D91="Available",R91>=55),ROW(),9999) -> 9999 | Y91: =IF(AND(D91="Available",R91>=40,R91<55),ROW(),9999) -> 9999 | Z91: =IF(AND(D91="Available",R91>=25,R91<40),ROW(),9999) -> 9999 | AA91: =IF(K91="","",IF(L91="",K91,ROUND(AVERAGE(K91,L91),0))) -> 167
A92: Sam LaPorta | B92: =R92-N92 -> -2 | C92: =IF(B92>=5,"SMASH BUY",IF(B92>=2,"BUY",IF(B92>=-1,"NEUTRAL",IF(B92>=-4,"AVOID","DO NOT BID")))) -> AVOID | D92: =IF(COUNTIFS('Auction Log'!$B$5:$B$304,A92,'Auction Log'!$D$5:$D$304,"<>",'Auction Log'!$E$5:$E$304,">0")=0,"Available",IFERROR(INDEX('Auction Log'!$D$5:$D$304,MATCH(1,('Auction Log'!$B$5:$B$304=A92)*('Auction Log'!$D$5:$D$304<>"")*('Auction Log'!$E$5:$E$304>0),0)),"SOLD")) -> Available | E92: =IF(COUNTIFS('Auction Log'!$B$5:$B$304,A92,'Auction Log'!$D$5:$D$304,"<>",'Auction Log'!$E$5:$E$304,">0")=0,"",IFERROR(INDEX('Auction Log'!$E$5:$E$304,MATCH(1,('Auction Log'!$B$5:$B$304=A92)*('Auction Log'!$D$5:$D$304<>"")*('Auction Log'!$E$5:$E$304>0),0)),"")) | F92: DET | G92: TE | H92: 6 | I92: 84 | J92: 7 | K92: 180 | L92: 189 | M92: 6 | N92: 11 | O92: 0 | P92: 0 | Q92: 2 | R92: 9 | S92: 8 | T92: DRAIN | U92: Hip - returned to practice 8/25 (ESPN). Prior 'uncertain' note stale; OK near Target. | V92: =IF(E92="","",R92-E92) | W92: YES | X92: =IF(AND(D92="Available",R92>=55),ROW(),9999) -> 9999 | Y92: =IF(AND(D92="Available",R92>=40,R92<55),ROW(),9999) -> 9999 | Z92: =IF(AND(D92="Available",R92>=25,R92<40),ROW(),9999) -> 9999 | AA92: =IF(K92="","",IF(L92="",K92,ROUND(AVERAGE(K92,L92),0))) -> 185
A93: Wan'Dale Robinson | B93: =R93-N93 -> -3 | C93: =IF(B93>=5,"SMASH BUY",IF(B93>=2,"BUY",IF(B93>=-1,"NEUTRAL",IF(B93>=-4,"AVOID","DO NOT BID")))) -> AVOID | D93: =IF(COUNTIFS('Auction Log'!$B$5:$B$304,A93,'Auction Log'!$D$5:$D$304,"<>",'Auction Log'!$E$5:$E$304,">0")=0,"Available",IFERROR(INDEX('Auction Log'!$D$5:$D$304,MATCH(1,('Auction Log'!$B$5:$B$304=A93)*('Auction Log'!$D$5:$D$304<>"")*('Auction Log'!$E$5:$E$304>0),0)),"SOLD")) -> Available | E93: =IF(COUNTIFS('Auction Log'!$B$5:$B$304,A93,'Auction Log'!$D$5:$D$304,"<>",'Auction Log'!$E$5:$E$304,">0")=0,"",IFERROR(INDEX('Auction Log'!$E$5:$E$304,MATCH(1,('Auction Log'!$B$5:$B$304=A93)*('Auction Log'!$D$5:$D$304<>"")*('Auction Log'!$E$5:$E$304>0),0)),"")) | F93: TEN | G93: WR | H93: 9 | I93: 85 | J93: 7 | K93: 179 | L93: 175 | M93: 3 | N93: 12 | O93: -3 | P93: 0 | Q93: 0 | R93: 9 | S93: 8 | T93: TARGET | V93: =IF(E93="","",R93-E93) | W93: YES | X93: =IF(AND(D93="Available",R93>=55),ROW(),9999) -> 9999 | Y93: =IF(AND(D93="Available",R93>=40,R93<55),ROW(),9999) -> 9999 | Z93: =IF(AND(D93="Available",R93>=25,R93<40),ROW(),9999) -> 9999 | AA93: =IF(K93="","",IF(L93="",K93,ROUND(AVERAGE(K93,L93),0))) -> 177
A94: Michael Wilson | B94: =R94-N94 -> -3 | C94: =IF(B94>=5,"SMASH BUY",IF(B94>=2,"BUY",IF(B94>=-1,"NEUTRAL",IF(B94>=-4,"AVOID","DO NOT BID")))) -> AVOID | D94: =IF(COUNTIFS('Auction Log'!$B$5:$B$304,A94,'Auction Log'!$D$5:$D$304,"<>",'Auction Log'!$E$5:$E$304,">0")=0,"Available",IFERROR(INDEX('Auction Log'!$D$5:$D$304,MATCH(1,('Auction Log'!$B$5:$B$304=A94)*('Auction Log'!$D$5:$D$304<>"")*('Auction Log'!$E$5:$E$304>0),0)),"SOLD")) -> Available | E94: =IF(COUNTIFS('Auction Log'!$B$5:$B$304,A94,'Auction Log'!$D$5:$D$304,"<>",'Auction Log'!$E$5:$E$304,">0")=0,"",IFERROR(INDEX('Auction Log'!$E$5:$E$304,MATCH(1,('Auction Log'!$B$5:$B$304=A94)*('Auction Log'!$D$5:$D$304<>"")*('Auction Log'!$E$5:$E$304>0),0)),"")) | F94: ARI | G94: WR | H94: 14 | I94: 87 | J94: 7 | K94: 177 | L94: 177 | M94: 4 | N94: 12 | O94: -3 | P94: 0 | Q94: 0 | R94: 9 | S94: 8 | T94: TARGET | V94: =IF(E94="","",R94-E94) | W94: YES | X94: =IF(AND(D94="Available",R94>=55),ROW(),9999) -> 9999 | Y94: =IF(AND(D94="Available",R94>=40,R94<55),ROW(),9999) -> 9999 | Z94: =IF(AND(D94="Available",R94>=25,R94<40),ROW(),9999) -> 9999 | AA94: =IF(K94="","",IF(L94="",K94,ROUND(AVERAGE(K94,L94),0))) -> 177
A95: Jonathon Brooks | B95: =R95-N95 -> -1 | C95: =IF(B95>=5,"SMASH BUY",IF(B95>=2,"BUY",IF(B95>=-1,"NEUTRAL",IF(B95>=-4,"AVOID","DO NOT BID")))) -> NEUTRAL | D95: =IF(COUNTIFS('Auction Log'!$B$5:$B$304,A95,'Auction Log'!$D$5:$D$304,"<>",'Auction Log'!$E$5:$E$304,">0")=0,"Available",IFERROR(INDEX('Auction Log'!$D$5:$D$304,MATCH(1,('Auction Log'!$B$5:$B$304=A95)*('Auction Log'!$D$5:$D$304<>"")*('Auction Log'!$E$5:$E$304>0),0)),"SOLD")) -> Available | E95: =IF(COUNTIFS('Auction Log'!$B$5:$B$304,A95,'Auction Log'!$D$5:$D$304,"<>",'Auction Log'!$E$5:$E$304,">0")=0,"",IFERROR(INDEX('Auction Log'!$E$5:$E$304,MATCH(1,('Auction Log'!$B$5:$B$304=A95)*('Auction Log'!$D$5:$D$304<>"")*('Auction Log'!$E$5:$E$304>0),0)),"")) | F95: CAR | G95: RB | H95: 5 | I95: 89 | J95: 7 | K95: 164 | L95: 171 | M95: 2 | N95: 10 | O95: -1 | P95: 0 | Q95: 0 | R95: 9 | S95: 8 | T95: HOLD | V95: =IF(E95="","",R95-E95) | W95: YES | X95: =IF(AND(D95="Available",R95>=55),ROW(),9999) -> 9999 | Y95: =IF(AND(D95="Available",R95>=40,R95<55),ROW(),9999) -> 9999 | Z95: =IF(AND(D95="Available",R95>=25,R95<40),ROW(),9999) -> 9999 | AA95: =IF(K95="","",IF(L95="",K95,ROUND(AVERAGE(K95,L95),0))) -> 168
A96: RJ Harvey | B96: =R96-N96 -> -1 | C96: =IF(B96>=5,"SMASH BUY",IF(B96>=2,"BUY",IF(B96>=-1,"NEUTRAL",IF(B96>=-4,"AVOID","DO NOT BID")))) -> NEUTRAL | D96: =IF(COUNTIFS('Auction Log'!$B$5:$B$304,A96,'Auction Log'!$D$5:$D$304,"<>",'Auction Log'!$E$5:$E$304,">0")=0,"Available",IFERROR(INDEX('Auction Log'!$D$5:$D$304,MATCH(1,('Auction Log'!$B$5:$B$304=A96)*('Auction Log'!$D$5:$D$304<>"")*('Auction Log'!$E$5:$E$304>0),0)),"SOLD")) -> Available | E96: =IF(COUNTIFS('Auction Log'!$B$5:$B$304,A96,'Auction Log'!$D$5:$D$304,"<>",'Auction Log'!$E$5:$E$304,">0")=0,"",IFERROR(INDEX('Auction Log'!$E$5:$E$304,MATCH(1,('Auction Log'!$B$5:$B$304=A96)*('Auction Log'!$D$5:$D$304<>"")*('Auction Log'!$E$5:$E$304>0),0)),"")) | F96: DEN | G96: RB | H96: 10 | I96: 90 | J96: 7 | K96: 162 | L96: 150 | M96: 1 | N96: 10 | O96: -1 | P96: 0 | Q96: 0 | R96: 9 | S96: 8 | T96: HOLD | V96: =IF(E96="","",R96-E96) | W96: YES | X96: =IF(AND(D96="Available",R96>=55),ROW(),9999) -> 9999 | Y96: =IF(AND(D96="Available",R96>=40,R96<55),ROW(),9999) -> 9999 | Z96: =IF(AND(D96="Available",R96>=25,R96<40),ROW(),9999) -> 9999 | AA96: =IF(K96="","",IF(L96="",K96,ROUND(AVERAGE(K96,L96),0))) -> 156
A97: Jaxson Dart | B97: =R97-N97 -> -2 | C97: =IF(B97>=5,"SMASH BUY",IF(B97>=2,"BUY",IF(B97>=-1,"NEUTRAL",IF(B97>=-4,"AVOID","DO NOT BID")))) -> AVOID | D97: =IF(COUNTIFS('Auction Log'!$B$5:$B$304,A97,'Auction Log'!$D$5:$D$304,"<>",'Auction Log'!$E$5:$E$304,">0")=0,"Available",IFERROR(INDEX('Auction Log'!$D$5:$D$304,MATCH(1,('Auction Log'!$B$5:$B$304=A97)*('Auction Log'!$D$5:$D$304<>"")*('Auction Log'!$E$5:$E$304>0),0)),"SOLD")) -> Available | E97: =IF(COUNTIFS('Auction Log'!$B$5:$B$304,A97,'Auction Log'!$D$5:$D$304,"<>",'Auction Log'!$E$5:$E$304,">0")=0,"",IFERROR(INDEX('Auction Log'!$E$5:$E$304,MATCH(1,('Auction Log'!$B$5:$B$304=A97)*('Auction Log'!$D$5:$D$304<>"")*('Auction Log'!$E$5:$E$304>0),0)),"")) | F97: NYG | G97: QB | H97: 8 | I97: 94 | J97: 7 | K97: 310 | L97: 300 | M97: 5 | N97: 11 | O97: -1 | P97: -1 | Q97: 0 | R97: 9 | S97: 8 | T97: HOLD | V97: =IF(E97="","",R97-E97) | W97: YES | X97: =IF(AND(D97="Available",R97>=55),ROW(),9999) -> 9999 | Y97: =IF(AND(D97="Available",R97>=40,R97<55),ROW(),9999) -> 9999 | Z97: =IF(AND(D97="Available",R97>=25,R97<40),ROW(),9999) -> 9999 | AA97: =IF(K97="","",IF(L97="",K97,ROUND(AVERAGE(K97,L97),0))) -> 305
A98: Travis Kelce | B98: =R98-N98 -> -3 | C98: =IF(B98>=5,"SMASH BUY",IF(B98>=2,"BUY",IF(B98>=-1,"NEUTRAL",IF(B98>=-4,"AVOID","DO NOT BID")))) -> AVOID | D98: =IF(COUNTIFS('Auction Log'!$B$5:$B$304,A98,'Auction Log'!$D$5:$D$304,"<>",'Auction Log'!$E$5:$E$304,">0")=0,"Available",IFERROR(INDEX('Auction Log'!$D$5:$D$304,MATCH(1,('Auction Log'!$B$5:$B$304=A98)*('Auction Log'!$D$5:$D$304<>"")*('Auction Log'!$E$5:$E$304>0),0)),"SOLD")) -> Available | E98: =IF(COUNTIFS('Auction Log'!$B$5:$B$304,A98,'Auction Log'!$D$5:$D$304,"<>",'Auction Log'!$E$5:$E$304,">0")=0,"",IFERROR(INDEX('Auction Log'!$E$5:$E$304,MATCH(1,('Auction Log'!$B$5:$B$304=A98)*('Auction Log'!$D$5:$D$304<>"")*('Auction Log'!$E$5:$E$304>0),0)),"")) | F98: KC | G98: TE | H98: 5 | I98: 95 | J98: 7 | K98: 182 | L98: 177 | M98: 2 | N98: 12 | O98: -3 | P98: 0 | Q98: 0 | R98: 9 | S98: 8 | T98: HOLD | V98: =IF(E98="","",R98-E98) | W98: YES | X98: =IF(AND(D98="Available",R98>=55),ROW(),9999) -> 9999 | Y98: =IF(AND(D98="Available",R98>=40,R98<55),ROW(),9999) -> 9999 | Z98: =IF(AND(D98="Available",R98>=25,R98<40),ROW(),9999) -> 9999 | AA98: =IF(K98="","",IF(L98="",K98,ROUND(AVERAGE(K98,L98),0))) -> 180
A99: George Kittle | B99: =R99-N99 -> -3 | C99: =IF(B99>=5,"SMASH BUY",IF(B99>=2,"BUY",IF(B99>=-1,"NEUTRAL",IF(B99>=-4,"AVOID","DO NOT BID")))) -> AVOID | D99: =IF(COUNTIFS('Auction Log'!$B$5:$B$304,A99,'Auction Log'!$D$5:$D$304,"<>",'Auction Log'!$E$5:$E$304,">0")=0,"Available",IFERROR(INDEX('Auction Log'!$D$5:$D$304,MATCH(1,('Auction Log'!$B$5:$B$304=A99)*('Auction Log'!$D$5:$D$304<>"")*('Auction Log'!$E$5:$E$304>0),0)),"SOLD")) -> Available | E99: =IF(COUNTIFS('Auction Log'!$B$5:$B$304,A99,'Auction Log'!$D$5:$D$304,"<>",'Auction Log'!$E$5:$E$304,">0")=0,"",IFERROR(INDEX('Auction Log'!$E$5:$E$304,MATCH(1,('Auction Log'!$B$5:$B$304=A99)*('Auction Log'!$D$5:$D$304<>"")*('Auction Log'!$E$5:$E$304>0),0)),"")) | F99: SF | G99: TE | H99: 8 | I99: 97 | J99: 7 | K99: 181 | L99: 177 | M99: 2 | N99: 12 | O99: -3 | P99: 0 | Q99: 0 | R99: 9 | S99: 8 | T99: HOLD | U99: Achilles - activated from PUP 8/23 (ESPN). Fine as cheap TE upside. | V99: =IF(E99="","",R99-E99) | W99: YES | X99: =IF(AND(D99="Available",R99>=55),ROW(),9999) -> 9999 | Y99: =IF(AND(D99="Available",R99>=40,R99<55),ROW(),9999) -> 9999 | Z99: =IF(AND(D99="Available",R99>=25,R99<40),ROW(),9999) -> 9999 | AA99: =IF(K99="","",IF(L99="",K99,ROUND(AVERAGE(K99,L99),0))) -> 179
A100: Tucker Kraft | B100: =R100-N100 -> -3 | C100: =IF(B100>=5,"SMASH BUY",IF(B100>=2,"BUY",IF(B100>=-1,"NEUTRAL",IF(B100>=-4,"AVOID","DO NOT BID")))) -> AVOID | D100: =IF(COUNTIFS('Auction Log'!$B$5:$B$304,A100,'Auction Log'!$D$5:$D$304,"<>",'Auction Log'!$E$5:$E$304,">0")=0,"Available",IFERROR(INDEX('Auction Log'!$D$5:$D$304,MATCH(1,('Auction Log'!$B$5:$B$304=A100)*('Auction Log'!$D$5:$D$304<>"")*('Auction Log'!$E$5:$E$304>0),0)),"SOLD")) -> Available | E100: =IF(COUNTIFS('Auction Log'!$B$5:$B$304,A100,'Auction Log'!$D$5:$D$304,"<>",'Auction Log'!$E$5:$E$304,">0")=0,"",IFERROR(INDEX('Auction Log'!$E$5:$E$304,MATCH(1,('Auction Log'!$B$5:$B$304=A100)*('Auction Log'!$D$5:$D$304<>"")*('Auction Log'!$E$5:$E$304>0),0)),"")) | F100: GB | G100: TE | H100: 11 | I100: 74 | J100: 7 | K100: 178 | L100: 181 | M100: 2 | N100: 11 | O100: -1 | P100: 0 | Q100: 2 | R100: 8 | S100: 7 | T100: DRAIN | U100: Knee - participating in team drills 8/26 (ESPN). Less dire than prior half-season limit comment. | V100: =IF(E100="","",R100-E100) | W100: YES | X100: =IF(AND(D100="Available",R100>=55),ROW(),9999) -> 9999 | Y100: =IF(AND(D100="Available",R100>=40,R100<55),ROW(),9999) -> 9999 | Z100: =IF(AND(D100="Available",R100>=25,R100<40),ROW(),9999) -> 9999 | AA100: =IF(K100="","",IF(L100="",K100,ROUND(AVERAGE(K100,L100),0))) -> 180
A101: Josh Downs | B101: =R101-N101 -> -1 | C101: =IF(B101>=5,"SMASH BUY",IF(B101>=2,"BUY",IF(B101>=-1,"NEUTRAL",IF(B101>=-4,"AVOID","DO NOT BID")))) -> NEUTRAL | D101: =IF(COUNTIFS('Auction Log'!$B$5:$B$304,A101,'Auction Log'!$D$5:$D$304,"<>",'Auction Log'!$E$5:$E$304,">0")=0,"Available",IFERROR(INDEX('Auction Log'!$D$5:$D$304,MATCH(1,('Auction Log'!$B$5:$B$304=A101)*('Auction Log'!$D$5:$D$304<>"")*('Auction Log'!$E$5:$E$304>0),0)),"SOLD")) -> Available | E101: =IF(COUNTIFS('Auction Log'!$B$5:$B$304,A101,'Auction Log'!$D$5:$D$304,"<>",'Auction Log'!$E$5:$E$304,">0")=0,"",IFERROR(INDEX('Auction Log'!$E$5:$E$304,MATCH(1,('Auction Log'!$B$5:$B$304=A101)*('Auction Log'!$D$5:$D$304<>"")*('Auction Log'!$E$5:$E$304>0),0)),"")) | F101: IND | G101: WR | H101: 13 | I101: 86 | J101: 7 | K101: 164 | L101: 158 | M101: 2 | N101: 9 | O101: 0 | P101: -1 | Q101: 0 | R101: 8 | S101: 7 | T101: HOLD | V101: =IF(E101="","",R101-E101) | W101: YES | X101: =IF(AND(D101="Available",R101>=55),ROW(),9999) -> 9999 | Y101: =IF(AND(D101="Available",R101>=40,R101<55),ROW(),9999) -> 9999 | Z101: =IF(AND(D101="Available",R101>=25,R101<40),ROW(),9999) -> 9999 | AA101: =IF(K101="","",IF(L101="",K101,ROUND(AVERAGE(K101,L101),0))) -> 161
A102: Quentin Johnston | B102: =R102-N102 -> -2 | C102: =IF(B102>=5,"SMASH BUY",IF(B102>=2,"BUY",IF(B102>=-1,"NEUTRAL",IF(B102>=-4,"AVOID","DO NOT BID")))) -> AVOID | D102: =IF(COUNTIFS('Auction Log'!$B$5:$B$304,A102,'Auction Log'!$D$5:$D$304,"<>",'Auction Log'!$E$5:$E$304,">0")=0,"Available",IFERROR(INDEX('Auction Log'!$D$5:$D$304,MATCH(1,('Auction Log'!$B$5:$B$304=A102)*('Auction Log'!$D$5:$D$304<>"")*('Auction Log'!$E$5:$E$304>0),0)),"SOLD")) -> Available | E102: =IF(COUNTIFS('Auction Log'!$B$5:$B$304,A102,'Auction Log'!$D$5:$D$304,"<>",'Auction Log'!$E$5:$E$304,">0")=0,"",IFERROR(INDEX('Auction Log'!$E$5:$E$304,MATCH(1,('Auction Log'!$B$5:$B$304=A102)*('Auction Log'!$D$5:$D$304<>"")*('Auction Log'!$E$5:$E$304>0),0)),"")) | F102: LAC | G102: WR | H102: 7 | I102: 93 | J102: 7 | K102: 170 | L102: 165 | M102: 2 | N102: 10 | O102: -2 | P102: 0 | Q102: 0 | R102: 8 | S102: 7 | T102: HOLD | U102: Lower body - not expected to miss much time (8/24) | V102: =IF(E102="","",R102-E102) | W102: YES | X102: =IF(AND(D102="Available",R102>=55),ROW(),9999) -> 9999 | Y102: =IF(AND(D102="Available",R102>=40,R102<55),ROW(),9999) -> 9999 | Z102: =IF(AND(D102="Available",R102>=25,R102<40),ROW(),9999) -> 9999 | AA102: =IF(K102="","",IF(L102="",K102,ROUND(AVERAGE(K102,L102),0))) -> 168
A103: Bo Nix | B103: =R103-N103 -> 1 | C103: =IF(B103>=5,"SMASH BUY",IF(B103>=2,"BUY",IF(B103>=-1,"NEUTRAL",IF(B103>=-4,"AVOID","DO NOT BID")))) -> NEUTRAL | D103: =IF(COUNTIFS('Auction Log'!$B$5:$B$304,A103,'Auction Log'!$D$5:$D$304,"<>",'Auction Log'!$E$5:$E$304,">0")=0,"Available",IFERROR(INDEX('Auction Log'!$D$5:$D$304,MATCH(1,('Auction Log'!$B$5:$B$304=A103)*('Auction Log'!$D$5:$D$304<>"")*('Auction Log'!$E$5:$E$304>0),0)),"SOLD")) -> Available | E103: =IF(COUNTIFS('Auction Log'!$B$5:$B$304,A103,'Auction Log'!$D$5:$D$304,"<>",'Auction Log'!$E$5:$E$304,">0")=0,"",IFERROR(INDEX('Auction Log'!$E$5:$E$304,MATCH(1,('Auction Log'!$B$5:$B$304=A103)*('Auction Log'!$D$5:$D$304<>"")*('Auction Log'!$E$5:$E$304>0),0)),"")) | F103: DEN | G103: QB | H103: 10 | I103: 102 | J103: 8 | K103: 298 | L103: 296 | M103: 4 | N103: 7 | O103: 1 | P103: 0 | Q103: 0 | R103: 8 | S103: 7 | T103: HOLD | V103: =IF(E103="","",R103-E103) | W103: YES | X103: =IF(AND(D103="Available",R103>=55),ROW(),9999) -> 9999 | Y103: =IF(AND(D103="Available",R103>=40,R103<55),ROW(),9999) -> 9999 | Z103: =IF(AND(D103="Available",R103>=25,R103<40),ROW(),9999) -> 9999 | AA103: =IF(K103="","",IF(L103="",K103,ROUND(AVERAGE(K103,L103),0))) -> 297
A104: Jakobi Meyers | B104: =R104-N104 -> -4 | C104: =IF(B104>=5,"SMASH BUY",IF(B104>=2,"BUY",IF(B104>=-1,"NEUTRAL",IF(B104>=-4,"AVOID","DO NOT BID")))) -> AVOID | D104: =IF(COUNTIFS('Auction Log'!$B$5:$B$304,A104,'Auction Log'!$D$5:$D$304,"<>",'Auction Log'!$E$5:$E$304,">0")=0,"Available",IFERROR(INDEX('Auction Log'!$D$5:$D$304,MATCH(1,('Auction Log'!$B$5:$B$304=A104)*('Auction Log'!$D$5:$D$304<>"")*('Auction Log'!$E$5:$E$304>0),0)),"SOLD")) -> Available | E104: =IF(COUNTIFS('Auction Log'!$B$5:$B$304,A104,'Auction Log'!$D$5:$D$304,"<>",'Auction Log'!$E$5:$E$304,">0")=0,"",IFERROR(INDEX('Auction Log'!$E$5:$E$304,MATCH(1,('Auction Log'!$B$5:$B$304=A104)*('Auction Log'!$D$5:$D$304<>"")*('Auction Log'!$E$5:$E$304>0),0)),"")) | F104: JAC | G104: WR | H104: 7 | I104: 103 | J104: 8 | K104: 179 | L104: 182 | M104: 4 | N104: 12 | O104: -4 | P104: 0 | Q104: 0 | R104: 8 | S104: 7 | T104: HOLD | U104: Hand - wearing a brace on his right hand; could miss practice week of (8/24) | V104: =IF(E104="","",R104-E104) | W104: YES | X104: =IF(AND(D104="Available",R104>=55),ROW(),9999) -> 9999 | Y104: =IF(AND(D104="Available",R104>=40,R104<55),ROW(),9999) -> 9999 | Z104: =IF(AND(D104="Available",R104>=25,R104<40),ROW(),9999) -> 9999 | AA104: =IF(K104="","",IF(L104="",K104,ROUND(AVERAGE(K104,L104),0))) -> 181
A105: Jared Goff | B105: =R105-N105 -> 3 | C105: =IF(B105>=5,"SMASH BUY",IF(B105>=2,"BUY",IF(B105>=-1,"NEUTRAL",IF(B105>=-4,"AVOID","DO NOT BID")))) -> BUY | D105: =IF(COUNTIFS('Auction Log'!$B$5:$B$304,A105,'Auction Log'!$D$5:$D$304,"<>",'Auction Log'!$E$5:$E$304,">0")=0,"Available",IFERROR(INDEX('Auction Log'!$D$5:$D$304,MATCH(1,('Auction Log'!$B$5:$B$304=A105)*('Auction Log'!$D$5:$D$304<>"")*('Auction Log'!$E$5:$E$304>0),0)),"SOLD")) -> Available | E105: =IF(COUNTIFS('Auction Log'!$B$5:$B$304,A105,'Auction Log'!$D$5:$D$304,"<>",'Auction Log'!$E$5:$E$304,">0")=0,"",IFERROR(INDEX('Auction Log'!$E$5:$E$304,MATCH(1,('Auction Log'!$B$5:$B$304=A105)*('Auction Log'!$D$5:$D$304<>"")*('Auction Log'!$E$5:$E$304>0),0)),"")) | F105: DET | G105: QB | H105: 6 | I105: 107 | J105: 8 | K105: 288 | L105: 268 | M105: 1 | N105: 5 | O105: 2 | P105: 1 | Q105: 0 | R105: 8 | S105: 7 | T105: TARGET | V105: =IF(E105="","",R105-E105) | W105: YES | X105: =IF(AND(D105="Available",R105>=55),ROW(),9999) -> 9999 | Y105: =IF(AND(D105="Available",R105>=40,R105<55),ROW(),9999) -> 9999 | Z105: =IF(AND(D105="Available",R105>=25,R105<40),ROW(),9999) -> 9999 | AA105: =IF(K105="","",IF(L105="",K105,ROUND(AVERAGE(K105,L105),0))) -> 278
A106: Stefon Diggs | B106: =R106-N106 -> -2 | C106: =IF(B106>=5,"SMASH BUY",IF(B106>=2,"BUY",IF(B106>=-1,"NEUTRAL",IF(B106>=-4,"AVOID","DO NOT BID")))) -> AVOID | D106: =IF(COUNTIFS('Auction Log'!$B$5:$B$304,A106,'Auction Log'!$D$5:$D$304,"<>",'Auction Log'!$E$5:$E$304,">0")=0,"Available",IFERROR(INDEX('Auction Log'!$D$5:$D$304,MATCH(1,('Auction Log'!$B$5:$B$304=A106)*('Auction Log'!$D$5:$D$304<>"")*('Auction Log'!$E$5:$E$304>0),0)),"SOLD")) -> Available | E106: =IF(COUNTIFS('Auction Log'!$B$5:$B$304,A106,'Auction Log'!$D$5:$D$304,"<>",'Auction Log'!$E$5:$E$304,">0")=0,"",IFERROR(INDEX('Auction Log'!$E$5:$E$304,MATCH(1,('Auction Log'!$B$5:$B$304=A106)*('Auction Log'!$D$5:$D$304<>"")*('Auction Log'!$E$5:$E$304>0),0)),"")) | F106: WAS | G106: WR | H106: 7 | I106: 92 | J106: 7 | K106: 166 | L106: 164 | M106: 1 | N106: 9 | O106: -1 | P106: -1 | Q106: 0 | R106: 7 | S106: 6 | T106: HOLD | V106: =IF(E106="","",R106-E106) | W106: YES | X106: =IF(AND(D106="Available",R106>=55),ROW(),9999) -> 9999 | Y106: =IF(AND(D106="Available",R106>=40,R106<55),ROW(),9999) -> 9999 | Z106: =IF(AND(D106="Available",R106>=25,R106<40),ROW(),9999) -> 9999 | AA106: =IF(K106="","",IF(L106="",K106,ROUND(AVERAGE(K106,L106),0))) -> 165
A107: Chuba Hubbard | B107: =R107-N107 -> -5 | C107: =IF(B107>=5,"SMASH BUY",IF(B107>=2,"BUY",IF(B107>=-1,"NEUTRAL",IF(B107>=-4,"AVOID","DO NOT BID")))) -> DO NOT BID | D107: =IF(COUNTIFS('Auction Log'!$B$5:$B$304,A107,'Auction Log'!$D$5:$D$304,"<>",'Auction Log'!$E$5:$E$304,">0")=0,"Available",IFERROR(INDEX('Auction Log'!$D$5:$D$304,MATCH(1,('Auction Log'!$B$5:$B$304=A107)*('Auction Log'!$D$5:$D$304<>"")*('Auction Log'!$E$5:$E$304>0),0)),"SOLD")) -> Available | E107: =IF(COUNTIFS('Auction Log'!$B$5:$B$304,A107,'Auction Log'!$D$5:$D$304,"<>",'Auction Log'!$E$5:$E$304,">0")=0,"",IFERROR(INDEX('Auction Log'!$E$5:$E$304,MATCH(1,('Auction Log'!$B$5:$B$304=A107)*('Auction Log'!$D$5:$D$304<>"")*('Auction Log'!$E$5:$E$304>0),0)),"")) | F107: CAR | G107: RB | H107: 5 | I107: 96 | J107: 7 | K107: 173 | L107: 173 | M107: 2 | N107: 12 | O107: -3 | P107: 0 | Q107: 2 | R107: 7 | S107: 6 | T107: HOLD | U107: Hamstring - remains on track for Week 1 (8/24 via ESPN). | V107: =IF(E107="","",R107-E107) | W107: YES | X107: =IF(AND(D107="Available",R107>=55),ROW(),9999) -> 9999 | Y107: =IF(AND(D107="Available",R107>=40,R107<55),ROW(),9999) -> 9999 | Z107: =IF(AND(D107="Available",R107>=25,R107<40),ROW(),9999) -> 9999 | AA107: =IF(K107="","",IF(L107="",K107,ROUND(AVERAGE(K107,L107),0))) -> 173
A108: Patrick Mahomes II | B108: =R108-N108 -> -1 | C108: =IF(B108>=5,"SMASH BUY",IF(B108>=2,"BUY",IF(B108>=-1,"NEUTRAL",IF(B108>=-4,"AVOID","DO NOT BID")))) -> NEUTRAL | D108: =IF(COUNTIFS('Auction Log'!$B$5:$B$304,A108,'Auction Log'!$D$5:$D$304,"<>",'Auction Log'!$E$5:$E$304,">0")=0,"Available",IFERROR(INDEX('Auction Log'!$D$5:$D$304,MATCH(1,('Auction Log'!$B$5:$B$304=A108)*('Auction Log'!$D$5:$D$304<>"")*('Auction Log'!$E$5:$E$304>0),0)),"SOLD")) -> Available | E108: =IF(COUNTIFS('Auction Log'!$B$5:$B$304,A108,'Auction Log'!$D$5:$D$304,"<>",'Auction Log'!$E$5:$E$304,">0")=0,"",IFERROR(INDEX('Auction Log'!$E$5:$E$304,MATCH(1,('Auction Log'!$B$5:$B$304=A108)*('Auction Log'!$D$5:$D$304<>"")*('Auction Log'!$E$5:$E$304>0),0)),"")) | F108: KC | G108: QB | H108: 5 | I108: 99 | J108: 8 | K108: 303 | L108: 291 | M108: 3 | N108: 8 | O108: 0 | P108: 0 | Q108: 1 | R108: 7 | S108: 6 | T108: HOLD | U108: Knee (ACL) - 'extremely confident' for Week 1 (8/22 via ESPN). Cheap QB plan still OK. | V108: =IF(E108="","",R108-E108) | W108: YES | X108: =IF(AND(D108="Available",R108>=55),ROW(),9999) -> 9999 | Y108: =IF(AND(D108="Available",R108>=40,R108<55),ROW(),9999) -> 9999 | Z108: =IF(AND(D108="Available",R108>=25,R108<40),ROW(),9999) -> 9999 | AA108: =IF(K108="","",IF(L108="",K108,ROUND(AVERAGE(K108,L108),0))) -> 297
...

Sheet Auction Log
A1: LIVE ENTRY + AUCTION LOG
A2: Use the first bright-green row. Tab: Player > Winner > Price > Roster Slot. Ctrl+Down moves quickly through the log.
A4: Nom # | B4: Player | C4: Pos | D4: Winner | E4: Price | F4: Roster Slot | G4: My Max | H4: Sale Value | I4: Note | J4: Entry Check | K4: Projection
A5: =IF(B5="","",ROW()-4) | C5: =IFERROR(INDEX('Player Board'!$G$5:$G$304,MATCH(B5,'Player Board'!$A$5:$A$304,0)),"") | G5: =IFERROR(INDEX('Player Board'!$R$5:$R$304,MATCH(B5,'Player Board'!$A$5:$A$304,0)),"") | H5: =IF(E5="","",G5-E5) | J5: =IF(B5="","",IF(A5=MAX($A$5:$A$304),"LAST — CLEAR INPUTS TO UNDO",IF(AND(D5<>"",E5<>""),"LOGGED","INCOMPLETE"))) | K5: =IFERROR(INDEX('Player Board'!$AA$5:$AA$304,MATCH(B5,'Player Board'!$A$5:$A$304,0)),"")
A6: =IF(B6="","",ROW()-4) | C6: =IFERROR(INDEX('Player Board'!$G$5:$G$304,MATCH(B6,'Player Board'!$A$5:$A$304,0)),"") | G6: =IFERROR(INDEX('Player Board'!$R$5:$R$304,MATCH(B6,'Player Board'!$A$5:$A$304,0)),"") | H6: =IF(E6="","",G6-E6) | J6: =IF(B6="","",IF(A6=MAX($A$5:$A$304),"LAST — CLEAR INPUTS TO UNDO",IF(AND(D6<>"",E6<>""),"LOGGED","INCOMPLETE"))) | K6: =IFERROR(INDEX('Player Board'!$AA$5:$AA$304,MATCH(B6,'Player Board'!$A$5:$A$304,0)),"")
A7: =IF(B7="","",ROW()-4) | C7: =IFERROR(INDEX('Player Board'!$G$5:$G$304,MATCH(B7,'Player Board'!$A$5:$A$304,0)),"") | G7: =IFERROR(INDEX('Player Board'!$R$5:$R$304,MATCH(B7,'Player Board'!$A$5:$A$304,0)),"") | H7: =IF(E7="","",G7-E7) | J7: =IF(B7="","",IF(A7=MAX($A$5:$A$304),"LAST — CLEAR INPUTS TO UNDO",IF(AND(D7<>"",E7<>""),"LOGGED","INCOMPLETE"))) | K7: =IFERROR(INDEX('Player Board'!$AA$5:$AA$304,MATCH(B7,'Player Board'!$A$5:$A$304,0)),"")
A8: =IF(B8="","",ROW()-4) | C8: =IFERROR(INDEX('Player Board'!$G$5:$G$304,MATCH(B8,'Player Board'!$A$5:$A$304,0)),"") | G8: =IFERROR(INDEX('Player Board'!$R$5:$R$304,MATCH(B8,'Player Board'!$A$5:$A$304,0)),"") | H8: =IF(E8="","",G8-E8) | J8: =IF(B8="","",IF(A8=MAX($A$5:$A$304),"LAST — CLEAR INPUTS TO UNDO",IF(AND(D8<>"",E8<>""),"LOGGED","INCOMPLETE"))) | K8: =IFERROR(INDEX('Player Board'!$AA$5:$AA$304,MATCH(B8,'Player Board'!$A$5:$A$304,0)),"")
A9: =IF(B9="","",ROW()-4) | C9: =IFERROR(INDEX('Player Board'!$G$5:$G$304,MATCH(B9,'Player Board'!$A$5:$A$304,0)),"") | G9: =IFERROR(INDEX('Player Board'!$R$5:$R$304,MATCH(B9,'Player Board'!$A$5:$A$304,0)),"") | H9: =IF(E9="","",G9-E9) | J9: =IF(B9="","",IF(A9=MAX($A$5:$A$304),"LAST — CLEAR INPUTS TO UNDO",IF(AND(D9<>"",E9<>""),"LOGGED","INCOMPLETE"))) | K9: =IFERROR(INDEX('Player Board'!$AA$5:$AA$304,MATCH(B9,'Player Board'!$A$5:$A$304,0)),"")
A10: =IF(B10="","",ROW()-4) | C10: =IFERROR(INDEX('Player Board'!$G$5:$G$304,MATCH(B10,'Player Board'!$A$5:$A$304,0)),"") | G10: =IFERROR(INDEX('Player Board'!$R$5:$R$304,MATCH(B10,'Player Board'!$A$5:$A$304,0)),"") | H10: =IF(E10="","",G10-E10) | J10: =IF(B10="","",IF(A10=MAX($A$5:$A$304),"LAST — CLEAR INPUTS TO UNDO",IF(AND(D10<>"",E10<>""),"LOGGED","INCOMPLETE"))) | K10: =IFERROR(INDEX('Player Board'!$AA$5:$AA$304,MATCH(B10,'Player Board'!$A$5:$A$304,0)),"")
A11: =IF(B11="","",ROW()-4) | C11: =IFERROR(INDEX('Player Board'!$G$5:$G$304,MATCH(B11,'Player Board'!$A$5:$A$304,0)),"") | G11: =IFERROR(INDEX('Player Board'!$R$5:$R$304,MATCH(B11,'Player Board'!$A$5:$A$304,0)),"") | H11: =IF(E11="","",G11-E11) | J11: =IF(B11="","",IF(A11=MAX($A$5:$A$304),"LAST — CLEAR INPUTS TO UNDO",IF(AND(D11<>"",E11<>""),"LOGGED","INCOMPLETE"))) | K11: =IFERROR(INDEX('Player Board'!$AA$5:$AA$304,MATCH(B11,'Player Board'!$A$5:$A$304,0)),"")
A12: =IF(B12="","",ROW()-4) | C12: =IFERROR(INDEX('Player Board'!$G$5:$G$304,MATCH(B12,'Player Board'!$A$5:$A$304,0)),"") | G12: =IFERROR(INDEX('Player Board'!$R$5:$R$304,MATCH(B12,'Player Board'!$A$5:$A$304,0)),"") | H12: =IF(E12="","",G12-E12) | J12: =IF(B12="","",IF(A12=MAX($A$5:$A$304),"LAST — CLEAR INPUTS TO UNDO",IF(AND(D12<>"",E12<>""),"LOGGED","INCOMPLETE"))) | K12: =IFERROR(INDEX('Player Board'!$AA$5:$AA$304,MATCH(B12,'Player Board'!$A$5:$A$304,0)),"")
A13: =IF(B13="","",ROW()-4) | C13: =IFERROR(INDEX('Player Board'!$G$5:$G$304,MATCH(B13,'Player Board'!$A$5:$A$304,0)),"") | G13: =IFERROR(INDEX('Player Board'!$R$5:$R$304,MATCH(B13,'Player Board'!$A$5:$A$304,0)),"") | H13: =IF(E13="","",G13-E13) | J13: =IF(B13="","",IF(A13=MAX($A$5:$A$304),"LAST — CLEAR INPUTS TO UNDO",IF(AND(D13<>"",E13<>""),"LOGGED","INCOMPLETE"))) | K13: =IFERROR(INDEX('Player Board'!$AA$5:$AA$304,MATCH(B13,'Player Board'!$A$5:$A$304,0)),"")
A14: =IF(B14="","",ROW()-4) | C14: =IFERROR(INDEX('Player Board'!$G$5:$G$304,MATCH(B14,'Player Board'!$A$5:$A$304,0)),"") | G14: =IFERROR(INDEX('Player Board'!$R$5:$R$304,MATCH(B14,'Player Board'!$A$5:$A$304,0)),"") | H14: =IF(E14="","",G14-E14) | J14: =IF(B14="","",IF(A14=MAX($A$5:$A$304),"LAST — CLEAR INPUTS TO UNDO",IF(AND(D14<>"",E14<>""),"LOGGED","INCOMPLETE"))) | K14: =IFERROR(INDEX('Player Board'!$AA$5:$AA$304,MATCH(B14,'Player Board'!$A$5:$A$304,0)),"")
A15: =IF(B15="","",ROW()-4) | C15: =IFERROR(INDEX('Player Board'!$G$5:$G$304,MATCH(B15,'Player Board'!$A$5:$A$304,0)),"") | G15: =IFERROR(INDEX('Player Board'!$R$5:$R$304,MATCH(B15,'Player Board'!$A$5:$A$304,0)),"") | H15: =IF(E15="","",G15-E15) | J15: =IF(B15="","",IF(A15=MAX($A$5:$A$304),"LAST — CLEAR INPUTS TO UNDO",IF(AND(D15<>"",E15<>""),"LOGGED","INCOMPLETE"))) | K15: =IFERROR(INDEX('Player Board'!$AA$5:$AA$304,MATCH(B15,'Player Board'!$A$5:$A$304,0)),"")
A16: =IF(B16="","",ROW()-4) | C16: =IFERROR(INDEX('Player Board'!$G$5:$G$304,MATCH(B16,'Player Board'!$A$5:$A$304,0)),"") | G16: =IFERROR(INDEX('Player Board'!$R$5:$R$304,MATCH(B16,'Player Board'!$A$5:$A$304,0)),"") | H16: =IF(E16="","",G16-E16) | J16: =IF(B16="","",IF(A16=MAX($A$5:$A$304),"LAST — CLEAR INPUTS TO UNDO",IF(AND(D16<>"",E16<>""),"LOGGED","INCOMPLETE"))) | K16: =IFERROR(INDEX('Player Board'!$AA$5:$AA$304,MATCH(B16,'Player Board'!$A$5:$A$304,0)),"")
... A304: =IF(B304="","",ROW()-4) | C304: =IFERROR(INDEX('Player Board'!$G$5:$G$304,MATCH(B304,'Player Board'!$A$5:$A$304,0)),"") | G304: =IFERROR(INDEX('Player Board'!$R$5:$R$304,MATCH(B304,'Player Board'!$A$5:$A$304,0)),"") | H304: =IF(E304="","",G304-E304) | J304: =IF(B304="","",IF(A304=MAX($A$5:$A$304),"LAST — CLEAR INPUTS TO UNDO",IF(AND(D304<>"",E304<>""),"LOGGED","INCOMPLETE"))) | K304: =IFERROR(INDEX('Player Board'!$AA$5:$AA$304,MATCH(B304,'Player Board'!$A$5:$A$304,0)),"")

Sheet Team Tracker
A1: TEAM, NEED & MAX-BID TRACKER
A2: TONIGHT: rename Team 2-Team 14 in blue. Winner dropdown and rival panels update automatically.
A4: Team | B4: Budget | C4: Spent | D4: Remaining | E4: Players | F4: Slots Left | G4: Max Bid | H4: QB | I4: RB | J4: WR | K4: TE | L4: D/ST | M4: K | N4: Biggest Need | O4: Threat Rank
A5: ME | B5: 200 | C5: =SUMIF('Auction Log'!$D$5:$D$304,A5,'Auction Log'!$E$5:$E$304) -> 0 | D5: =B5-C5 -> 200 | E5: =COUNTIF('Auction Log'!$D$5:$D$304,A5) -> 0 | F5: =15-E5 -> 15 | G5: =IF(F5=0,0,D5-F5+1) -> 186 | H5: =COUNTIFS('Auction Log'!$D$5:$D$304,A5,'Auction Log'!$C$5:$C$304,H$4) -> 0 | I5: =COUNTIFS('Auction Log'!$D$5:$D$304,A5,'Auction Log'!$C$5:$C$304,I$4) -> 0 | J5: =COUNTIFS('Auction Log'!$D$5:$D$304,A5,'Auction Log'!$C$5:$C$304,J$4) -> 0 | K5: =COUNTIFS('Auction Log'!$D$5:$D$304,A5,'Auction Log'!$C$5:$C$304,K$4) -> 0 | L5: =COUNTIFS('Auction Log'!$D$5:$D$304,A5,'Auction Log'!$C$5:$C$304,L$4) -> 0 | M5: =COUNTIFS('Auction Log'!$D$5:$D$304,A5,'Auction Log'!$C$5:$C$304,M$4) -> 0 | N5: =IF(F5=0,"DONE",IF(I5<5,"RB",IF(J5<5,"WR",IF(K5<1,"TE",IF(H5<1,"QB",IF(L5<1,"D/ST",IF(M5<1,"K","BENCH"))))))) -> RB | O5: =IF(A5="ME","",COUNTIF($G$6:$G$18,">"&G5)+1)
A6: RD | B6: 200 | C6: =SUMIF('Auction Log'!$D$5:$D$304,A6,'Auction Log'!$E$5:$E$304) -> 0 | D6: =B6-C6 -> 200 | E6: =COUNTIF('Auction Log'!$D$5:$D$304,A6) -> 0 | F6: =15-E6 -> 15 | G6: =IF(F6=0,0,D6-F6+1) -> 186 | H6: =COUNTIFS('Auction Log'!$D$5:$D$304,A6,'Auction Log'!$C$5:$C$304,H$4) -> 0 | I6: =COUNTIFS('Auction Log'!$D$5:$D$304,A6,'Auction Log'!$C$5:$C$304,I$4) -> 0 | J6: =COUNTIFS('Auction Log'!$D$5:$D$304,A6,'Auction Log'!$C$5:$C$304,J$4) -> 0 | K6: =COUNTIFS('Auction Log'!$D$5:$D$304,A6,'Auction Log'!$C$5:$C$304,K$4) -> 0 | L6: =COUNTIFS('Auction Log'!$D$5:$D$304,A6,'Auction Log'!$C$5:$C$304,L$4) -> 0 | M6: =COUNTIFS('Auction Log'!$D$5:$D$304,A6,'Auction Log'!$C$5:$C$304,M$4) -> 0 | N6: =IF(F6=0,"DONE",IF(I6<5,"RB",IF(J6<5,"WR",IF(K6<1,"TE",IF(H6<1,"QB",IF(L6<1,"D/ST",IF(M6<1,"K","BENCH"))))))) -> RB | O6: =IF(A6="ME","",COUNTIF($G$6:$G$18,">"&G6)+1) -> 1
A7: CATE | B7: 200 | C7: =SUMIF('Auction Log'!$D$5:$D$304,A7,'Auction Log'!$E$5:$E$304) -> 0 | D7: =B7-C7 -> 200 | E7: =COUNTIF('Auction Log'!$D$5:$D$304,A7) -> 0 | F7: =15-E7 -> 15 | G7: =IF(F7=0,0,D7-F7+1) -> 186 | H7: =COUNTIFS('Auction Log'!$D$5:$D$304,A7,'Auction Log'!$C$5:$C$304,H$4) -> 0 | I7: =COUNTIFS('Auction Log'!$D$5:$D$304,A7,'Auction Log'!$C$5:$C$304,I$4) -> 0 | J7: =COUNTIFS('Auction Log'!$D$5:$D$304,A7,'Auction Log'!$C$5:$C$304,J$4) -> 0 | K7: =COUNTIFS('Auction Log'!$D$5:$D$304,A7,'Auction Log'!$C$5:$C$304,K$4) -> 0 | L7: =COUNTIFS('Auction Log'!$D$5:$D$304,A7,'Auction Log'!$C$5:$C$304,L$4) -> 0 | M7: =COUNTIFS('Auction Log'!$D$5:$D$304,A7,'Auction Log'!$C$5:$C$304,M$4) -> 0 | N7: =IF(F7=0,"DONE",IF(I7<5,"RB",IF(J7<5,"WR",IF(K7<1,"TE",IF(H7<1,"QB",IF(L7<1,"D/ST",IF(M7<1,"K","BENCH"))))))) -> RB | O7: =IF(A7="ME","",COUNTIF($G$6:$G$18,">"&G7)+1) -> 1
A8: SV | B8: 200 | C8: =SUMIF('Auction Log'!$D$5:$D$304,A8,'Auction Log'!$E$5:$E$304) -> 0 | D8: =B8-C8 -> 200 | E8: =COUNTIF('Auction Log'!$D$5:$D$304,A8) -> 0 | F8: =15-E8 -> 15 | G8: =IF(F8=0,0,D8-F8+1) -> 186 | H8: =COUNTIFS('Auction Log'!$D$5:$D$304,A8,'Auction Log'!$C$5:$C$304,H$4) -> 0 | I8: =COUNTIFS('Auction Log'!$D$5:$D$304,A8,'Auction Log'!$C$5:$C$304,I$4) -> 0 | J8: =COUNTIFS('Auction Log'!$D$5:$D$304,A8,'Auction Log'!$C$5:$C$304,J$4) -> 0 | K8: =COUNTIFS('Auction Log'!$D$5:$D$304,A8,'Auction Log'!$C$5:$C$304,K$4) -> 0 | L8: =COUNTIFS('Auction Log'!$D$5:$D$304,A8,'Auction Log'!$C$5:$C$304,L$4) -> 0 | M8: =COUNTIFS('Auction Log'!$D$5:$D$304,A8,'Auction Log'!$C$5:$C$304,M$4) -> 0 | N8: =IF(F8=0,"DONE",IF(I8<5,"RB",IF(J8<5,"WR",IF(K8<1,"TE",IF(H8<1,"QB",IF(L8<1,"D/ST",IF(M8<1,"K","BENCH"))))))) -> RB | O8: =IF(A8="ME","",COUNTIF($G$6:$G$18,">"&G8)+1) -> 1
A9: NWK | B9: 200 | C9: =SUMIF('Auction Log'!$D$5:$D$304,A9,'Auction Log'!$E$5:$E$304) -> 0 | D9: =B9-C9 -> 200 | E9: =COUNTIF('Auction Log'!$D$5:$D$304,A9) -> 0 | F9: =15-E9 -> 15 | G9: =IF(F9=0,0,D9-F9+1) -> 186 | H9: =COUNTIFS('Auction Log'!$D$5:$D$304,A9,'Auction Log'!$C$5:$C$304,H$4) -> 0 | I9: =COUNTIFS('Auction Log'!$D$5:$D$304,A9,'Auction Log'!$C$5:$C$304,I$4) -> 0 | J9: =COUNTIFS('Auction Log'!$D$5:$D$304,A9,'Auction Log'!$C$5:$C$304,J$4) -> 0 | K9: =COUNTIFS('Auction Log'!$D$5:$D$304,A9,'Auction Log'!$C$5:$C$304,K$4) -> 0 | L9: =COUNTIFS('Auction Log'!$D$5:$D$304,A9,'Auction Log'!$C$5:$C$304,L$4) -> 0 | M9: =COUNTIFS('Auction Log'!$D$5:$D$304,A9,'Auction Log'!$C$5:$C$304,M$4) -> 0 | N9: =IF(F9=0,"DONE",IF(I9<5,"RB",IF(J9<5,"WR",IF(K9<1,"TE",IF(H9<1,"QB",IF(L9<1,"D/ST",IF(M9<1,"K","BENCH"))))))) -> RB | O9: =IF(A9="ME","",COUNTIF($G$6:$G$18,">"&G9)+1) -> 1
A10: SST | B10: 200 | C10: =SUMIF('Auction Log'!$D$5:$D$304,A10,'Auction Log'!$E$5:$E$304) -> 0 | D10: =B10-C10 -> 200 | E10: =COUNTIF('Auction Log'!$D$5:$D$304,A10) -> 0 | F10: =15-E10 -> 15 | G10: =IF(F10=0,0,D10-F10+1) -> 186 | H10: =COUNTIFS('Auction Log'!$D$5:$D$304,A10,'Auction Log'!$C$5:$C$304,H$4) -> 0 | I10: =COUNTIFS('Auction Log'!$D$5:$D$304,A10,'Auction Log'!$C$5:$C$304,I$4) -> 0 | J10: =COUNTIFS('Auction Log'!$D$5:$D$304,A10,'Auction Log'!$C$5:$C$304,J$4) -> 0 | K10: =COUNTIFS('Auction Log'!$D$5:$D$304,A10,'Auction Log'!$C$5:$C$304,K$4) -> 0 | L10: =COUNTIFS('Auction Log'!$D$5:$D$304,A10,'Auction Log'!$C$5:$C$304,L$4) -> 0 | M10: =COUNTIFS('Auction Log'!$D$5:$D$304,A10,'Auction Log'!$C$5:$C$304,M$4) -> 0 | N10: =IF(F10=0,"DONE",IF(I10<5,"RB",IF(J10<5,"WR",IF(K10<1,"TE",IF(H10<1,"QB",IF(L10<1,"D/ST",IF(M10<1,"K","BENCH"))))))) -> RB | O10: =IF(A10="ME","",COUNTIF($G$6:$G$18,">"&G10)+1) -> 1
A11: PA | B11: 200 | C11: =SUMIF('Auction Log'!$D$5:$D$304,A11,'Auction Log'!$E$5:$E$304) -> 0 | D11: =B11-C11 -> 200 | E11: =COUNTIF('Auction Log'!$D$5:$D$304,A11) -> 0 | F11: =15-E11 -> 15 | G11: =IF(F11=0,0,D11-F11+1) -> 186 | H11: =COUNTIFS('Auction Log'!$D$5:$D$304,A11,'Auction Log'!$C$5:$C$304,H$4) -> 0 | I11: =COUNTIFS('Auction Log'!$D$5:$D$304,A11,'Auction Log'!$C$5:$C$304,I$4) -> 0 | J11: =COUNTIFS('Auction Log'!$D$5:$D$304,A11,'Auction Log'!$C$5:$C$304,J$4) -> 0 | K11: =COUNTIFS('Auction Log'!$D$5:$D$304,A11,'Auction Log'!$C$5:$C$304,K$4) -> 0 | L11: =COUNTIFS('Auction Log'!$D$5:$D$304,A11,'Auction Log'!$C$5:$C$304,L$4) -> 0 | M11: =COUNTIFS('Auction Log'!$D$5:$D$304,A11,'Auction Log'!$C$5:$C$304,M$4) -> 0 | N11: =IF(F11=0,"DONE",IF(I11<5,"RB",IF(J11<5,"WR",IF(K11<1,"TE",IF(H11<1,"QB",IF(L11<1,"D/ST",IF(M11<1,"K","BENCH"))))))) -> RB | O11: =IF(A11="ME","",COUNTIF($G$6:$G$18,">"&G11)+1) -> 1
A12: GGW | B12: 200 | C12: =SUMIF('Auction Log'!$D$5:$D$304,A12,'Auction Log'!$E$5:$E$304) -> 0 | D12: =B12-C12 -> 200 | E12: =COUNTIF('Auction Log'!$D$5:$D$304,A12) -> 0 | F12: =15-E12 -> 15 | G12: =IF(F12=0,0,D12-F12+1) -> 186 | H12: =COUNTIFS('Auction Log'!$D$5:$D$304,A12,'Auction Log'!$C$5:$C$304,H$4) -> 0 | I12: =COUNTIFS('Auction Log'!$D$5:$D$304,A12,'Auction Log'!$C$5:$C$304,I$4) -> 0 | J12: =COUNTIFS('Auction Log'!$D$5:$D$304,A12,'Auction Log'!$C$5:$C$304,J$4) -> 0 | K12: =COUNTIFS('Auction Log'!$D$5:$D$304,A12,'Auction Log'!$C$5:$C$304,K$4) -> 0 | L12: =COUNTIFS('Auction Log'!$D$5:$D$304,A12,'Auction Log'!$C$5:$C$304,L$4) -> 0 | M12: =COUNTIFS('Auction Log'!$D$5:$D$304,A12,'Auction Log'!$C$5:$C$304,M$4) -> 0 | N12: =IF(F12=0,"DONE",IF(I12<5,"RB",IF(J12<5,"WR",IF(K12<1,"TE",IF(H12<1,"QB",IF(L12<1,"D/ST",IF(M12<1,"K","BENCH"))))))) -> RB | O12: =IF(A12="ME","",COUNTIF($G$6:$G$18,">"&G12)+1) -> 1
A13: BBT | B13: 200 | C13: =SUMIF('Auction Log'!$D$5:$D$304,A13,'Auction Log'!$E$5:$E$304) -> 0 | D13: =B13-C13 -> 200 | E13: =COUNTIF('Auction Log'!$D$5:$D$304,A13) -> 0 | F13: =15-E13 -> 15 | G13: =IF(F13=0,0,D13-F13+1) -> 186 | H13: =COUNTIFS('Auction Log'!$D$5:$D$304,A13,'Auction Log'!$C$5:$C$304,H$4) -> 0 | I13: =COUNTIFS('Auction Log'!$D$5:$D$304,A13,'Auction Log'!$C$5:$C$304,I$4) -> 0 | J13: =COUNTIFS('Auction Log'!$D$5:$D$304,A13,'Auction Log'!$C$5:$C$304,J$4) -> 0 | K13: =COUNTIFS('Auction Log'!$D$5:$D$304,A13,'Auction Log'!$C$5:$C$304,K$4) -> 0 | L13: =COUNTIFS('Auction Log'!$D$5:$D$304,A13,'Auction Log'!$C$5:$C$304,L$4) -> 0 | M13: =COUNTIFS('Auction Log'!$D$5:$D$304,A13,'Auction Log'!$C$5:$C$304,M$4) -> 0 | N13: =IF(F13=0,"DONE",IF(I13<5,"RB",IF(J13<5,"WR",IF(K13<1,"TE",IF(H13<1,"QB",IF(L13<1,"D/ST",IF(M13<1,"K","BENCH"))))))) -> RB | O13: =IF(A13="ME","",COUNTIF($G$6:$G$18,">"&G13)+1) -> 1
A14: KNS | B14: 200 | C14: =SUMIF('Auction Log'!$D$5:$D$304,A14,'Auction Log'!$E$5:$E$304) -> 0 | D14: =B14-C14 -> 200 | E14: =COUNTIF('Auction Log'!$D$5:$D$304,A14) -> 0 | F14: =15-E14 -> 15 | G14: =IF(F14=0,0,D14-F14+1) -> 186 | H14: =COUNTIFS('Auction Log'!$D$5:$D$304,A14,'Auction Log'!$C$5:$C$304,H$4) -> 0 | I14: =COUNTIFS('Auction Log'!$D$5:$D$304,A14,'Auction Log'!$C$5:$C$304,I$4) -> 0 | J14: =COUNTIFS('Auction Log'!$D$5:$D$304,A14,'Auction Log'!$C$5:$C$304,J$4) -> 0 | K14: =COUNTIFS('Auction Log'!$D$5:$D$304,A14,'Auction Log'!$C$5:$C$304,K$4) -> 0 | L14: =COUNTIFS('Auction Log'!$D$5:$D$304,A14,'Auction Log'!$C$5:$C$304,L$4) -> 0 | M14: =COUNTIFS('Auction Log'!$D$5:$D$304,A14,'Auction Log'!$C$5:$C$304,M$4) -> 0 | N14: =IF(F14=0,"DONE",IF(I14<5,"RB",IF(J14<5,"WR",IF(K14<1,"TE",IF(H14<1,"QB",IF(L14<1,"D/ST",IF(M14<1,"K","BENCH"))))))) -> RB | O14: =IF(A14="ME","",COUNTIF($G$6:$G$18,">"&G14)+1) -> 1
A15: KNOX | B15: 200 | C15: =SUMIF('Auction Log'!$D$5:$D$304,A15,'Auction Log'!$E$5:$E$304) -> 0 | D15: =B15-C15 -> 200 | E15: =COUNTIF('Auction Log'!$D$5:$D$304,A15) -> 0 | F15: =15-E15 -> 15 | G15: =IF(F15=0,0,D15-F15+1) -> 186 | H15: =COUNTIFS('Auction Log'!$D$5:$D$304,A15,'Auction Log'!$C$5:$C$304,H$4) -> 0 | I15: =COUNTIFS('Auction Log'!$D$5:$D$304,A15,'Auction Log'!$C$5:$C$304,I$4) -> 0 | J15: =COUNTIFS('Auction Log'!$D$5:$D$304,A15,'Auction Log'!$C$5:$C$304,J$4) -> 0 | K15: =COUNTIFS('Auction Log'!$D$5:$D$304,A15,'Auction Log'!$C$5:$C$304,K$4) -> 0 | L15: =COUNTIFS('Auction Log'!$D$5:$D$304,A15,'Auction Log'!$C$5:$C$304,L$4) -> 0 | M15: =COUNTIFS('Auction Log'!$D$5:$D$304,A15,'Auction Log'!$C$5:$C$304,M$4) -> 0 | N15: =IF(F15=0,"DONE",IF(I15<5,"RB",IF(J15<5,"WR",IF(K15<1,"TE",IF(H15<1,"QB",IF(L15<1,"D/ST",IF(M15<1,"K","BENCH"))))))) -> RB | O15: =IF(A15="ME","",COUNTIF($G$6:$G$18,">"&G15)+1) -> 1
A16: SS | B16: 200 | C16: =SUMIF('Auction Log'!$D$5:$D$304,A16,'Auction Log'!$E$5:$E$304) -> 0 | D16: =B16-C16 -> 200 | E16: =COUNTIF('Auction Log'!$D$5:$D$304,A16) -> 0 | F16: =15-E16 -> 15 | G16: =IF(F16=0,0,D16-F16+1) -> 186 | H16: =COUNTIFS('Auction Log'!$D$5:$D$304,A16,'Auction Log'!$C$5:$C$304,H$4) -> 0 | I16: =COUNTIFS('Auction Log'!$D$5:$D$304,A16,'Auction Log'!$C$5:$C$304,I$4) -> 0 | J16: =COUNTIFS('Auction Log'!$D$5:$D$304,A16,'Auction Log'!$C$5:$C$304,J$4) -> 0 | K16: =COUNTIFS('Auction Log'!$D$5:$D$304,A16,'Auction Log'!$C$5:$C$304,K$4) -> 0 | L16: =COUNTIFS('Auction Log'!$D$5:$D$304,A16,'Auction Log'!$C$5:$C$304,L$4) -> 0 | M16: =COUNTIFS('Auction Log'!$D$5:$D$304,A16,'Auction Log'!$C$5:$C$304,M$4) -> 0 | N16: =IF(F16=0,"DONE",IF(I16<5,"RB",IF(J16<5,"WR",IF(K16<1,"TE",IF(H16<1,"QB",IF(L16<1,"D/ST",IF(M16<1,"K","BENCH"))))))) -> RB | O16: =IF(A16="ME","",COUNTIF($G$6:$G$18,">"&G16)+1) -> 1
... A18: SKE | B18: 200 | C18: =SUMIF('Auction Log'!$D$5:$D$304,A18,'Auction Log'!$E$5:$E$304) -> 0 | D18: =B18-C18 -> 200 | E18: =COUNTIF('Auction Log'!$D$5:$D$304,A18) -> 0 | F18: =15-E18 -> 15 | G18: =IF(F18=0,0,D18-F18+1) -> 186 | H18: =COUNTIFS('Auction Log'!$D$5:$D$304,A18,'Auction Log'!$C$5:$C$304,H$4) -> 0 | I18: =COUNTIFS('Auction Log'!$D$5:$D$304,A18,'Auction Log'!$C$5:$C$304,I$4) -> 0 | J18: =COUNTIFS('Auction Log'!$D$5:$D$304,A18,'Auction Log'!$C$5:$C$304,J$4) -> 0 | K18: =COUNTIFS('Auction Log'!$D$5:$D$304,A18,'Auction Log'!$C$5:$C$304,K$4) -> 0 | L18: =COUNTIFS('Auction Log'!$D$5:$D$304,A18,'Auction Log'!$C$5:$C$304,L$4) -> 0 | M18: =COUNTIFS('Auction Log'!$D$5:$D$304,A18,'Auction Log'!$C$5:$C$304,M$4) -> 0 | N18: =IF(F18=0,"DONE",IF(I18<5,"RB",IF(J18<5,"WR",IF(K18<1,"TE",IF(H18<1,"QB",IF(L18<1,"D/ST",IF(M18<1,"K","BENCH"))))))) -> RB | O18: =IF(A18="ME","",COUNTIF($G$6:$G$18,">"&G18)+1) -> 1

Sheet My Roster
A1: MY ROSTER — PROJECTION & VALUE
A2: Populates from roster-slot assignments in the live log. Projection uses the average of current FantasyPros and ESPN Clay forecasts when both are available.
A4: Budget Left | B4: ='Draft HQ'!B7 -> 200 | C4: Slots Left | D4: ='Draft HQ'!B9 -> 15 | E4: Max Bid | F4: ='Draft HQ'!B10 -> 186 | G4: Starting Pts | H4: =SUM(F7:F15) -> 0 | I4: Total Pts | J4: =SUM(F7:F21) -> 0
A6: Slot | B6: Player | C6: Pos | D6: Price | E6: Bye | F6: Proj | G6: Hard | H6: Value | I6: Injury / News | J6: Grade
A7: QB | B7: =IFERROR(LOOKUP(2,1/(('Auction Log'!$F$5:$F$304=A7)*('Auction Log'!$D$5:$D$304="ME")),'Auction Log'!$B$5:$B$304),"") | C7: =IF(B7="","",IFERROR(INDEX('Player Board'!$G$5:$G$304,MATCH(B7,'Player Board'!$A$5:$A$304,0)),"")) | D7: =IFERROR(LOOKUP(2,1/(('Auction Log'!$F$5:$F$304=A7)*('Auction Log'!$D$5:$D$304="ME")),'Auction Log'!$E$5:$E$304),"") | E7: =IF(B7="","",IFERROR(INDEX('Player Board'!$H$5:$H$304,MATCH(B7,'Player Board'!$A$5:$A$304,0)),"")) | F7: =IF(B7="","",IFERROR(INDEX('Player Board'!$AA$5:$AA$304,MATCH(B7,'Player Board'!$A$5:$A$304,0)),"")) | G7: =IF(B7="","",IFERROR(INDEX('Player Board'!$R$5:$R$304,MATCH(B7,'Player Board'!$A$5:$A$304,0)),"")) | H7: =IF(D7="","",G7-D7) | I7: =IF(B7="","",IFERROR(INDEX('Player Board'!$U$5:$U$304,MATCH(B7,'Player Board'!$A$5:$A$304,0)),"")) | J7: =IF(B7="","",IF(H7>=5,"STEAL",IF(H7>=2,"VALUE",IF(H7>=-1,"FAIR","OVERPAY"))))
A8: RB1 | B8: =IFERROR(LOOKUP(2,1/(('Auction Log'!$F$5:$F$304=A8)*('Auction Log'!$D$5:$D$304="ME")),'Auction Log'!$B$5:$B$304),"") | C8: =IF(B8="","",IFERROR(INDEX('Player Board'!$G$5:$G$304,MATCH(B8,'Player Board'!$A$5:$A$304,0)),"")) | D8: =IFERROR(LOOKUP(2,1/(('Auction Log'!$F$5:$F$304=A8)*('Auction Log'!$D$5:$D$304="ME")),'Auction Log'!$E$5:$E$304),"") | E8: =IF(B8="","",IFERROR(INDEX('Player Board'!$H$5:$H$304,MATCH(B8,'Player Board'!$A$5:$A$304,0)),"")) | F8: =IF(B8="","",IFERROR(INDEX('Player Board'!$AA$5:$AA$304,MATCH(B8,'Player Board'!$A$5:$A$304,0)),"")) | G8: =IF(B8="","",IFERROR(INDEX('Player Board'!$R$5:$R$304,MATCH(B8,'Player Board'!$A$5:$A$304,0)),"")) | H8: =IF(D8="","",G8-D8) | I8: =IF(B8="","",IFERROR(INDEX('Player Board'!$U$5:$U$304,MATCH(B8,'Player Board'!$A$5:$A$304,0)),"")) | J8: =IF(B8="","",IF(H8>=5,"STEAL",IF(H8>=2,"VALUE",IF(H8>=-1,"FAIR","OVERPAY"))))
A9: RB2 | B9: =IFERROR(LOOKUP(2,1/(('Auction Log'!$F$5:$F$304=A9)*('Auction Log'!$D$5:$D$304="ME")),'Auction Log'!$B$5:$B$304),"") | C9: =IF(B9="","",IFERROR(INDEX('Player Board'!$G$5:$G$304,MATCH(B9,'Player Board'!$A$5:$A$304,0)),"")) | D9: =IFERROR(LOOKUP(2,1/(('Auction Log'!$F$5:$F$304=A9)*('Auction Log'!$D$5:$D$304="ME")),'Auction Log'!$E$5:$E$304),"") | E9: =IF(B9="","",IFERROR(INDEX('Player Board'!$H$5:$H$304,MATCH(B9,'Player Board'!$A$5:$A$304,0)),"")) | F9: =IF(B9="","",IFERROR(INDEX('Player Board'!$AA$5:$AA$304,MATCH(B9,'Player Board'!$A$5:$A$304,0)),"")) | G9: =IF(B9="","",IFERROR(INDEX('Player Board'!$R$5:$R$304,MATCH(B9,'Player Board'!$A$5:$A$304,0)),"")) | H9: =IF(D9="","",G9-D9) | I9: =IF(B9="","",IFERROR(INDEX('Player Board'!$U$5:$U$304,MATCH(B9,'Player Board'!$A$5:$A$304,0)),"")) | J9: =IF(B9="","",IF(H9>=5,"STEAL",IF(H9>=2,"VALUE",IF(H9>=-1,"FAIR","OVERPAY"))))
A10: WR1 | B10: =IFERROR(LOOKUP(2,1/(('Auction Log'!$F$5:$F$304=A10)*('Auction Log'!$D$5:$D$304="ME")),'Auction Log'!$B$5:$B$304),"") | C10: =IF(B10="","",IFERROR(INDEX('Player Board'!$G$5:$G$304,MATCH(B10,'Player Board'!$A$5:$A$304,0)),"")) | D10: =IFERROR(LOOKUP(2,1/(('Auction Log'!$F$5:$F$304=A10)*('Auction Log'!$D$5:$D$304="ME")),'Auction Log'!$E$5:$E$304),"") | E10: =IF(B10="","",IFERROR(INDEX('Player Board'!$H$5:$H$304,MATCH(B10,'Player Board'!$A$5:$A$304,0)),"")) | F10: =IF(B10="","",IFERROR(INDEX('Player Board'!$AA$5:$AA$304,MATCH(B10,'Player Board'!$A$5:$A$304,0)),"")) | G10: =IF(B10="","",IFERROR(INDEX('Player Board'!$R$5:$R$304,MATCH(B10,'Player Board'!$A$5:$A$304,0)),"")) | H10: =IF(D10="","",G10-D10) | I10: =IF(B10="","",IFERROR(INDEX('Player Board'!$U$5:$U$304,MATCH(B10,'Player Board'!$A$5:$A$304,0)),"")) | J10: =IF(B10="","",IF(H10>=5,"STEAL",IF(H10>=2,"VALUE",IF(H10>=-1,"FAIR","OVERPAY"))))
A11: WR2 | B11: =IFERROR(LOOKUP(2,1/(('Auction Log'!$F$5:$F$304=A11)*('Auction Log'!$D$5:$D$304="ME")),'Auction Log'!$B$5:$B$304),"") | C11: =IF(B11="","",IFERROR(INDEX('Player Board'!$G$5:$G$304,MATCH(B11,'Player Board'!$A$5:$A$304,0)),"")) | D11: =IFERROR(LOOKUP(2,1/(('Auction Log'!$F$5:$F$304=A11)*('Auction Log'!$D$5:$D$304="ME")),'Auction Log'!$E$5:$E$304),"") | E11: =IF(B11="","",IFERROR(INDEX('Player Board'!$H$5:$H$304,MATCH(B11,'Player Board'!$A$5:$A$304,0)),"")) | F11: =IF(B11="","",IFERROR(INDEX('Player Board'!$AA$5:$AA$304,MATCH(B11,'Player Board'!$A$5:$A$304,0)),"")) | G11: =IF(B11="","",IFERROR(INDEX('Player Board'!$R$5:$R$304,MATCH(B11,'Player Board'!$A$5:$A$304,0)),"")) | H11: =IF(D11="","",G11-D11) | I11: =IF(B11="","",IFERROR(INDEX('Player Board'!$U$5:$U$304,MATCH(B11,'Player Board'!$A$5:$A$304,0)),"")) | J11: =IF(B11="","",IF(H11>=5,"STEAL",IF(H11>=2,"VALUE",IF(H11>=-1,"FAIR","OVERPAY"))))
A12: TE | B12: =IFERROR(LOOKUP(2,1/(('Auction Log'!$F$5:$F$304=A12)*('Auction Log'!$D$5:$D$304="ME")),'Auction Log'!$B$5:$B$304),"") | C12: =IF(B12="","",IFERROR(INDEX('Player Board'!$G$5:$G$304,MATCH(B12,'Player Board'!$A$5:$A$304,0)),"")) | D12: =IFERROR(LOOKUP(2,1/(('Auction Log'!$F$5:$F$304=A12)*('Auction Log'!$D$5:$D$304="ME")),'Auction Log'!$E$5:$E$304),"") | E12: =IF(B12="","",IFERROR(INDEX('Player Board'!$H$5:$H$304,MATCH(B12,'Player Board'!$A$5:$A$304,0)),"")) | F12: =IF(B12="","",IFERROR(INDEX('Player Board'!$AA$5:$AA$304,MATCH(B12,'Player Board'!$A$5:$A$304,0)),"")) | G12: =IF(B12="","",IFERROR(INDEX('Player Board'!$R$5:$R$304,MATCH(B12,'Player Board'!$A$5:$A$304,0)),"")) | H12: =IF(D12="","",G12-D12) | I12: =IF(B12="","",IFERROR(INDEX('Player Board'!$U$5:$U$304,MATCH(B12,'Player Board'!$A$5:$A$304,0)),"")) | J12: =IF(B12="","",IF(H12>=5,"STEAL",IF(H12>=2,"VALUE",IF(H12>=-1,"FAIR","OVERPAY"))))
A13: FLEX | B13: =IFERROR(LOOKUP(2,1/(('Auction Log'!$F$5:$F$304=A13)*('Auction Log'!$D$5:$D$304="ME")),'Auction Log'!$B$5:$B$304),"") | C13: =IF(B13="","",IFERROR(INDEX('Player Board'!$G$5:$G$304,MATCH(B13,'Player Board'!$A$5:$A$304,0)),"")) | D13: =IFERROR(LOOKUP(2,1/(('Auction Log'!$F$5:$F$304=A13)*('Auction Log'!$D$5:$D$304="ME")),'Auction Log'!$E$5:$E$304),"") | E13: =IF(B13="","",IFERROR(INDEX('Player Board'!$H$5:$H$304,MATCH(B13,'Player Board'!$A$5:$A$304,0)),"")) | F13: =IF(B13="","",IFERROR(INDEX('Player Board'!$AA$5:$AA$304,MATCH(B13,'Player Board'!$A$5:$A$304,0)),"")) | G13: =IF(B13="","",IFERROR(INDEX('Player Board'!$R$5:$R$304,MATCH(B13,'Player Board'!$A$5:$A$304,0)),"")) | H13: =IF(D13="","",G13-D13) | I13: =IF(B13="","",IFERROR(INDEX('Player Board'!$U$5:$U$304,MATCH(B13,'Player Board'!$A$5:$A$304,0)),"")) | J13: =IF(B13="","",IF(H13>=5,"STEAL",IF(H13>=2,"VALUE",IF(H13>=-1,"FAIR","OVERPAY"))))
A14: D/ST | B14: =IFERROR(LOOKUP(2,1/(('Auction Log'!$F$5:$F$304=A14)*('Auction Log'!$D$5:$D$304="ME")),'Auction Log'!$B$5:$B$304),"") | C14: =IF(B14="","",IFERROR(INDEX('Player Board'!$G$5:$G$304,MATCH(B14,'Player Board'!$A$5:$A$304,0)),"")) | D14: =IFERROR(LOOKUP(2,1/(('Auction Log'!$F$5:$F$304=A14)*('Auction Log'!$D$5:$D$304="ME")),'Auction Log'!$E$5:$E$304),"") | E14: =IF(B14="","",IFERROR(INDEX('Player Board'!$H$5:$H$304,MATCH(B14,'Player Board'!$A$5:$A$304,0)),"")) | F14: =IF(B14="","",IFERROR(INDEX('Player Board'!$AA$5:$AA$304,MATCH(B14,'Player Board'!$A$5:$A$304,0)),"")) | G14: =IF(B14="","",IFERROR(INDEX('Player Board'!$R$5:$R$304,MATCH(B14,'Player Board'!$A$5:$A$304,0)),"")) | H14: =IF(D14="","",G14-D14) | I14: =IF(B14="","",IFERROR(INDEX('Player Board'!$U$5:$U$304,MATCH(B14,'Player Board'!$A$5:$A$304,0)),"")) | J14: =IF(B14="","",IF(H14>=5,"STEAL",IF(H14>=2,"VALUE",IF(H14>=-1,"FAIR","OVERPAY"))))
A15: K | B15: =IFERROR(LOOKUP(2,1/(('Auction Log'!$F$5:$F$304=A15)*('Auction Log'!$D$5:$D$304="ME")),'Auction Log'!$B$5:$B$304),"") | C15: =IF(B15="","",IFERROR(INDEX('Player Board'!$G$5:$G$304,MATCH(B15,'Player Board'!$A$5:$A$304,0)),"")) | D15: =IFERROR(LOOKUP(2,1/(('Auction Log'!$F$5:$F$304=A15)*('Auction Log'!$D$5:$D$304="ME")),'Auction Log'!$E$5:$E$304),"") | E15: =IF(B15="","",IFERROR(INDEX('Player Board'!$H$5:$H$304,MATCH(B15,'Player Board'!$A$5:$A$304,0)),"")) | F15: =IF(B15="","",IFERROR(INDEX('Player Board'!$AA$5:$AA$304,MATCH(B15,'Player Board'!$A$5:$A$304,0)),"")) | G15: =IF(B15="","",IFERROR(INDEX('Player Board'!$R$5:$R$304,MATCH(B15,'Player Board'!$A$5:$A$304,0)),"")) | H15: =IF(D15="","",G15-D15) | I15: =IF(B15="","",IFERROR(INDEX('Player Board'!$U$5:$U$304,MATCH(B15,'Player Board'!$A$5:$A$304,0)),"")) | J15: =IF(B15="","",IF(H15>=5,"STEAL",IF(H15>=2,"VALUE",IF(H15>=-1,"FAIR","OVERPAY"))))
A16: BE1 | B16: =IFERROR(LOOKUP(2,1/(('Auction Log'!$F$5:$F$304=A16)*('Auction Log'!$D$5:$D$304="ME")),'Auction Log'!$B$5:$B$304),"") | C16: =IF(B16="","",IFERROR(INDEX('Player Board'!$G$5:$G$304,MATCH(B16,'Player Board'!$A$5:$A$304,0)),"")) | D16: =IFERROR(LOOKUP(2,1/(('Auction Log'!$F$5:$F$304=A16)*('Auction Log'!$D$5:$D$304="ME")),'Auction Log'!$E$5:$E$304),"") | E16: =IF(B16="","",IFERROR(INDEX('Player Board'!$H$5:$H$304,MATCH(B16,'Player Board'!$A$5:$A$304,0)),"")) | F16: =IF(B16="","",IFERROR(INDEX('Player Board'!$AA$5:$AA$304,MATCH(B16,'Player Board'!$A$5:$A$304,0)),"")) | G16: =IF(B16="","",IFERROR(INDEX('Player Board'!$R$5:$R$304,MATCH(B16,'Player Board'!$A$5:$A$304,0)),"")) | H16: =IF(D16="","",G16-D16) | I16: =IF(B16="","",IFERROR(INDEX('Player Board'!$U$5:$U$304,MATCH(B16,'Player Board'!$A$5:$A$304,0)),"")) | J16: =IF(B16="","",IF(H16>=5,"STEAL",IF(H16>=2,"VALUE",IF(H16>=-1,"FAIR","OVERPAY"))))
A17: BE2 | B17: =IFERROR(LOOKUP(2,1/(('Auction Log'!$F$5:$F$304=A17)*('Auction Log'!$D$5:$D$304="ME")),'Auction Log'!$B$5:$B$304),"") | C17: =IF(B17="","",IFERROR(INDEX('Player Board'!$G$5:$G$304,MATCH(B17,'Player Board'!$A$5:$A$304,0)),"")) | D17: =IFERROR(LOOKUP(2,1/(('Auction Log'!$F$5:$F$304=A17)*('Auction Log'!$D$5:$D$304="ME")),'Auction Log'!$E$5:$E$304),"") | E17: =IF(B17="","",IFERROR(INDEX('Player Board'!$H$5:$H$304,MATCH(B17,'Player Board'!$A$5:$A$304,0)),"")) | F17: =IF(B17="","",IFERROR(INDEX('Player Board'!$AA$5:$AA$304,MATCH(B17,'Player Board'!$A$5:$A$304,0)),"")) | G17: =IF(B17="","",IFERROR(INDEX('Player Board'!$R$5:$R$304,MATCH(B17,'Player Board'!$A$5:$A$304,0)),"")) | H17: =IF(D17="","",G17-D17) | I17: =IF(B17="","",IFERROR(INDEX('Player Board'!$U$5:$U$304,MATCH(B17,'Player Board'!$A$5:$A$304,0)),"")) | J17: =IF(B17="","",IF(H17>=5,"STEAL",IF(H17>=2,"VALUE",IF(H17>=-1,"FAIR","OVERPAY"))))
A18: BE3 | B18: =IFERROR(LOOKUP(2,1/(('Auction Log'!$F$5:$F$304=A18)*('Auction Log'!$D$5:$D$304="ME")),'Auction Log'!$B$5:$B$304),"") | C18: =IF(B18="","",IFERROR(INDEX('Player Board'!$G$5:$G$304,MATCH(B18,'Player Board'!$A$5:$A$304,0)),"")) | D18: =IFERROR(LOOKUP(2,1/(('Auction Log'!$F$5:$F$304=A18)*('Auction Log'!$D$5:$D$304="ME")),'Auction Log'!$E$5:$E$304),"") | E18: =IF(B18="","",IFERROR(INDEX('Player Board'!$H$5:$H$304,MATCH(B18,'Player Board'!$A$5:$A$304,0)),"")) | F18: =IF(B18="","",IFERROR(INDEX('Player Board'!$AA$5:$AA$304,MATCH(B18,'Player Board'!$A$5:$A$304,0)),"")) | G18: =IF(B18="","",IFERROR(INDEX('Player Board'!$R$5:$R$304,MATCH(B18,'Player Board'!$A$5:$A$304,0)),"")) | H18: =IF(D18="","",G18-D18) | I18: =IF(B18="","",IFERROR(INDEX('Player Board'!$U$5:$U$304,MATCH(B18,'Player Board'!$A$5:$A$304,0)),"")) | J18: =IF(B18="","",IF(H18>=5,"STEAL",IF(H18>=2,"VALUE",IF(H18>=-1,"FAIR","OVERPAY"))))
... A21: BE6 | B21: =IFERROR(LOOKUP(2,1/(('Auction Log'!$F$5:$F$304=A21)*('Auction Log'!$D$5:$D$304="ME")),'Auction Log'!$B$5:$B$304),"") | C21: =IF(B21="","",IFERROR(INDEX('Player Board'!$G$5:$G$304,MATCH(B21,'Player Board'!$A$5:$A$304,0)),"")) | D21: =IFERROR(LOOKUP(2,1/(('Auction Log'!$F$5:$F$304=A21)*('Auction Log'!$D$5:$D$304="ME")),'Auction Log'!$E$5:$E$304),"") | E21: =IF(B21="","",IFERROR(INDEX('Player Board'!$H$5:$H$304,MATCH(B21,'Player Board'!$A$5:$A$304,0)),"")) | F21: =IF(B21="","",IFERROR(INDEX('Player Board'!$AA$5:$AA$304,MATCH(B21,'Player Board'!$A$5:$A$304,0)),"")) | G21: =IF(B21="","",IFERROR(INDEX('Player Board'!$R$5:$R$304,MATCH(B21,'Player Board'!$A$5:$A$304,0)),"")) | H21: =IF(D21="","",G21-D21) | I21: =IF(B21="","",IFERROR(INDEX('Player Board'!$U$5:$U$304,MATCH(B21,'Player Board'!$A$5:$A$304,0)),"")) | J21: =IF(B21="","",IF(H21>=5,"STEAL",IF(H21>=2,"VALUE",IF(H21>=-1,"FAIR","OVERPAY"))))
A23: POSITION PROJECTION VS DRAFTED AVERAGE
A24: Position | B24: My Avg Proj | C24: Drafted Avg | D24: Difference | E24: Status
A25: QB | B25: =IFERROR(AVERAGEIF($C$7:$C$21,A25,$F$7:$F$21),0) -> 0 | C25: =IFERROR(AVERAGEIF('Auction Log'!$C$5:$C$304,A25,'Auction Log'!$K$5:$K$304),0) -> 0 | D25: =B25-C25 -> 0 | E25: =IF(D25>5,"ABOVE AVG",IF(D25<-5,"BELOW AVG","ON PAR")) -> ON PAR
A26: RB | B26: =IFERROR(AVERAGEIF($C$7:$C$21,A26,$F$7:$F$21),0) -> 0 | C26: =IFERROR(AVERAGEIF('Auction Log'!$C$5:$C$304,A26,'Auction Log'!$K$5:$K$304),0) -> 0 | D26: =B26-C26 -> 0 | E26: =IF(D26>5,"ABOVE AVG",IF(D26<-5,"BELOW AVG","ON PAR")) -> ON PAR
A27: WR | B27: =IFERROR(AVERAGEIF($C$7:$C$21,A27,$F$7:$F$21),0) -> 0 | C27: =IFERROR(AVERAGEIF('Auction Log'!$C$5:$C$304,A27,'Auction Log'!$K$5:$K$304),0) -> 0 | D27: =B27-C27 -> 0 | E27: =IF(D27>5,"ABOVE AVG",IF(D27<-5,"BELOW AVG","ON PAR")) -> ON PAR
A28: TE | B28: =IFERROR(AVERAGEIF($C$7:$C$21,A28,$F$7:$F$21),0) -> 0 | C28: =IFERROR(AVERAGEIF('Auction Log'!$C$5:$C$304,A28,'Auction Log'!$K$5:$K$304),0) -> 0 | D28: =B28-C28 -> 0 | E28: =IF(D28>5,"ABOVE AVG",IF(D28<-5,"BELOW AVG","ON PAR")) -> ON PAR

Sheet Strategy
A1: DRAFT-DAY OPERATING PLAN
A2: A controlled-aggression auction plan tailored to 14 teams, full PPR, one FLEX, a $200 cap, and meaningful explosive-play / yardage bonuses.
A4: LEAGUE EDGES TO EXPLOIT
A5: 1. 14-team scarcity matters: do not leave the room with a weak RB2 or TE after chasing two $55+ stars.
A6: 2. Full PPR makes repeatable targets the base; the bonus rules then break ties toward explosive, high-yardage profiles.
A7: 3. Only one FLEX means the room may overpay WR depth; retain the option to flex an RB when prices shift.
A8: 4. Eight playoff teams reward floor first, but one-week playoffs reward keeping ceiling on the roster.
A9: 5. No acquisition limit: draft upside and churn the final bench spots aggressively after Week 1 roles become real.
A11: $200 ROLE BLUEPRINT | E11: NOMINATION SEQUENCE
A12: Role | B12: Budget | C12: Operating range | E12: Phase | F12: Action
A13: Anchor | B13: 62 | C13: $52–$66 | E13: Opening 1–20 | F13: Nominate DRAIN-tagged expensive players you do not want. Learn the room before exposing targets.
A14: Core starter 2 | B14: 34 | C14: $28–$40
A15: Core starter 3 | B15: 25 | C15: $20–$30 | E15: Middle 21–90 | F15: Nominate from a tier where you will buy any survivor at Target Price. Do not wait for the final name.
A16: Starter 4 | B16: 20 | C16: $15–$24
A17: FLEX starter | B17: 15 | C17: $10–$19 | E17: Late 91+ | F17: Nominate your $1 targets while at least two rivals can still bid; otherwise they can be stolen uncontested.
A18: QB | B18: 9 | C18: $4–$15
A19: TE | B19: 10 | C19: $4–$16 | E19: Whenever stuck | F19: Nominate a position a cash-rich rival needs. Every dollar removed improves your endgame leverage.
A20: Six bench spots | B20: 23 | C20: $1–$8 each
A21: D/ST + K | B21: 2 | C21: $1 each
A23: BIDDING RULES — RUN THESE IN ORDER
A24: Step | B24: Decision | C24: Rule
A25: 1 | B25: Check legal max | C25: Draft HQ Absolute Max Bid preserves $1 for every remaining slot.
A26: 2 | B26: Check room price | C26: Inflation factor converts the static ceiling into today’s room-adjusted ceiling.
A27: 3 | B27: Check roster fit | C27: Do not buy a second QB, D/ST or K early; protect RB/WR depth.
A28: 4 | B28: Bid assertively | C28: Below Target Price, use $2 jumps to discourage price-enforcement bidders.
A29: 5 | B29: Stop cleanly | C29: At SAFE BID NOW, stop. A replacement tier is already on Player Board.
A32: ANCHOR MENU — BUY ONE, NOT TWO, UNLESS BOTH CLEAR TARGET
A33: Player | B33: Pos | C33: Market | D33: Hard | E33: Target | F33: Why this format
A34: Jahmyr Gibbs | B34: RB | C34: 59 | D34: 66 | E34: 62 | F34: Elite PPR role plus rushing-yardage and explosive-TD bonus paths.
A35: Ja'Marr Chase | B35: WR | C35: 58 | D35: 65 | E35: 61 | F35: Safest elite target volume with multi-bonus receiving ceiling.
A36: Bijan Robinson | B36: RB | C36: 58 | D36: 65 | E36: 61 | F36: Three-down PPR workload; less touchdown-dependent than most RBs.
A37: Jaxon Smith-Njigba | B37: WR | C37: 55 | D37: 63 | E37: 59 | F37: Volume and projected yardage align perfectly with 100-yard bonuses.
A38: Amon-Ra St. Brown | B38: WR | C38: 53 | D38: 60 | E38: 56 | F38: High reception floor with repeatable 100-yard game access.
A39: CeeDee Lamb | B39: WR | C39: 39 | D39: 48 | E39: 44 | F39: Consensus rank is stronger than current auction projection price.
A40: Justin Jefferson | B40: WR | C40: 39 | D40: 46 | E40: 42 | F40: Consensus discount creates an elite talent buying window.
A41: Jonathan Taylor | B41: RB | C41: 43 | D41: 51 | E41: 47 | F41: Workhorse rushing profile gains the most from 100/200-yard bonuses.
A43: VALUE TARGETS — PRICE, NOT PLAYER, IS THE EDGE
A44: Player | B44: Pos | C44: Market | D44: Hard | E44: Target | F44: Case
A45: Justin Herbert | B45: QB | C45: 7 | D45: 10 | E45: 8 | F45: Pocket volume and rushing support; bonuses preserve upside without elite-QB price.
A46: Trevor Lawrence | B46: QB | C46: 9 | D46: 12 | E46: 10 | F46: Strong 14-team starter price; 300-yard and long-TD bonus paths.
A47: Bhayshul Tuten | B47: RB | C47: 19 | D47: 18 | E47: 16 | F47: Projected volume is much stronger than the headline price.
A48: Rhamondre Stevenson | B48: RB | C48: 15 | D48: 13 | E48: 11 | F48: Full-PPR touches and a price outside the room’s glamorous tier.
A49: David Montgomery | B49: RB | C49: 16 | D49: 15 | E49: 13 | F49: Goal-line and 100-yard bonus access at a bench-friendly price.
A50: Jadarian Price | B50: RB | C50: 14 | D50: 14 | E50: 12 | F50: Cheap volume bet for a 14-team room.
A51: Nico Collins | B51: WR | C51: 32 | D51: 37 | E51: 34 | F51: Consensus and yardage ceiling both support buying above generic price.
A52: DeVonta Smith | B52: WR | C52: 29 | D52: 30 | E52: 27 | F52: PPR floor plus consensus edge versus projected auction cost.
A53: Jaylen Waddle | B53: WR | C53: 21 | D53: 23 | E53: 21 | F53: Consensus discount and explosive bonus fit.
A54: Parker Washington | B54: WR | C54: 14 | D54: 14 | E54: 12 | F54: Affordable target share; monitor the minor injury note.
A55: Michael Wilson | B55: WR | C55: 12 | D55: 9 | E55: 8 | F55: Late PPR volume at a price that preserves flexibility.
A56: Wan'Dale Robinson | B56: WR | C56: 12 | D56: 9 | E56: 8 | F56: Reception volume is unusually valuable in full PPR.
... A59: Harold Fannin Jr. | B59: TE | C59: 15 | D59: 14 | E59: 12 | F59: Target-driven TE fallback in a 14-team scarcity environment.
A62: DRAFT-DAY INJURY BOARD — RECHECK 60 MINUTES BEFORE START
A63: Player | B63: Pos | C63: Market | D63: Hard | E63: Target | F63: Current note
A64: Puka Nacua | B64: WR | C64: 59 | D64: 62 | E64: 58 | F64: Groin - still questionable; was not practicing as of 8/24 (ESPN 8/26). Discount only — no smash at full Target.
A65: Ashton Jeanty | B65: RB | C65: 32 | D65: 34 | E65: 31 | F65: Ankle - Raiders optimistic 'more low than high' sprain, not long-term (Rapoport 8/25 via ESPN). Buyable near Target; not a healthy stud.
A66: Jeremiyah Love | B66: RB | C66: 30 | D66: 29 | E66: 26 | F66: High ankle - light agility only 8/26; est. return Sep 13 (ESPN). Week 1 risk real — fade unless steal.
A67: Breece Hall | B67: RB | C67: 28 | D67: 28 | E67: 25 | F67: Groin - side agility only 8/24; earlier 2–3 week miss outlook (ESPN). Discount only — early-season hole.
A68: Patrick Mahomes II | B68: QB | C68: 8 | D68: 7 | E68: 6 | F68: Knee (ACL) - 'extremely confident' for Week 1 (8/22 via ESPN). Cheap QB plan still OK.
A69: Malik Nabers | B69: WR | C69: 30 | D69: 32 | E69: 29 | F69: Knee - still on limited/red-jersey path as of 8/23 (ESPN). Cap at Target; do not chase.
A70: Emeka Egbuka | B70: WR | C70: 26 | D70: 23 | E70: 21 | F70: Toe - not participating in practice as of 8/25 (ESPN). Soft pass / require big discount.
A71: Tyler Warren | B71: TE | C71: 17 | D71: 19 | E71: 17 | F71: Groin - may sit practice this week but staff preparing him for opener (8/25 via ESPN). Week 1 intent intact.
A72: George Kittle | B72: TE | C72: 12 | D72: 9 | E72: 8 | F72: Achilles - activated from PUP 8/23 (ESPN). Fine as cheap TE upside.
A73: Sam LaPorta | B73: TE | C73: 11 | D73: 9 | E73: 8 | F73: Hip - returned to practice 8/25 (ESPN). Prior 'uncertain' note stale; OK near Target.
A74: Tucker Kraft | B74: TE | C74: 11 | D74: 8 | E74: 7 | F74: Knee - participating in team drills 8/26 (ESPN). Less dire than prior half-season limit comment.
A76: ENDGAME TARGETS — LIVE STATUS
A77: Player | B77: Pos | C77: Target | D77: Max | E77: Status | F77: Rule
A78: Matthew Stafford | B78: =IFERROR(INDEX('Player Board'!$G$5:$G$304,MATCH(A78,'Player Board'!$A$5:$A$304,0)),"") -> QB | C78: =IFERROR(INDEX('Player Board'!$S$5:$S$304,MATCH(A78,'Player Board'!$A$5:$A$304,0)),"") -> 8 | D78: =IFERROR(INDEX('Player Board'!$R$5:$R$304,MATCH(A78,'Player Board'!$A$5:$A$304,0)),"") -> 10 | E78: =IFERROR(INDEX('Player Board'!$D$5:$D$304,MATCH(A78,'Player Board'!$A$5:$A$304,0)),"NOT ON BOARD") -> Available | F78: Reliable late QB ceiling
A79: Wan'Dale Robinson | B79: =IFERROR(INDEX('Player Board'!$G$5:$G$304,MATCH(A79,'Player Board'!$A$5:$A$304,0)),"") -> WR | C79: =IFERROR(INDEX('Player Board'!$S$5:$S$304,MATCH(A79,'Player Board'!$A$5:$A$304,0)),"") -> 8 | D79: =IFERROR(INDEX('Player Board'!$R$5:$R$304,MATCH(A79,'Player Board'!$A$5:$A$304,0)),"") -> 9 | E79: =IFERROR(INDEX('Player Board'!$D$5:$D$304,MATCH(A79,'Player Board'!$A$5:$A$304,0)),"NOT ON BOARD") -> Available | F79: Full-PPR volume
A80: Michael Wilson | B80: =IFERROR(INDEX('Player Board'!$G$5:$G$304,MATCH(A80,'Player Board'!$A$5:$A$304,0)),"") -> WR | C80: =IFERROR(INDEX('Player Board'!$S$5:$S$304,MATCH(A80,'Player Board'!$A$5:$A$304,0)),"") -> 8 | D80: =IFERROR(INDEX('Player Board'!$R$5:$R$304,MATCH(A80,'Player Board'!$A$5:$A$304,0)),"") -> 9 | E80: =IFERROR(INDEX('Player Board'!$D$5:$D$304,MATCH(A80,'Player Board'!$A$5:$A$304,0)),"NOT ON BOARD") -> Available | F80: Cheap target share
A81: Kyle Pitts Sr. | B81: =IFERROR(INDEX('Player Board'!$G$5:$G$304,MATCH(A81,'Player Board'!$A$5:$A$304,0)),"") -> TE | C81: =IFERROR(INDEX('Player Board'!$S$5:$S$304,MATCH(A81,'Player Board'!$A$5:$A$304,0)),"") -> 12 | D81: =IFERROR(INDEX('Player Board'!$R$5:$R$304,MATCH(A81,'Player Board'!$A$5:$A$304,0)),"") -> 14 | E81: =IFERROR(INDEX('Player Board'!$D$5:$D$304,MATCH(A81,'Player Board'!$A$5:$A$304,0)),"NOT ON BOARD") -> Available | F81: TE upside at a discount
A82: David Montgomery | B82: =IFERROR(INDEX('Player Board'!$G$5:$G$304,MATCH(A82,'Player Board'!$A$5:$A$304,0)),"") -> RB | C82: =IFERROR(INDEX('Player Board'!$S$5:$S$304,MATCH(A82,'Player Board'!$A$5:$A$304,0)),"") -> 13 | D82: =IFERROR(INDEX('Player Board'!$R$5:$R$304,MATCH(A82,'Player Board'!$A$5:$A$304,0)),"") -> 15 | E82: =IFERROR(INDEX('Player Board'!$D$5:$D$304,MATCH(A82,'Player Board'!$A$5:$A$304,0)),"NOT ON BOARD") -> Available | F82: RB touchdown and yardage access
A84: MACRO-FREE RECOVERY CONTROLS
A85: Undo last sale | B85: Clear Player, Winner, Price, Roster Slot and Note in the Auction Log row marked LAST.
A86: Clear draft data | B86: Select Auction Log input ranges B5:B304, D5:F304 and I5:I304; press Delete. Formulas remain intact.
A87: Refresh formulas | B87: Press Ctrl+Alt+F9 if Excel calculation is set to Manual.

Sheet Sources
A1: SOURCES & MODEL NOTES
A2: Values are a decision aid, not a prediction of exact room prices. All web data checked August 25, 2026 ET.
A4: Source | B4: Used for | C4: As of | D4: URL
A5: League screenshots | B5: Exact roster, cap, PPR and custom scoring settings | C5: 2026-08-25 | D5: Attached league-info screenshots
A6: FantasyPros PPR ECR | B6: Current consensus rank, tiers and rank disagreement | C6: 2026-08-25 | D6: https://www.fantasypros.com/nfl/rankings/ppr-cheatsheets.php
A7: FantasyPros Auction Calculator | B7: 14-team / $200 / PPR market baseline | C7: 2026-08-25 | D7: https://www.fantasypros.com/nfl/auction-values/calculator.php
A8: ESPN Mike Clay Projection Guide | B8: Player-level PPR projections and underlying volume | C8: 2026-08-19 | D8: https://g.espncdn.com/s/ffldraftkit/26/NFLDK2026_CS_ClayProjections2026.pdf
A9: ESPN PPR Top 300 | B9: Independent ESPN rank and 10-team value comparison | C9: 2026-08-19 | D9: https://g.espncdn.com/s/ffldraftkit/26/NFL26_CS_PPR300.pdf?adddata=2026CS_PPR300
A10: ESPN NFL Injuries | B10: Current injury cross-check | C10: 2026-08-25 | D10: https://www.espn.com/nfl/injuries
A11: ESPN Fantasy Buzz | B11: Fantasy-relevant injury and role context | C11: 2026-08-25 | D11: https://www.espn.com/fantasy/football/story/_/id/40699880/fantasy-football-injuries-position-battles-nfl-news-analysis
A12: Field Yates PPR Top 160 | B12: Current ESPN rank sanity check | C12: 2026-08-24 | D12: https://www.espn.com/fantasy/football/story/_/id/48711830/2026-fantasy-football-rankings-ppr-field-yates
A13: Model calibration | B13: 210-player draft pool sums to the league-wide $2,800 budget | C13: 2026-08-25 | D13: Raw pool $2670; scale 1.0528; bonus medians QB 10.7, RB 2.1, WR 3.6, TE 0.7
A14: Workbook v2 intelligence | B14: Dynamic exposure, tier scarcity, rival threat, phase logic, projections and draft grading | C14: 2026-08-25 | D14: Formula-driven from Player Board, Auction Log, Team Tracker and My Roster

Sheet Draft Grade
A1: POST-DRAFT GRADE & HAUL SUMMARY
A2: Grades update automatically. Before all 15 slots are filled, the overall result remains INCOMPLETE. Room averages use the market baseline until sales are logged.
A4: GRADE SUMMARY | E4: POSITION SPEND VS ROOM AVERAGE
A5: Draft status | B5: =IF('Draft HQ'!B8=15,"COMPLETE","INCOMPLETE — "&'Draft HQ'!B9&" slots left") -> INCOMPLETE — 15 slots left | E5: Position | F5: My Spend | G5: Room Avg / Baseline | H5: Difference | I5: Status
A6: Total spent | B6: ='Draft HQ'!B6 -> 0 | E6: QB | F6: =SUMIFS('Auction Log'!$E$5:$E$304,'Auction Log'!$D$5:$D$304,"ME",'Auction Log'!$C$5:$C$304,E6) -> 0 | G6: =IF(COUNTIF('Auction Log'!$C$5:$C$304,E6)>=14,SUMIFS('Auction Log'!$E$5:$E$304,'Auction Log'!$C$5:$C$304,E6)/14,INDEX('Draft HQ'!$I$6:$I$11,MATCH(E6,'Draft HQ'!$H$6:$H$11,0))) -> 9 | H6: =F6-G6 -> -9 | I6: =IF('Draft HQ'!$B$8<15,"BUILDING",IF(H6>MAX(2,G6*20%),"OVERSPENT",IF(H6<-MAX(2,G6*20%),"EFFICIENT","ON PLAN"))) -> BUILDING
A7: Value bought | B7: =SUMIF('Auction Log'!$D$5:$D$304,"ME",'Auction Log'!$G$5:$G$304) -> 0 | E7: RB | F7: =SUMIFS('Auction Log'!$E$5:$E$304,'Auction Log'!$D$5:$D$304,"ME",'Auction Log'!$C$5:$C$304,E7) -> 0 | G7: =IF(COUNTIF('Auction Log'!$C$5:$C$304,E7)>=14,SUMIFS('Auction Log'!$E$5:$E$304,'Auction Log'!$C$5:$C$304,E7)/14,INDEX('Draft HQ'!$I$6:$I$11,MATCH(E7,'Draft HQ'!$H$6:$H$11,0))) -> 90 | H7: =F7-G7 -> -90 | I7: =IF('Draft HQ'!$B$8<15,"BUILDING",IF(H7>MAX(2,G7*20%),"OVERSPENT",IF(H7<-MAX(2,G7*20%),"EFFICIENT","ON PLAN"))) -> BUILDING
A8: Value captured | B8: =B7-B6 -> 0 | E8: WR | F8: =SUMIFS('Auction Log'!$E$5:$E$304,'Auction Log'!$D$5:$D$304,"ME",'Auction Log'!$C$5:$C$304,E8) -> 0 | G8: =IF(COUNTIF('Auction Log'!$C$5:$C$304,E8)>=14,SUMIFS('Auction Log'!$E$5:$E$304,'Auction Log'!$C$5:$C$304,E8)/14,INDEX('Draft HQ'!$I$6:$I$11,MATCH(E8,'Draft HQ'!$H$6:$H$11,0))) -> 88 | H8: =F8-G8 -> -88 | I8: =IF('Draft HQ'!$B$8<15,"BUILDING",IF(H8>MAX(2,G8*20%),"OVERSPENT",IF(H8<-MAX(2,G8*20%),"EFFICIENT","ON PLAN"))) -> BUILDING
A9: Roster projection | B9: =SUM('My Roster'!$F$7:$F$21) -> 0 | E9: TE | F9: =SUMIFS('Auction Log'!$E$5:$E$304,'Auction Log'!$D$5:$D$304,"ME",'Auction Log'!$C$5:$C$304,E9) -> 0 | G9: =IF(COUNTIF('Auction Log'!$C$5:$C$304,E9)>=14,SUMIFS('Auction Log'!$E$5:$E$304,'Auction Log'!$C$5:$C$304,E9)/14,INDEX('Draft HQ'!$I$6:$I$11,MATCH(E9,'Draft HQ'!$H$6:$H$11,0))) -> 11 | H9: =F9-G9 -> -11 | I9: =IF('Draft HQ'!$B$8<15,"BUILDING",IF(H9>MAX(2,G9*20%),"OVERSPENT",IF(H9<-MAX(2,G9*20%),"EFFICIENT","ON PLAN"))) -> BUILDING
A10: League avg projection | B10: =IF('Draft HQ'!B15<210,SUMIFS('Player Board'!$AA$5:$AA$304,'Player Board'!$W$5:$W$304,"YES")/14,SUM('Auction Log'!$K$5:$K$304)/14) -> 2612.3571 | E10: D/ST | F10: =SUMIFS('Auction Log'!$E$5:$E$304,'Auction Log'!$D$5:$D$304,"ME",'Auction Log'!$C$5:$C$304,E10) -> 0 | G10: =IF(COUNTIF('Auction Log'!$C$5:$C$304,E10)>=14,SUMIFS('Auction Log'!$E$5:$E$304,'Auction Log'!$C$5:$C$304,E10)/14,INDEX('Draft HQ'!$I$6:$I$11,MATCH(E10,'Draft HQ'!$H$6:$H$11,0))) -> 1 | H10: =F10-G10 -> -1 | I10: =IF('Draft HQ'!$B$8<15,"BUILDING",IF(H10>MAX(2,G10*20%),"OVERSPENT",IF(H10<-MAX(2,G10*20%),"EFFICIENT","ON PLAN"))) -> BUILDING
A11: Completion | B11: ='Draft HQ'!B8/15 -> 0 | E11: K | F11: =SUMIFS('Auction Log'!$E$5:$E$304,'Auction Log'!$D$5:$D$304,"ME",'Auction Log'!$C$5:$C$304,E11) -> 0 | G11: =IF(COUNTIF('Auction Log'!$C$5:$C$304,E11)>=14,SUMIFS('Auction Log'!$E$5:$E$304,'Auction Log'!$C$5:$C$304,E11)/14,INDEX('Draft HQ'!$I$6:$I$11,MATCH(E11,'Draft HQ'!$H$6:$H$11,0))) -> 1 | H11: =F11-G11 -> -1 | I11: =IF('Draft HQ'!$B$8<15,"BUILDING",IF(H11>MAX(2,G11*20%),"OVERSPENT",IF(H11<-MAX(2,G11*20%),"EFFICIENT","ON PLAN"))) -> BUILDING
A13: SCORECARD
A14: Metric | B14: Score | C14: Rating
A15: Value efficiency | B15: =IF(B6=0,0,MAX(0,MIN(100,75+(B8/B6)*100))) -> 0 | C15: =REPT("★",ROUND(B15/20,0))
A16: Projection strength | B16: =IF(B10=0,0,MAX(0,MIN(100,75+(B9/B10-1)*100))) -> 0 | C16: =REPT("★",ROUND(B16/20,0))
A17: Positional balance | B17: =100*(MIN(1,'Team Tracker'!I5/5)*35%+MIN(1,'Team Tracker'!J5/5)*35%+MIN(1,'Team Tracker'!H5)*10%+MIN(1,'Team Tracker'!K5)*10%+MIN(1,'Team Tracker'!L5)*5%+MIN(1,'Team Tracker'!M5)*5%) -> 0 | C17: =REPT("★",ROUND(B17/20,0))
A18: Star power | B18: =MIN(100,COUNTIFS('Auction Log'!$D$5:$D$304,"ME",'Auction Log'!$G$5:$G$304,">=40")*35+COUNTIFS('Auction Log'!$D$5:$D$304,"ME",'Auction Log'!$G$5:$G$304,">=25",'Auction Log'!$G$5:$G$304,"<40")*15) -> 0 | C18: =REPT("★",ROUND(B18/20,0))
A19: Depth | B19: =IFERROR(MAX(0,MIN(100,75+(AVERAGE('My Roster'!$F$16:$F$21)/AVERAGE('Auction Log'!$K$5:$K$304)-1)*50)),0) -> 0 | C19: =REPT("★",ROUND(B19/20,0))
A21: OVERALL | B21: =ROUND(B15*25%+B16*30%+B17*20%+B18*15%+B19*10%,0) -> 0 | C21: =IF(B5<>"COMPLETE","INCOMPLETE",IF(B21>=97,"A+",IF(B21>=93,"A",IF(B21>=90,"A-",IF(B21>=87,"B+",IF(B21>=83,"B",IF(B21>=80,"B-",IF(B21>=77,"C+",IF(B21>=73,"C",IF(B21>=70,"C-","D")))))))))) -> INCOMPLETE
A23: MY HAUL
A24: Slot | B24: Player | C24: Pos | D24: Price | E24: Hard | F24: Value | G24: Proj
A25: ='My Roster'!A7 -> QB | B25: =IF('My Roster'!B7="","",'My Roster'!B7) | C25: =IF(B25="","",'My Roster'!C7) | D25: =IF(B25="","",'My Roster'!D7) | E25: =IF(B25="","",'My Roster'!G7) | F25: =IF(B25="","",'My Roster'!H7) | G25: =IF(B25="","",'My Roster'!F7)
A26: ='My Roster'!A8 -> RB1 | B26: =IF('My Roster'!B8="","",'My Roster'!B8) | C26: =IF(B26="","",'My Roster'!C8) | D26: =IF(B26="","",'My Roster'!D8) | E26: =IF(B26="","",'My Roster'!G8) | F26: =IF(B26="","",'My Roster'!H8) | G26: =IF(B26="","",'My Roster'!F8)
A27: ='My Roster'!A9 -> RB2 | B27: =IF('My Roster'!B9="","",'My Roster'!B9) | C27: =IF(B27="","",'My Roster'!C9) | D27: =IF(B27="","",'My Roster'!D9) | E27: =IF(B27="","",'My Roster'!G9) | F27: =IF(B27="","",'My Roster'!H9) | G27: =IF(B27="","",'My Roster'!F9)
A28: ='My Roster'!A10 -> WR1 | B28: =IF('My Roster'!B10="","",'My Roster'!B10) | C28: =IF(B28="","",'My Roster'!C10) | D28: =IF(B28="","",'My Roster'!D10) | E28: =IF(B28="","",'My Roster'!G10) | F28: =IF(B28="","",'My Roster'!H10) | G28: =IF(B28="","",'My Roster'!F10)
A29: ='My Roster'!A11 -> WR2 | B29: =IF('My Roster'!B11="","",'My Roster'!B11) | C29: =IF(B29="","",'My Roster'!C11) | D29: =IF(B29="","",'My Roster'!D11) | E29: =IF(B29="","",'My Roster'!G11) | F29: =IF(B29="","",'My Roster'!H11) | G29: =IF(B29="","",'My Roster'!F11)
A30: ='My Roster'!A12 -> TE | B30: =IF('My Roster'!B12="","",'My Roster'!B12) | C30: =IF(B30="","",'My Roster'!C12) | D30: =IF(B30="","",'My Roster'!D12) | E30: =IF(B30="","",'My Roster'!G12) | F30: =IF(B30="","",'My Roster'!H12) | G30: =IF(B30="","",'My Roster'!F12)
A31: ='My Roster'!A13 -> FLEX | B31: =IF('My Roster'!B13="","",'My Roster'!B13) | C31: =IF(B31="","",'My Roster'!C13) | D31: =IF(B31="","",'My Roster'!D13) | E31: =IF(B31="","",'My Roster'!G13) | F31: =IF(B31="","",'My Roster'!H13) | G31: =IF(B31="","",'My Roster'!F13)
A32: ='My Roster'!A14 -> D/ST | B32: =IF('My Roster'!B14="","",'My Roster'!B14) | C32: =IF(B32="","",'My Roster'!C14) | D32: =IF(B32="","",'My Roster'!D14) | E32: =IF(B32="","",'My Roster'!G14) | F32: =IF(B32="","",'My Roster'!H14) | G32: =IF(B32="","",'My Roster'!F14)
A33: ='My Roster'!A15 -> K | B33: =IF('My Roster'!B15="","",'My Roster'!B15) | C33: =IF(B33="","",'My Roster'!C15) | D33: =IF(B33="","",'My Roster'!D15) | E33: =IF(B33="","",'My Roster'!G15) | F33: =IF(B33="","",'My Roster'!H15) | G33: =IF(B33="","",'My Roster'!F15)
A34: ='My Roster'!A16 -> BE1 | B34: =IF('My Roster'!B16="","",'My Roster'!B16) | C34: =IF(B34="","",'My Roster'!C16) | D34: =IF(B34="","",'My Roster'!D16) | E34: =IF(B34="","",'My Roster'!G16) | F34: =IF(B34="","",'My Roster'!H16) | G34: =IF(B34="","",'My Roster'!F16)
A35: ='My Roster'!A17 -> BE2 | B35: =IF('My Roster'!B17="","",'My Roster'!B17) | C35: =IF(B35="","",'My Roster'!C17) | D35: =IF(B35="","",'My Roster'!D17) | E35: =IF(B35="","",'My Roster'!G17) | F35: =IF(B35="","",'My Roster'!H17) | G35: =IF(B35="","",'My Roster'!F17)
A36: ='My Roster'!A18 -> BE3 | B36: =IF('My Roster'!B18="","",'My Roster'!B18) | C36: =IF(B36="","",'My Roster'!C18) | D36: =IF(B36="","",'My Roster'!D18) | E36: =IF(B36="","",'My Roster'!G18) | F36: =IF(B36="","",'My Roster'!H18) | G36: =IF(B36="","",'My Roster'!F18)
... A39: ='My Roster'!A21 -> BE6 | B39: =IF('My Roster'!B21="","",'My Roster'!B21) | C39: =IF(B39="","",'My Roster'!C21) | D39: =IF(B39="","",'My Roster'!D21) | E39: =IF(B39="","",'My Roster'!G21) | F39: =IF(B39="","",'My Roster'!H21) | G39: =IF(B39="","",'My Roster'!F21)
